Workbook

Sheet Cripto
A1: Janeiro | B1: 1
A2: Fevereiro | B2: 2
A3: Março | B3: 3
A4: Abril | B4: 4
A5: Maio | B5: 5
A6: Junho | B6: 6
A7: Julho | B7: 7
A8: Agosto | B8: 8
A9: Setembro | B9: 9
A10: Outubro | B10: 10
A11: Novembro | B11: 11
A12: Dezembro | B12: 12

Sheet Mensal
A1: Saldo da conta em 01 de Janeiro: | D1: 9523.69 | E1: =D1+E3+E103-E122 -> 9758.92 | F1: =E1+F3+F103-F122 -> 8085.88 | G1: =F1+G3+G103-G122 -> 9530.62 | H1: =G1+H3+H103-H122 -> 9591.21 | I1: =H1+I3+I103-I122 -> 10488.8 | J1: =I1+J3+J103-J122 -> 10968.92 | K1: =J1+K3+K103-K122 -> 11112.46 | L1: =K1+L3+L103-L122 -> 11772.46 | ... P1: =O1+P3+P103-P122 -> 11772.46
C2: Mensalidade | E2: Janeiro | F2: Fevereiro | G2: Março | H2: Abril | I2: Maio | J2: Junho | K2: Julho | L2: Agosto | M2: Setembro | N2: Outubro | O2: Novembro | P2: Dezembro | S2: =MONTH(TODAY())*20 -> 160
B3: Inativo | C3: Total mensal: | E3: =SUM(E4:E100) -> 320 | F3: =SUM(F4:F100) -> 1300 | G3: =SUM(G4:G100) -> 2280 | H3: =SUM(H4:H100) -> 660 | I3: =SUM(I4:I100) -> 920 | J3: =SUM(J4:J100) -> 1440 | K3: =SUM(K4:K100) -> 620 | L3: =SUM(L4:L100) -> 660 | ... P3: =SUM(P4:P100) -> 0 | Q3: PRIMEIRO PAGAMENTO DO ANO | R3: ATRASO | S3: GRÁFICO
B4: {=IFERROR(INDEX(#REF!,MATCH(C4,#REF!,0)),"")} | C4: =IFERROR(__xludf.DUMMYFUNCTION("QUERY('Cadastro de Sócios 2026'!A2:V170,""SELECT C, D WHERE U = TRUE"",1)"),"Angélica") -> Angélica | D4: =IFERROR(__xludf.DUMMYFUNCTION("""COMPUTED_VALUE"""),"Angélica Mateus") -> Angélica Mateus | E4: =SUMIFS(Pagamentos!$E:$E,Pagamentos!$F:$F,TRUE,Pagamentos!$C:$C,$C4,Pagamentos!$D:$D,E$2) -> 0 | F4: =SUMIFS(Pagamentos!$E:$E,Pagamentos!$F:$F,TRUE,Pagamentos!$C:$C,$C4,Pagamentos!$D:$D,F$2) -> 40 | G4: =SUMIFS(Pagamentos!$E:$E,Pagamentos!$F:$F,TRUE,Pagamentos!$C:$C,$C4,Pagamentos!$D:$D,G$2) -> 20 | H4: =SUMIFS(Pagamentos!$E:$E,Pagamentos!$F:$F,TRUE,Pagamentos!$C:$C,$C4,Pagamentos!$D:$D,H$2) -> 0 | I4: =SUMIFS(Pagamentos!$E:$E,Pagamentos!$F:$F,TRUE,Pagamentos!$C:$C,$C4,Pagamentos!$D:$D,I$2) -> 40 | J4: =SUMIFS(Pagamentos!$E:$E,Pagamentos!$F:$F,TRUE,Pagamentos!$C:$C,$C4,Pagamentos!$D:$D,J$2) -> 20 | K4: =SUMIFS(Pagamentos!$E:$E,Pagamentos!$F:$F,TRUE,Pagamentos!$C:$C,$C4,Pagamentos!$D:$D,K$2) -> 0 | L4: =SUMIFS(Pagamentos!$E:$E,Pagamentos!$F:$F,TRUE,Pagamentos!$C:$C,$C4,Pagamentos!$D:$D,L$2) -> 0 | ... P4: =SUMIFS(Pagamentos!$E:$E,Pagamentos!$F:$F,TRUE,Pagamentos!$C:$C,$C4,Pagamentos!$D:$D,P$2) -> 0 | Q4: 0 | R4: =IF(Q4="","",((SUM(E4:P4)-$S$2)/20)+Q4) -> -2 | S4: =IFERROR(__xludf.DUMMYFUNCTION("SPARKLINE(SUM(E4:P4),{""charttype"",""bar"";""max"",$S$2})"),"")
B5: {=IFERROR(INDEX(#REF!,MATCH(C5,#REF!,0)),"")} | C5: =IFERROR(__xludf.DUMMYFUNCTION("""COMPUTED_VALUE"""),"Antunes") -> Antunes | D5: =IFERROR(__xludf.DUMMYFUNCTION("""COMPUTED_VALUE"""),"Douglas Antunes") -> Douglas Antunes | E5: =SUMIFS(Pagamentos!$E:$E,Pagamentos!$F:$F,TRUE,Pagamentos!$C:$C,$C5,Pagamentos!$D:$D,E$2) -> 20 | F5: =SUMIFS(Pagamentos!$E:$E,Pagamentos!$F:$F,TRUE,Pagamentos!$C:$C,$C5,Pagamentos!$D:$D,F$2) -> 20 | G5: =SUMIFS(Pagamentos!$E:$E,Pagamentos!$F:$F,TRUE,Pagamentos!$C:$C,$C5,Pagamentos!$D:$D,G$2) -> 20 | H5: =SUMIFS(Pagamentos!$E:$E,Pagamentos!$F:$F,TRUE,Pagamentos!$C:$C,$C5,Pagamentos!$D:$D,H$2) -> 0 | I5: =SUMIFS(Pagamentos!$E:$E,Pagamentos!$F:$F,TRUE,Pagamentos!$C:$C,$C5,Pagamentos!$D:$D,I$2) -> 40 | J5: =SUMIFS(Pagamentos!$E:$E,Pagamentos!$F:$F,TRUE,Pagamentos!$C:$C,$C5,Pagamentos!$D:$D,J$2) -> 20 | K5: =SUMIFS(Pagamentos!$E:$E,Pagamentos!$F:$F,TRUE,Pagamentos!$C:$C,$C5,Pagamentos!$D:$D,K$2) -> 20 | L5: =SUMIFS(Pagamentos!$E:$E,Pagamentos!$F:$F,TRUE,Pagamentos!$C:$C,$C5,Pagamentos!$D:$D,L$2) -> 0 | ... P5: =SUMIFS(Pagamentos!$E:$E,Pagamentos!$F:$F,TRUE,Pagamentos!$C:$C,$C5,Pagamentos!$D:$D,P$2) -> 0 | Q5: 0 | R5: =IF(Q5="","",((SUM(E5:P5)-$S$2)/20)+Q5) -> -1 | S5: =IFERROR(__xludf.DUMMYFUNCTION("SPARKLINE(SUM(E5:P5),{""charttype"",""bar"";""max"",$S$2})"),"")
B6: {=IFERROR(INDEX(#REF!,MATCH(C6,#REF!,0)),"")} | C6: =IFERROR(__xludf.DUMMYFUNCTION("""COMPUTED_VALUE"""),"Augusto") -> Augusto | D6: =IFERROR(__xludf.DUMMYFUNCTION("""COMPUTED_VALUE"""),"Murilo Augusto Galdino De Souza") -> Murilo Augusto Galdino De Souza | E6: =SUMIFS(Pagamentos!$E:$E,Pagamentos!$F:$F,TRUE,Pagamentos!$C:$C,$C6,Pagamentos!$D:$D,E$2) -> 20 | F6: =SUMIFS(Pagamentos!$E:$E,Pagamentos!$F:$F,TRUE,Pagamentos!$C:$C,$C6,Pagamentos!$D:$D,F$2) -> 20 | G6: =SUMIFS(Pagamentos!$E:$E,Pagamentos!$F:$F,TRUE,Pagamentos!$C:$C,$C6,Pagamentos!$D:$D,G$2) -> 20 | H6: =SUMIFS(Pagamentos!$E:$E,Pagamentos!$F:$F,TRUE,Pagamentos!$C:$C,$C6,Pagamentos!$D:$D,H$2) -> 20 | I6: =SUMIFS(Pagamentos!$E:$E,Pagamentos!$F:$F,TRUE,Pagamentos!$C:$C,$C6,Pagamentos!$D:$D,I$2) -> 20 | J6: =SUMIFS(Pagamentos!$E:$E,Pagamentos!$F:$F,TRUE,Pagamentos!$C:$C,$C6,Pagamentos!$D:$D,J$2) -> 20 | K6: =SUMIFS(Pagamentos!$E:$E,Pagamentos!$F:$F,TRUE,Pagamentos!$C:$C,$C6,Pagamentos!$D:$D,K$2) -> 0 | L6: =SUMIFS(Pagamentos!$E:$E,Pagamentos!$F:$F,TRUE,Pagamentos!$C:$C,$C6,Pagamentos!$D:$D,L$2) -> 20 | ... P6: =SUMIFS(Pagamentos!$E:$E,Pagamentos!$F:$F,TRUE,Pagamentos!$C:$C,$C6,Pagamentos!$D:$D,P$2) -> 0 | Q6: 0 | R6: =IF(Q6="","",((SUM(E6:P6)-$S$2)/20)+Q6) -> -1 | S6: =IFERROR(__xludf.DUMMYFUNCTION("SPARKLINE(SUM(E6:P6),{""charttype"",""bar"";""max"",$S$2})"),"")
B7: {=IFERROR(INDEX(#REF!,MATCH(C7,#REF!,0)),"")} | C7: =IFERROR(__xludf.DUMMYFUNCTION("""COMPUTED_VALUE"""),"Andreia") -> Andreia | D7: =IFERROR(__xludf.DUMMYFUNCTION("""COMPUTED_VALUE"""),"Andreia de Fátima Machado ") -> Andreia de Fátima Machado | E7: =SUMIFS(Pagamentos!$E:$E,Pagamentos!$F:$F,TRUE,Pagamentos!$C:$C,$C7,Pagamentos!$D:$D,E$2) -> 0 | F7: =SUMIFS(Pagamentos!$E:$E,Pagamentos!$F:$F,TRUE,Pagamentos!$C:$C,$C7,Pagamentos!$D:$D,F$2) -> 0 | G7: =SUMIFS(Pagamentos!$E:$E,Pagamentos!$F:$F,TRUE,Pagamentos!$C:$C,$C7,Pagamentos!$D:$D,G$2) -> 80 | H7: =SUMIFS(Pagamentos!$E:$E,Pagamentos!$F:$F,TRUE,Pagamentos!$C:$C,$C7,Pagamentos!$D:$D,H$2) -> 0 | I7: =SUMIFS(Pagamentos!$E:$E,Pagamentos!$F:$F,TRUE,Pagamentos!$C:$C,$C7,Pagamentos!$D:$D,I$2) -> 0 | J7: =SUMIFS(Pagamentos!$E:$E,Pagamentos!$F:$F,TRUE,Pagamentos!$C:$C,$C7,Pagamentos!$D:$D,J$2) -> 0 | K7: =SUMIFS(Pagamentos!$E:$E,Pagamentos!$F:$F,TRUE,Pagamentos!$C:$C,$C7,Pagamentos!$D:$D,K$2) -> 0 | L7: =SUMIFS(Pagamentos!$E:$E,Pagamentos!$F:$F,TRUE,Pagamentos!$C:$C,$C7,Pagamentos!$D:$D,L$2) -> 80 | ... P7: =SUMIFS(Pagamentos!$E:$E,Pagamentos!$F:$F,TRUE,Pagamentos!$C:$C,$C7,Pagamentos!$D:$D,P$2) -> 0 | Q7: 0 | R7: =IF(Q7="","",((SUM(E7:P7)-$S$2)/20)+Q7) -> 0 | S7: =IFERROR(__xludf.DUMMYFUNCTION("SPARKLINE(SUM(E7:P7),{""charttype"",""bar"";""max"",$S$2})"),"")
B8: {=IFERROR(INDEX(#REF!,MATCH(C8,#REF!,0)),"")} | C8: =IFERROR(__xludf.DUMMYFUNCTION("""COMPUTED_VALUE"""),"Bento") -> Bento | D8: =IFERROR(__xludf.DUMMYFUNCTION("""COMPUTED_VALUE"""),"Daniel Bento") -> Daniel Bento | E8: =SUMIFS(Pagamentos!$E:$E,Pagamentos!$F:$F,TRUE,Pagamentos!$C:$C,$C8,Pagamentos!$D:$D,E$2) -> 0 | F8: =SUMIFS(Pagamentos!$E:$E,Pagamentos!$F:$F,TRUE,Pagamentos!$C:$C,$C8,Pagamentos!$D:$D,F$2) -> 0 | G8: =SUMIFS(Pagamentos!$E:$E,Pagamentos!$F:$F,TRUE,Pagamentos!$C:$C,$C8,Pagamentos!$D:$D,G$2) -> 20 | H8: =SUMIFS(Pagamentos!$E:$E,Pagamentos!$F:$F,TRUE,Pagamentos!$C:$C,$C8,Pagamentos!$D:$D,H$2) -> 0 | I8: =SUMIFS(Pagamentos!$E:$E,Pagamentos!$F:$F,TRUE,Pagamentos!$C:$C,$C8,Pagamentos!$D:$D,I$2) -> 20 | J8: =SUMIFS(Pagamentos!$E:$E,Pagamentos!$F:$F,TRUE,Pagamentos!$C:$C,$C8,Pagamentos!$D:$D,J$2) -> 20 | K8: =SUMIFS(Pagamentos!$E:$E,Pagamentos!$F:$F,TRUE,Pagamentos!$C:$C,$C8,Pagamentos!$D:$D,K$2) -> 20 | L8: =SUMIFS(Pagamentos!$E:$E,Pagamentos!$F:$F,TRUE,Pagamentos!$C:$C,$C8,Pagamentos!$D:$D,L$2) -> 0 | ... P8: =SUMIFS(Pagamentos!$E:$E,Pagamentos!$F:$F,TRUE,Pagamentos!$C:$C,$C8,Pagamentos!$D:$D,P$2) -> 0 | Q8: 2 | R8: =IF(Q8="","",((SUM(E8:P8)-$S$2)/20)+Q8) -> -2 | S8: =IFERROR(__xludf.DUMMYFUNCTION("SPARKLINE(SUM(E8:P8),{""charttype"",""bar"";""max"",$S$2})"),"")
B9: {=IFERROR(INDEX(#REF!,MATCH(C9,#REF!,0)),"")} | C9: =IFERROR(__xludf.DUMMYFUNCTION("""COMPUTED_VALUE"""),"Binhoti") -> Binhoti | D9: =IFERROR(__xludf.DUMMYFUNCTION("""COMPUTED_VALUE"""),"Tiago Binhoti") -> Tiago Binhoti | E9: =SUMIFS(Pagamentos!$E:$E,Pagamentos!$F:$F,TRUE,Pagamentos!$C:$C,$C9,Pagamentos!$D:$D,E$2) -> 0 | F9: =SUMIFS(Pagamentos!$E:$E,Pagamentos!$F:$F,TRUE,Pagamentos!$C:$C,$C9,Pagamentos!$D:$D,F$2) -> 120 | G9: =SUMIFS(Pagamentos!$E:$E,Pagamentos!$F:$F,TRUE,Pagamentos!$C:$C,$C9,Pagamentos!$D:$D,G$2) -> 0 | H9: =SUMIFS(Pagamentos!$E:$E,Pagamentos!$F:$F,TRUE,Pagamentos!$C:$C,$C9,Pagamentos!$D:$D,H$2) -> 0 | I9: =SUMIFS(Pagamentos!$E:$E,Pagamentos!$F:$F,TRUE,Pagamentos!$C:$C,$C9,Pagamentos!$D:$D,I$2) -> 0 | J9: =SUMIFS(Pagamentos!$E:$E,Pagamentos!$F:$F,TRUE,Pagamentos!$C:$C,$C9,Pagamentos!$D:$D,J$2) -> 0 | K9: =SUMIFS(Pagamentos!$E:$E,Pagamentos!$F:$F,TRUE,Pagamentos!$C:$C,$C9,Pagamentos!$D:$D,K$2) -> 0 | L9: =SUMIFS(Pagamentos!$E:$E,Pagamentos!$F:$F,TRUE,Pagamentos!$C:$C,$C9,Pagamentos!$D:$D,L$2) -> 120 | ... P9: =SUMIFS(Pagamentos!$E:$E,Pagamentos!$F:$F,TRUE,Pagamentos!$C:$C,$C9,Pagamentos!$D:$D,P$2) -> 0 | Q9: 1 | R9: =IF(Q9="","",((SUM(E9:P9)-$S$2)/20)+Q9) -> 5 | S9: =IFERROR(__xludf.DUMMYFUNCTION("SPARKLINE(SUM(E9:P9),{""charttype"",""bar"";""max"",$S$2})"),"")
B10: {=IFERROR(INDEX(#REF!,MATCH(C10,#REF!,0)),"")} | C10: =IFERROR(__xludf.DUMMYFUNCTION("""COMPUTED_VALUE"""),"Boiko") -> Boiko | D10: =IFERROR(__xludf.DUMMYFUNCTION("""COMPUTED_VALUE"""),"Emerson Roberto Boiko") -> Emerson Roberto Boiko | E10: =SUMIFS(Pagamentos!$E:$E,Pagamentos!$F:$F,TRUE,Pagamentos!$C:$C,$C10,Pagamentos!$D:$D,E$2) -> 0 | F10: =SUMIFS(Pagamentos!$E:$E,Pagamentos!$F:$F,TRUE,Pagamentos!$C:$C,$C10,Pagamentos!$D:$D,F$2) -> 0 | G10: =SUMIFS(Pagamentos!$E:$E,Pagamentos!$F:$F,TRUE,Pagamentos!$C:$C,$C10,Pagamentos!$D:$D,G$2) -> 100 | H10: =SUMIFS(Pagamentos!$E:$E,Pagamentos!$F:$F,TRUE,Pagamentos!$C:$C,$C10,Pagamentos!$D:$D,H$2) -> 0 | I10: =SUMIFS(Pagamentos!$E:$E,Pagamentos!$F:$F,TRUE,Pagamentos!$C:$C,$C10,Pagamentos!$D:$D,I$2) -> 0 | J10: =SUMIFS(Pagamentos!$E:$E,Pagamentos!$F:$F,TRUE,Pagamentos!$C:$C,$C10,Pagamentos!$D:$D,J$2) -> 60 | K10: =SUMIFS(Pagamentos!$E:$E,Pagamentos!$F:$F,TRUE,Pagamentos!$C:$C,$C10,Pagamentos!$D:$D,K$2) -> 0 | L10: =SUMIFS(Pagamentos!$E:$E,Pagamentos!$F:$F,TRUE,Pagamentos!$C:$C,$C10,Pagamentos!$D:$D,L$2) -> 0 | ... P10: =SUMIFS(Pagamentos!$E:$E,Pagamentos!$F:$F,TRUE,Pagamentos!$C:$C,$C10,Pagamentos!$D:$D,P$2) -> 0 | Q10: -2 | R10: =IF(Q10="","",((SUM(E10:P10)-$S$2)/20)+Q10) -> -2 | S10: =IFERROR(__xludf.DUMMYFUNCTION("SPARKLINE(SUM(E10:P10),{""charttype"",""bar"";""max"",$S$2})"),"")
B11: {=IFERROR(INDEX(#REF!,MATCH(C11,#REF!,0)),"")} | C11: =IFERROR(__xludf.DUMMYFUNCTION("""COMPUTED_VALUE"""),"Camila") -> Camila | D11: =IFERROR(__xludf.DUMMYFUNCTION("""COMPUTED_VALUE"""),"Camila Coelho Soares") -> Camila Coelho Soares | E11: =SUMIFS(Pagamentos!$E:$E,Pagamentos!$F:$F,TRUE,Pagamentos!$C:$C,$C11,Pagamentos!$D:$D,E$2) -> 20 | F11: =SUMIFS(Pagamentos!$E:$E,Pagamentos!$F:$F,TRUE,Pagamentos!$C:$C,$C11,Pagamentos!$D:$D,F$2) -> 20 | G11: =SUMIFS(Pagamentos!$E:$E,Pagamentos!$F:$F,TRUE,Pagamentos!$C:$C,$C11,Pagamentos!$D:$D,G$2) -> 20 | H11: =SUMIFS(Pagamentos!$E:$E,Pagamentos!$F:$F,TRUE,Pagamentos!$C:$C,$C11,Pagamentos!$D:$D,H$2) -> 20 | I11: =SUMIFS(Pagamentos!$E:$E,Pagamentos!$F:$F,TRUE,Pagamentos!$C:$C,$C11,Pagamentos!$D:$D,I$2) -> 20 | J11: =SUMIFS(Pagamentos!$E:$E,Pagamentos!$F:$F,TRUE,Pagamentos!$C:$C,$C11,Pagamentos!$D:$D,J$2) -> 20 | K11: =SUMIFS(Pagamentos!$E:$E,Pagamentos!$F:$F,TRUE,Pagamentos!$C:$C,$C11,Pagamentos!$D:$D,K$2) -> 20 | L11: =SUMIFS(Pagamentos!$E:$E,Pagamentos!$F:$F,TRUE,Pagamentos!$C:$C,$C11,Pagamentos!$D:$D,L$2) -> 0 | ... P11: =SUMIFS(Pagamentos!$E:$E,Pagamentos!$F:$F,TRUE,Pagamentos!$C:$C,$C11,Pagamentos!$D:$D,P$2) -> 0 | Q11: 0 | R11: =IF(Q11="","",((SUM(E11:P11)-$S$2)/20)+Q11) -> -1 | S11: =IFERROR(__xludf.DUMMYFUNCTION("SPARKLINE(SUM(E11:P11),{""charttype"",""bar"";""max"",$S$2})"),"")
B12: {=IFERROR(INDEX(#REF!,MATCH(C12,#REF!,0)),"")} | C12: =IFERROR(__xludf.DUMMYFUNCTION("""COMPUTED_VALUE"""),"Coelho") -> Coelho | D12: =IFERROR(__xludf.DUMMYFUNCTION("""COMPUTED_VALUE"""),"Ricardo Augusto Coelho") -> Ricardo Augusto Coelho | E12: =SUMIFS(Pagamentos!$E:$E,Pagamentos!$F:$F,TRUE,Pagamentos!$C:$C,$C12,Pagamentos!$D:$D,E$2) -> 0 | F12: =SUMIFS(Pagamentos!$E:$E,Pagamentos!$F:$F,TRUE,Pagamentos!$C:$C,$C12,Pagamentos!$D:$D,F$2) -> 0 | G12: =SUMIFS(Pagamentos!$E:$E,Pagamentos!$F:$F,TRUE,Pagamentos!$C:$C,$C12,Pagamentos!$D:$D,G$2) -> 60 | H12: =SUMIFS(Pagamentos!$E:$E,Pagamentos!$F:$F,TRUE,Pagamentos!$C:$C,$C12,Pagamentos!$D:$D,H$2) -> 60 | I12: =SUMIFS(Pagamentos!$E:$E,Pagamentos!$F:$F,TRUE,Pagamentos!$C:$C,$C12,Pagamentos!$D:$D,I$2) -> 0 | J12: =SUMIFS(Pagamentos!$E:$E,Pagamentos!$F:$F,TRUE,Pagamentos!$C:$C,$C12,Pagamentos!$D:$D,J$2) -> 0 | K12: =SUMIFS(Pagamentos!$E:$E,Pagamentos!$F:$F,TRUE,Pagamentos!$C:$C,$C12,Pagamentos!$D:$D,K$2) -> 0 | L12: =SUMIFS(Pagamentos!$E:$E,Pagamentos!$F:$F,TRUE,Pagamentos!$C:$C,$C12,Pagamentos!$D:$D,L$2) -> 80 | ... P12: =SUMIFS(Pagamentos!$E:$E,Pagamentos!$F:$F,TRUE,Pagamentos!$C:$C,$C12,Pagamentos!$D:$D,P$2) -> 0 | Q12: 0 | R12: =IF(Q12="","",((SUM(E12:P12)-$S$2)/20)+Q12) -> 2 | S12: =IFERROR(__xludf.DUMMYFUNCTION("SPARKLINE(SUM(E12:P12),{""charttype"",""bar"";""max"",$S$2})"),"")
B13: {=IFERROR(INDEX(#REF!,MATCH(C13,#REF!,0)),"")} | C13: =IFERROR(__xludf.DUMMYFUNCTION("""COMPUTED_VALUE"""),"Da Silva") -> Da Silva | D13: =IFERROR(__xludf.DUMMYFUNCTION("""COMPUTED_VALUE"""),"Alex Sandro Batista da Silva") -> Alex Sandro Batista da Silva | E13: =SUMIFS(Pagamentos!$E:$E,Pagamentos!$F:$F,TRUE,Pagamentos!$C:$C,$C13,Pagamentos!$D:$D,E$2) -> 0 | F13: =SUMIFS(Pagamentos!$E:$E,Pagamentos!$F:$F,TRUE,Pagamentos!$C:$C,$C13,Pagamentos!$D:$D,F$2) -> 0 | G13: =SUMIFS(Pagamentos!$E:$E,Pagamentos!$F:$F,TRUE,Pagamentos!$C:$C,$C13,Pagamentos!$D:$D,G$2) -> 0 | H13: =SUMIFS(Pagamentos!$E:$E,Pagamentos!$F:$F,TRUE,Pagamentos!$C:$C,$C13,Pagamentos!$D:$D,H$2) -> 0 | I13: =SUMIFS(Pagamentos!$E:$E,Pagamentos!$F:$F,TRUE,Pagamentos!$C:$C,$C13,Pagamentos!$D:$D,I$2) -> 0 | J13: =SUMIFS(Pagamentos!$E:$E,Pagamentos!$F:$F,TRUE,Pagamentos!$C:$C,$C13,Pagamentos!$D:$D,J$2) -> 0 | K13: =SUMIFS(Pagamentos!$E:$E,Pagamentos!$F:$F,TRUE,Pagamentos!$C:$C,$C13,Pagamentos!$D:$D,K$2) -> 0 | L13: =SUMIFS(Pagamentos!$E:$E,Pagamentos!$F:$F,TRUE,Pagamentos!$C:$C,$C13,Pagamentos!$D:$D,L$2) -> 0 | ... P13: =SUMIFS(Pagamentos!$E:$E,Pagamentos!$F:$F,TRUE,Pagamentos!$C:$C,$C13,Pagamentos!$D:$D,P$2) -> 0 | Q13: 12 | R13: =IF(Q13="","",((SUM(E13:P13)-$S$2)/20)+Q13) -> 4 | S13: =IFERROR(__xludf.DUMMYFUNCTION("SPARKLINE(SUM(E13:P13),{""charttype"",""bar"";""max"",$S$2})"),"")
B14: {=IFERROR(INDEX(#REF!,MATCH(C14,#REF!,0)),"")} | C14: =IFERROR(__xludf.DUMMYFUNCTION("""COMPUTED_VALUE"""),"Barros") -> Barros | D14: =IFERROR(__xludf.DUMMYFUNCTION("""COMPUTED_VALUE"""),"Michel da Silveira Barros ") -> Michel da Silveira Barros | E14: =SUMIFS(Pagamentos!$E:$E,Pagamentos!$F:$F,TRUE,Pagamentos!$C:$C,$C14,Pagamentos!$D:$D,E$2) -> 0 | F14: =SUMIFS(Pagamentos!$E:$E,Pagamentos!$F:$F,TRUE,Pagamentos!$C:$C,$C14,Pagamentos!$D:$D,F$2) -> 20 | G14: =SUMIFS(Pagamentos!$E:$E,Pagamentos!$F:$F,TRUE,Pagamentos!$C:$C,$C14,Pagamentos!$D:$D,G$2) -> 40 | H14: =SUMIFS(Pagamentos!$E:$E,Pagamentos!$F:$F,TRUE,Pagamentos!$C:$C,$C14,Pagamentos!$D:$D,H$2) -> 0 | I14: =SUMIFS(Pagamentos!$E:$E,Pagamentos!$F:$F,TRUE,Pagamentos!$C:$C,$C14,Pagamentos!$D:$D,I$2) -> 0 | J14: =SUMIFS(Pagamentos!$E:$E,Pagamentos!$F:$F,TRUE,Pagamentos!$C:$C,$C14,Pagamentos!$D:$D,J$2) -> 60 | K14: =SUMIFS(Pagamentos!$E:$E,Pagamentos!$F:$F,TRUE,Pagamentos!$C:$C,$C14,Pagamentos!$D:$D,K$2) -> 0 | L14: =SUMIFS(Pagamentos!$E:$E,Pagamentos!$F:$F,TRUE,Pagamentos!$C:$C,$C14,Pagamentos!$D:$D,L$2) -> 0 | ... P14: =SUMIFS(Pagamentos!$E:$E,Pagamentos!$F:$F,TRUE,Pagamentos!$C:$C,$C14,Pagamentos!$D:$D,P$2) -> 0 | Q14: 0 | R14: =IF(Q14="","",((SUM(E14:P14)-$S$2)/20)+Q14) -> -2 | S14: =IFERROR(__xludf.DUMMYFUNCTION("SPARKLINE(SUM(E14:P14),{""charttype"",""bar"";""max"",$S$2})"),"")
B15: {=IFERROR(INDEX(#REF!,MATCH(C15,#REF!,0)),"")} | C15: =IFERROR(__xludf.DUMMYFUNCTION("""COMPUTED_VALUE"""),"Deny") -> Deny | D15: =IFERROR(__xludf.DUMMYFUNCTION("""COMPUTED_VALUE"""),"Deny Anderson Azevedo ") -> Deny Anderson Azevedo | E15: =SUMIFS(Pagamentos!$E:$E,Pagamentos!$F:$F,TRUE,Pagamentos!$C:$C,$C15,Pagamentos!$D:$D,E$2) -> 0 | F15: =SUMIFS(Pagamentos!$E:$E,Pagamentos!$F:$F,TRUE,Pagamentos!$C:$C,$C15,Pagamentos!$D:$D,F$2) -> 0 | G15: =SUMIFS(Pagamentos!$E:$E,Pagamentos!$F:$F,TRUE,Pagamentos!$C:$C,$C15,Pagamentos!$D:$D,G$2) -> 0 | H15: =SUMIFS(Pagamentos!$E:$E,Pagamentos!$F:$F,TRUE,Pagamentos!$C:$C,$C15,Pagamentos!$D:$D,H$2) -> 0 | I15: =SUMIFS(Pagamentos!$E:$E,Pagamentos!$F:$F,TRUE,Pagamentos!$C:$C,$C15,Pagamentos!$D:$D,I$2) -> 0 | J15: =SUMIFS(Pagamentos!$E:$E,Pagamentos!$F:$F,TRUE,Pagamentos!$C:$C,$C15,Pagamentos!$D:$D,J$2) -> 60 | K15: =SUMIFS(Pagamentos!$E:$E,Pagamentos!$F:$F,TRUE,Pagamentos!$C:$C,$C15,Pagamentos!$D:$D,K$2) -> 0 | L15: =SUMIFS(Pagamentos!$E:$E,Pagamentos!$F:$F,TRUE,Pagamentos!$C:$C,$C15,Pagamentos!$D:$D,L$2) -> 0 | ... P15: =SUMIFS(Pagamentos!$E:$E,Pagamentos!$F:$F,TRUE,Pagamentos!$C:$C,$C15,Pagamentos!$D:$D,P$2) -> 0 | Q15: 3 | R15: =IF(Q15="","",((SUM(E15:P15)-$S$2)/20)+Q15) -> -2 | S15: =IFERROR(__xludf.DUMMYFUNCTION("SPARKLINE(SUM(E15:P15),{""charttype"",""bar"";""max"",$S$2})"),"")
B16: {=IFERROR(INDEX(#REF!,MATCH(C16,#REF!,0)),"")} | C16: =IFERROR(__xludf.DUMMYFUNCTION("""COMPUTED_VALUE"""),"Eder") -> Eder | D16: =IFERROR(__xludf.DUMMYFUNCTION("""COMPUTED_VALUE"""),"Eder Alison Da Silva") -> Eder Alison Da Silva | E16: =SUMIFS(Pagamentos!$E:$E,Pagamentos!$F:$F,TRUE,Pagamentos!$C:$C,$C16,Pagamentos!$D:$D,E$2) -> 0 | F16: =SUMIFS(Pagamentos!$E:$E,Pagamentos!$F:$F,TRUE,Pagamentos!$C:$C,$C16,Pagamentos!$D:$D,F$2) -> 0 | G16: =SUMIFS(Pagamentos!$E:$E,Pagamentos!$F:$F,TRUE,Pagamentos!$C:$C,$C16,Pagamentos!$D:$D,G$2) -> 0 | H16: =SUMIFS(Pagamentos!$E:$E,Pagamentos!$F:$F,TRUE,Pagamentos!$C:$C,$C16,Pagamentos!$D:$D,H$2) -> 100 | I16: =SUMIFS(Pagamentos!$E:$E,Pagamentos!$F:$F,TRUE,Pagamentos!$C:$C,$C16,Pagamentos!$D:$D,I$2) -> 0 | J16: =SUMIFS(Pagamentos!$E:$E,Pagamentos!$F:$F,TRUE,Pagamentos!$C:$C,$C16,Pagamentos!$D:$D,J$2) -> 40 | K16: =SUMIFS(Pagamentos!$E:$E,Pagamentos!$F:$F,TRUE,Pagamentos!$C:$C,$C16,Pagamentos!$D:$D,K$2) -> 0 | L16: =SUMIFS(Pagamentos!$E:$E,Pagamentos!$F:$F,TRUE,Pagamentos!$C:$C,$C16,Pagamentos!$D:$D,L$2) -> 0 | ... P16: =SUMIFS(Pagamentos!$E:$E,Pagamentos!$F:$F,TRUE,Pagamentos!$C:$C,$C16,Pagamentos!$D:$D,P$2) -> 0 | Q16: -1 | R16: =IF(Q16="","",((SUM(E16:P16)-$S$2)/20)+Q16) -> -2 | S16: =IFERROR(__xludf.DUMMYFUNCTION("SPARKLINE(SUM(E16:P16),{""charttype"",""bar"";""max"",$S$2})"),"")
B17: {=IFERROR(INDEX(#REF!,MATCH(C17,#REF!,0)),"")} | C17: =IFERROR(__xludf.DUMMYFUNCTION("""COMPUTED_VALUE"""),"Elaine") -> Elaine | D17: =IFERROR(__xludf.DUMMYFUNCTION("""COMPUTED_VALUE"""),"Elaine Conrado Bittencourt ") -> Elaine Conrado Bittencourt | E17: =SUMIFS(Pagamentos!$E:$E,Pagamentos!$F:$F,TRUE,Pagamentos!$C:$C,$C17,Pagamentos!$D:$D,E$2) -> 0 | F17: =SUMIFS(Pagamentos!$E:$E,Pagamentos!$F:$F,TRUE,Pagamentos!$C:$C,$C17,Pagamentos!$D:$D,F$2) -> 40 | G17: =SUMIFS(Pagamentos!$E:$E,Pagamentos!$F:$F,TRUE,Pagamentos!$C:$C,$C17,Pagamentos!$D:$D,G$2) -> 20 | H17: =SUMIFS(Pagamentos!$E:$E,Pagamentos!$F:$F,TRUE,Pagamentos!$C:$C,$C17,Pagamentos!$D:$D,H$2) -> 0 | I17: =SUMIFS(Pagamentos!$E:$E,Pagamentos!$F:$F,TRUE,Pagamentos!$C:$C,$C17,Pagamentos!$D:$D,I$2) -> 20 | J17: =SUMIFS(Pagamentos!$E:$E,Pagamentos!$F:$F,TRUE,Pagamentos!$C:$C,$C17,Pagamentos!$D:$D,J$2) -> 60 | K17: =SUMIFS(Pagamentos!$E:$E,Pagamentos!$F:$F,TRUE,Pagamentos!$C:$C,$C17,Pagamentos!$D:$D,K$2) -> 0 | L17: =SUMIFS(Pagamentos!$E:$E,Pagamentos!$F:$F,TRUE,Pagamentos!$C:$C,$C17,Pagamentos!$D:$D,L$2) -> 0 | ... P17: =SUMIFS(Pagamentos!$E:$E,Pagamentos!$F:$F,TRUE,Pagamentos!$C:$C,$C17,Pagamentos!$D:$D,P$2) -> 0 | Q17: 0 | R17: =IF(Q17="","",((SUM(E17:P17)-$S$2)/20)+Q17) -> -1 | S17: =IFERROR(__xludf.DUMMYFUNCTION("SPARKLINE(SUM(E17:P17),{""charttype"",""bar"";""max"",$S$2})"),"")
B18: {=IFERROR(INDEX(#REF!,MATCH(C18,#REF!,0)),"")} | C18: =IFERROR(__xludf.DUMMYFUNCTION("""COMPUTED_VALUE"""),"Fabiana") -> Fabiana | D18: =IFERROR(__xludf.DUMMYFUNCTION("""COMPUTED_VALUE"""),"Fabiana Oro Cericato Costa") -> Fabiana Oro Cericato Costa | E18: =SUMIFS(Pagamentos!$E:$E,Pagamentos!$F:$F,TRUE,Pagamentos!$C:$C,$C18,Pagamentos!$D:$D,E$2) -> 0 | F18: =SUMIFS(Pagamentos!$E:$E,Pagamentos!$F:$F,TRUE,Pagamentos!$C:$C,$C18,Pagamentos!$D:$D,F$2) -> 200 | G18: =SUMIFS(Pagamentos!$E:$E,Pagamentos!$F:$F,TRUE,Pagamentos!$C:$C,$C18,Pagamentos!$D:$D,G$2) -> 0 | H18: =SUMIFS(Pagamentos!$E:$E,Pagamentos!$F:$F,TRUE,Pagamentos!$C:$C,$C18,Pagamentos!$D:$D,H$2) -> 0 | I18: =SUMIFS(Pagamentos!$E:$E,Pagamentos!$F:$F,TRUE,Pagamentos!$C:$C,$C18,Pagamentos!$D:$D,I$2) -> 0 | J18: =SUMIFS(Pagamentos!$E:$E,Pagamentos!$F:$F,TRUE,Pagamentos!$C:$C,$C18,Pagamentos!$D:$D,J$2) -> 0 | K18: =SUMIFS(Pagamentos!$E:$E,Pagamentos!$F:$F,TRUE,Pagamentos!$C:$C,$C18,Pagamentos!$D:$D,K$2) -> 0 | L18: =SUMIFS(Pagamentos!$E:$E,Pagamentos!$F:$F,TRUE,Pagamentos!$C:$C,$C18,Pagamentos!$D:$D,L$2) -> 0 | ... P18: =SUMIFS(Pagamentos!$E:$E,Pagamentos!$F:$F,TRUE,Pagamentos!$C:$C,$C18,Pagamentos!$D:$D,P$2) -> 0 | Q18: 1 | R18: =IF(Q18="","",((SUM(E18:P18)-$S$2)/20)+Q18) -> 3 | S18: =IFERROR(__xludf.DUMMYFUNCTION("SPARKLINE(SUM(E18:P18),{""charttype"",""bar"";""max"",$S$2})"),"")
B19: {=IFERROR(INDEX(#REF!,MATCH(C19,#REF!,0)),"")} | C19: =IFERROR(__xludf.DUMMYFUNCTION("""COMPUTED_VALUE"""),"Gabriel") -> Gabriel | D19: =IFERROR(__xludf.DUMMYFUNCTION("""COMPUTED_VALUE"""),"Gabriel Francisco Farias da Silva") -> Gabriel Francisco Farias da Silva | E19: =SUMIFS(Pagamentos!$E:$E,Pagamentos!$F:$F,TRUE,Pagamentos!$C:$C,$C19,Pagamentos!$D:$D,E$2) -> 0 | F19: =SUMIFS(Pagamentos!$E:$E,Pagamentos!$F:$F,TRUE,Pagamentos!$C:$C,$C19,Pagamentos!$D:$D,F$2) -> 40 | G19: =SUMIFS(Pagamentos!$E:$E,Pagamentos!$F:$F,TRUE,Pagamentos!$C:$C,$C19,Pagamentos!$D:$D,G$2) -> 20 | H19: =SUMIFS(Pagamentos!$E:$E,Pagamentos!$F:$F,TRUE,Pagamentos!$C:$C,$C19,Pagamentos!$D:$D,H$2) -> 0 | I19: =SUMIFS(Pagamentos!$E:$E,Pagamentos!$F:$F,TRUE,Pagamentos!$C:$C,$C19,Pagamentos!$D:$D,I$2) -> 0 | J19: =SUMIFS(Pagamentos!$E:$E,Pagamentos!$F:$F,TRUE,Pagamentos!$C:$C,$C19,Pagamentos!$D:$D,J$2) -> 60 | K19: =SUMIFS(Pagamentos!$E:$E,Pagamentos!$F:$F,TRUE,Pagamentos!$C:$C,$C19,Pagamentos!$D:$D,K$2) -> 0 | L19: =SUMIFS(Pagamentos!$E:$E,Pagamentos!$F:$F,TRUE,Pagamentos!$C:$C,$C19,Pagamentos!$D:$D,L$2) -> 40 | ... P19: =SUMIFS(Pagamentos!$E:$E,Pagamentos!$F:$F,TRUE,Pagamentos!$C:$C,$C19,Pagamentos!$D:$D,P$2) -> 0 | Q19: 0 | R19: =IF(Q19="","",((SUM(E19:P19)-$S$2)/20)+Q19) -> 0 | S19: =IFERROR(__xludf.DUMMYFUNCTION("SPARKLINE(SUM(E19:P19),{""charttype"",""bar"";""max"",$S$2})"),"")
B20: {=IFERROR(INDEX(#REF!,MATCH(C20,#REF!,0)),"")} | C20: =IFERROR(__xludf.DUMMYFUNCTION("""COMPUTED_VALUE"""),"Henkes") -> Henkes | D20: =IFERROR(__xludf.DUMMYFUNCTION("""COMPUTED_VALUE"""),"Marcia Aparecida Henkes") -> Marcia Aparecida Henkes | E20: =SUMIFS(Pagamentos!$E:$E,Pagamentos!$F:$F,TRUE,Pagamentos!$C:$C,$C20,Pagamentos!$D:$D,E$2) -> 0 | F20: =SUMIFS(Pagamentos!$E:$E,Pagamentos!$F:$F,TRUE,Pagamentos!$C:$C,$C20,Pagamentos!$D:$D,F$2) -> 0 | G20: =SUMIFS(Pagamentos!$E:$E,Pagamentos!$F:$F,TRUE,Pagamentos!$C:$C,$C20,Pagamentos!$D:$D,G$2) -> 100 | H20: =SUMIFS(Pagamentos!$E:$E,Pagamentos!$F:$F,TRUE,Pagamentos!$C:$C,$C20,Pagamentos!$D:$D,H$2) -> 0 | I20: =SUMIFS(Pagamentos!$E:$E,Pagamentos!$F:$F,TRUE,Pagamentos!$C:$C,$C20,Pagamentos!$D:$D,I$2) -> 0 | J20: =SUMIFS(Pagamentos!$E:$E,Pagamentos!$F:$F,TRUE,Pagamentos!$C:$C,$C20,Pagamentos!$D:$D,J$2) -> 60 | K20: =SUMIFS(Pagamentos!$E:$E,Pagamentos!$F:$F,TRUE,Pagamentos!$C:$C,$C20,Pagamentos!$D:$D,K$2) -> 0 | L20: =SUMIFS(Pagamentos!$E:$E,Pagamentos!$F:$F,TRUE,Pagamentos!$C:$C,$C20,Pagamentos!$D:$D,L$2) -> 0 | ... P20: =SUMIFS(Pagamentos!$E:$E,Pagamentos!$F:$F,TRUE,Pagamentos!$C:$C,$C20,Pagamentos!$D:$D,P$2) -> 0 | Q20: -2 | R20: =IF(Q20="","",((SUM(E20:P20)-$S$2)/20)+Q20) -> -2 | S20: =IFERROR(__xludf.DUMMYFUNCTION("SPARKLINE(SUM(E20:P20),{""charttype"",""bar"";""max"",$S$2})"),"")
B21: {=IFERROR(INDEX(#REF!,MATCH(C21,#REF!,0)),"")} | C21: =IFERROR(__xludf.DUMMYFUNCTION("""COMPUTED_VALUE"""),"Humberto") -> Humberto | D21: =IFERROR(__xludf.DUMMYFUNCTION("""COMPUTED_VALUE"""),"Carlos Humberto luiz") -> Carlos Humberto luiz | E21: =SUMIFS(Pagamentos!$E:$E,Pagamentos!$F:$F,TRUE,Pagamentos!$C:$C,$C21,Pagamentos!$D:$D,E$2) -> 0 | F21: =SUMIFS(Pagamentos!$E:$E,Pagamentos!$F:$F,TRUE,Pagamentos!$C:$C,$C21,Pagamentos!$D:$D,F$2) -> 0 | G21: =SUMIFS(Pagamentos!$E:$E,Pagamentos!$F:$F,TRUE,Pagamentos!$C:$C,$C21,Pagamentos!$D:$D,G$2) -> 60 | H21: =SUMIFS(Pagamentos!$E:$E,Pagamentos!$F:$F,TRUE,Pagamentos!$C:$C,$C21,Pagamentos!$D:$D,H$2) -> 20 | I21: =SUMIFS(Pagamentos!$E:$E,Pagamentos!$F:$F,TRUE,Pagamentos!$C:$C,$C21,Pagamentos!$D:$D,I$2) -> 20 | J21: =SUMIFS(Pagamentos!$E:$E,Pagamentos!$F:$F,TRUE,Pagamentos!$C:$C,$C21,Pagamentos!$D:$D,J$2) -> 20 | K21: =SUMIFS(Pagamentos!$E:$E,Pagamentos!$F:$F,TRUE,Pagamentos!$C:$C,$C21,Pagamentos!$D:$D,K$2) -> 20 | L21: =SUMIFS(Pagamentos!$E:$E,Pagamentos!$F:$F,TRUE,Pagamentos!$C:$C,$C21,Pagamentos!$D:$D,L$2) -> 20 | ... P21: =SUMIFS(Pagamentos!$E:$E,Pagamentos!$F:$F,TRUE,Pagamentos!$C:$C,$C21,Pagamentos!$D:$D,P$2) -> 0 | Q21: 2 | R21: =IF(Q21="","",((SUM(E21:P21)-$S$2)/20)+Q21) -> 2 | S21: =IFERROR(__xludf.DUMMYFUNCTION("SPARKLINE(SUM(E21:P21),{""charttype"",""bar"";""max"",$S$2})"),"")
B22: {=IFERROR(INDEX(#REF!,MATCH(C22,#REF!,0)),"")} | C22: =IFERROR(__xludf.DUMMYFUNCTION("""COMPUTED_VALUE"""),"Ilton") -> Ilton | D22: =IFERROR(__xludf.DUMMYFUNCTION("""COMPUTED_VALUE"""),"Ilton Saturnino Braz") -> Ilton Saturnino Braz | E22: =SUMIFS(Pagamentos!$E:$E,Pagamentos!$F:$F,TRUE,Pagamentos!$C:$C,$C22,Pagamentos!$D:$D,E$2) -> 0 | F22: =SUMIFS(Pagamentos!$E:$E,Pagamentos!$F:$F,TRUE,Pagamentos!$C:$C,$C22,Pagamentos!$D:$D,F$2) -> 0 | G22: =SUMIFS(Pagamentos!$E:$E,Pagamentos!$F:$F,TRUE,Pagamentos!$C:$C,$C22,Pagamentos!$D:$D,G$2) -> 100 | H22: =SUMIFS(Pagamentos!$E:$E,Pagamentos!$F:$F,TRUE,Pagamentos!$C:$C,$C22,Pagamentos!$D:$D,H$2) -> 0 | I22: =SUMIFS(Pagamentos!$E:$E,Pagamentos!$F:$F,TRUE,Pagamentos!$C:$C,$C22,Pagamentos!$D:$D,I$2) -> 0 | J22: =SUMIFS(Pagamentos!$E:$E,Pagamentos!$F:$F,TRUE,Pagamentos!$C:$C,$C22,Pagamentos!$D:$D,J$2) -> 60 | K22: =SUMIFS(Pagamentos!$E:$E,Pagamentos!$F:$F,TRUE,Pagamentos!$C:$C,$C22,Pagamentos!$D:$D,K$2) -> 0 | L22: =SUMIFS(Pagamentos!$E:$E,Pagamentos!$F:$F,TRUE,Pagamentos!$C:$C,$C22,Pagamentos!$D:$D,L$2) -> 0 | ... P22: =SUMIFS(Pagamentos!$E:$E,Pagamentos!$F:$F,TRUE,Pagamentos!$C:$C,$C22,Pagamentos!$D:$D,P$2) -> 0 | Q22: -2 | R22: =IF(Q22="","",((SUM(E22:P22)-$S$2)/20)+Q22) -> -2 | S22: =IFERROR(__xludf.DUMMYFUNCTION("SPARKLINE(SUM(E22:P22),{""charttype"",""bar"";""max"",$S$2})"),"")
B23: {=IFERROR(INDEX(#REF!,MATCH(C23,#REF!,0)),"")} | C23: =IFERROR(__xludf.DUMMYFUNCTION("""COMPUTED_VALUE"""),"Kassandra") -> Kassandra | D23: =IFERROR(__xludf.DUMMYFUNCTION("""COMPUTED_VALUE"""),"Gabriela Kassandra Luiz Colossi") -> Gabriela Kassandra Luiz Colossi | E23: =SUMIFS(Pagamentos!$E:$E,Pagamentos!$F:$F,TRUE,Pagamentos!$C:$C,$C23,Pagamentos!$D:$D,E$2) -> 20 | F23: =SUMIFS(Pagamentos!$E:$E,Pagamentos!$F:$F,TRUE,Pagamentos!$C:$C,$C23,Pagamentos!$D:$D,F$2) -> 40 | G23: =SUMIFS(Pagamentos!$E:$E,Pagamentos!$F:$F,TRUE,Pagamentos!$C:$C,$C23,Pagamentos!$D:$D,G$2) -> 40 | H23: =SUMIFS(Pagamentos!$E:$E,Pagamentos!$F:$F,TRUE,Pagamentos!$C:$C,$C23,Pagamentos!$D:$D,H$2) -> 20 | I23: =SUMIFS(Pagamentos!$E:$E,Pagamentos!$F:$F,TRUE,Pagamentos!$C:$C,$C23,Pagamentos!$D:$D,I$2) -> 20 | J23: =SUMIFS(Pagamentos!$E:$E,Pagamentos!$F:$F,TRUE,Pagamentos!$C:$C,$C23,Pagamentos!$D:$D,J$2) -> 0 | K23: =SUMIFS(Pagamentos!$E:$E,Pagamentos!$F:$F,TRUE,Pagamentos!$C:$C,$C23,Pagamentos!$D:$D,K$2) -> 20 | L23: =SUMIFS(Pagamentos!$E:$E,Pagamentos!$F:$F,TRUE,Pagamentos!$C:$C,$C23,Pagamentos!$D:$D,L$2) -> 0 | ... P23: =SUMIFS(Pagamentos!$E:$E,Pagamentos!$F:$F,TRUE,Pagamentos!$C:$C,$C23,Pagamentos!$D:$D,P$2) -> 0 | Q23: 2 | R23: =IF(Q23="","",((SUM(E23:P23)-$S$2)/20)+Q23) -> 2 | S23: =IFERROR(__xludf.DUMMYFUNCTION("SPARKLINE(SUM(E23:P23),{""charttype"",""bar"";""max"",$S$2})"),"")
B24: {=IFERROR(INDEX(#REF!,MATCH(C24,#REF!,0)),"")} | C24: =IFERROR(__xludf.DUMMYFUNCTION("""COMPUTED_VALUE"""),"Linder") -> Linder | D24: =IFERROR(__xludf.DUMMYFUNCTION("""COMPUTED_VALUE"""),"Gustavo Augusto Linder") -> Gustavo Augusto Linder | E24: =SUMIFS(Pagamentos!$E:$E,Pagamentos!$F:$F,TRUE,Pagamentos!$C:$C,$C24,Pagamentos!$D:$D,E$2) -> 0 | F24: =SUMIFS(Pagamentos!$E:$E,Pagamentos!$F:$F,TRUE,Pagamentos!$C:$C,$C24,Pagamentos!$D:$D,F$2) -> 60 | G24: =SUMIFS(Pagamentos!$E:$E,Pagamentos!$F:$F,TRUE,Pagamentos!$C:$C,$C24,Pagamentos!$D:$D,G$2) -> 0 | H24: =SUMIFS(Pagamentos!$E:$E,Pagamentos!$F:$F,TRUE,Pagamentos!$C:$C,$C24,Pagamentos!$D:$D,H$2) -> 0 | I24: =SUMIFS(Pagamentos!$E:$E,Pagamentos!$F:$F,TRUE,Pagamentos!$C:$C,$C24,Pagamentos!$D:$D,I$2) -> 0 | J24: =SUMIFS(Pagamentos!$E:$E,Pagamentos!$F:$F,TRUE,Pagamentos!$C:$C,$C24,Pagamentos!$D:$D,J$2) -> 40 | K24: =SUMIFS(Pagamentos!$E:$E,Pagamentos!$F:$F,TRUE,Pagamentos!$C:$C,$C24,Pagamentos!$D:$D,K$2) -> 0 | L24: =SUMIFS(Pagamentos!$E:$E,Pagamentos!$F:$F,TRUE,Pagamentos!$C:$C,$C24,Pagamentos!$D:$D,L$2) -> 0 | ... P24: =SUMIFS(Pagamentos!$E:$E,Pagamentos!$F:$F,TRUE,Pagamentos!$C:$C,$C24,Pagamentos!$D:$D,P$2) -> 0 | Q24: 1 | R24: =IF(Q24="","",((SUM(E24:P24)-$S$2)/20)+Q24) -> -2 | S24: =IFERROR(__xludf.DUMMYFUNCTION("SPARKLINE(SUM(E24:P24),{""charttype"",""bar"";""max"",$S$2})"),"")
B25: {=IFERROR(INDEX(#REF!,MATCH(C25,#REF!,0)),"")} | C25: =IFERROR(__xludf.DUMMYFUNCTION("""COMPUTED_VALUE"""),"Lourenço") -> Lourenço | D25: =IFERROR(__xludf.DUMMYFUNCTION("""COMPUTED_VALUE"""),"Carlos Henrique Lourenço Gonçalves") -> Carlos Henrique Lourenço Gonçalves | E25: =SUMIFS(Pagamentos!$E:$E,Pagamentos!$F:$F,TRUE,Pagamentos!$C:$C,$C25,Pagamentos!$D:$D,E$2) -> 20 | F25: =SUMIFS(Pagamentos!$E:$E,Pagamentos!$F:$F,TRUE,Pagamentos!$C:$C,$C25,Pagamentos!$D:$D,F$2) -> 20 | G25: =SUMIFS(Pagamentos!$E:$E,Pagamentos!$F:$F,TRUE,Pagamentos!$C:$C,$C25,Pagamentos!$D:$D,G$2) -> 20 | H25: =SUMIFS(Pagamentos!$E:$E,Pagamentos!$F:$F,TRUE,Pagamentos!$C:$C,$C25,Pagamentos!$D:$D,H$2) -> 20 | I25: =SUMIFS(Pagamentos!$E:$E,Pagamentos!$F:$F,TRUE,Pagamentos!$C:$C,$C25,Pagamentos!$D:$D,I$2) -> 20 | J25: =SUMIFS(Pagamentos!$E:$E,Pagamentos!$F:$F,TRUE,Pagamentos!$C:$C,$C25,Pagamentos!$D:$D,J$2) -> 20 | K25: =SUMIFS(Pagamentos!$E:$E,Pagamentos!$F:$F,TRUE,Pagamentos!$C:$C,$C25,Pagamentos!$D:$D,K$2) -> 20 | L25: =SUMIFS(Pagamentos!$E:$E,Pagamentos!$F:$F,TRUE,Pagamentos!$C:$C,$C25,Pagamentos!$D:$D,L$2) -> 0 | ... P25: =SUMIFS(Pagamentos!$E:$E,Pagamentos!$F:$F,TRUE,Pagamentos!$C:$C,$C25,Pagamentos!$D:$D,P$2) -> 0 | Q25: -1 | R25: =IF(Q25="","",((SUM(E25:P25)-$S$2)/20)+Q25) -> -2 | S25: =IFERROR(__xludf.DUMMYFUNCTION("SPARKLINE(SUM(E25:P25),{""charttype"",""bar"";""max"",$S$2})"),"")
B26: {=IFERROR(INDEX(#REF!,MATCH(C26,#REF!,0)),"")} | C26: =IFERROR(__xludf.DUMMYFUNCTION("""COMPUTED_VALUE"""),"Lucas") -> Lucas | D26: =IFERROR(__xludf.DUMMYFUNCTION("""COMPUTED_VALUE"""),"Lucas Rodrigues Antônio ") -> Lucas Rodrigues Antônio | E26: =SUMIFS(Pagamentos!$E:$E,Pagamentos!$F:$F,TRUE,Pagamentos!$C:$C,$C26,Pagamentos!$D:$D,E$2) -> 0 | F26: =SUMIFS(Pagamentos!$E:$E,Pagamentos!$F:$F,TRUE,Pagamentos!$C:$C,$C26,Pagamentos!$D:$D,F$2) -> 0 | G26: =SUMIFS(Pagamentos!$E:$E,Pagamentos!$F:$F,TRUE,Pagamentos!$C:$C,$C26,Pagamentos!$D:$D,G$2) -> 100 | H26: =SUMIFS(Pagamentos!$E:$E,Pagamentos!$F:$F,TRUE,Pagamentos!$C:$C,$C26,Pagamentos!$D:$D,H$2) -> 0 | I26: =SUMIFS(Pagamentos!$E:$E,Pagamentos!$F:$F,TRUE,Pagamentos!$C:$C,$C26,Pagamentos!$D:$D,I$2) -> 0 | J26: =SUMIFS(Pagamentos!$E:$E,Pagamentos!$F:$F,TRUE,Pagamentos!$C:$C,$C26,Pagamentos!$D:$D,J$2) -> 0 | K26: =SUMIFS(Pagamentos!$E:$E,Pagamentos!$F:$F,TRUE,Pagamentos!$C:$C,$C26,Pagamentos!$D:$D,K$2) -> 0 | L26: =SUMIFS(Pagamentos!$E:$E,Pagamentos!$F:$F,TRUE,Pagamentos!$C:$C,$C26,Pagamentos!$D:$D,L$2) -> 100 | ... P26: =SUMIFS(Pagamentos!$E:$E,Pagamentos!$F:$F,TRUE,Pagamentos!$C:$C,$C26,Pagamentos!$D:$D,P$2) -> 0 | Q26: 2 | R26: =IF(Q26="","",((SUM(E26:P26)-$S$2)/20)+Q26) -> 4 | S26: =IFERROR(__xludf.DUMMYFUNCTION("SPARKLINE(SUM(E26:P26),{""charttype"",""bar"";""max"",$S$2})"),"")
B27: {=IFERROR(INDEX(#REF!,MATCH(C27,#REF!,0)),"")} | C27: =IFERROR(__xludf.DUMMYFUNCTION("""COMPUTED_VALUE"""),"Mayara") -> Mayara | D27: =IFERROR(__xludf.DUMMYFUNCTION("""COMPUTED_VALUE"""),"Mayara Vieira Soares") -> Mayara Vieira Soares | E27: =SUMIFS(Pagamentos!$E:$E,Pagamentos!$F:$F,TRUE,Pagamentos!$C:$C,$C27,Pagamentos!$D:$D,E$2) -> 0 | F27: =SUMIFS(Pagamentos!$E:$E,Pagamentos!$F:$F,TRUE,Pagamentos!$C:$C,$C27,Pagamentos!$D:$D,F$2) -> 0 | G27: =SUMIFS(Pagamentos!$E:$E,Pagamentos!$F:$F,TRUE,Pagamentos!$C:$C,$C27,Pagamentos!$D:$D,G$2) -> 120 | H27: =SUMIFS(Pagamentos!$E:$E,Pagamentos!$F:$F,TRUE,Pagamentos!$C:$C,$C27,Pagamentos!$D:$D,H$2) -> 0 | I27: =SUMIFS(Pagamentos!$E:$E,Pagamentos!$F:$F,TRUE,Pagamentos!$C:$C,$C27,Pagamentos!$D:$D,I$2) -> 0 | J27: =SUMIFS(Pagamentos!$E:$E,Pagamentos!$F:$F,TRUE,Pagamentos!$C:$C,$C27,Pagamentos!$D:$D,J$2) -> 0 | K27: =SUMIFS(Pagamentos!$E:$E,Pagamentos!$F:$F,TRUE,Pagamentos!$C:$C,$C27,Pagamentos!$D:$D,K$2) -> 0 | L27: =SUMIFS(Pagamentos!$E:$E,Pagamentos!$F:$F,TRUE,Pagamentos!$C:$C,$C27,Pagamentos!$D:$D,L$2) -> 0 | ... P27: =SUMIFS(Pagamentos!$E:$E,Pagamentos!$F:$F,TRUE,Pagamentos!$C:$C,$C27,Pagamentos!$D:$D,P$2) -> 0 | Q27: -1 | R27: =IF(Q27="","",((SUM(E27:P27)-$S$2)/20)+Q27) -> -3 | S27: =IFERROR(__xludf.DUMMYFUNCTION("SPARKLINE(SUM(E27:P27),{""charttype"",""bar"";""max"",$S$2})"),"")
B28: {=IFERROR(INDEX(#REF!,MATCH(C28,#REF!,0)),"")} | C28: =IFERROR(__xludf.DUMMYFUNCTION("""COMPUTED_VALUE"""),"Mina") -> Mina | D28: =IFERROR(__xludf.DUMMYFUNCTION("""COMPUTED_VALUE"""),"Kleber Pacheco Mina") -> Kleber Pacheco Mina | E28: =SUMIFS(Pagamentos!$E:$E,Pagamentos!$F:$F,TRUE,Pagamentos!$C:$C,$C28,Pagamentos!$D:$D,E$2) -> 0 | F28: =SUMIFS(Pagamentos!$E:$E,Pagamentos!$F:$F,TRUE,Pagamentos!$C:$C,$C28,Pagamentos!$D:$D,F$2) -> 0 | G28: =SUMIFS(Pagamentos!$E:$E,Pagamentos!$F:$F,TRUE,Pagamentos!$C:$C,$C28,Pagamentos!$D:$D,G$2) -> 60 | H28: =SUMIFS(Pagamentos!$E:$E,Pagamentos!$F:$F,TRUE,Pagamentos!$C:$C,$C28,Pagamentos!$D:$D,H$2) -> 0 | I28: =SUMIFS(Pagamentos!$E:$E,Pagamentos!$F:$F,TRUE,Pagamentos!$C:$C,$C28,Pagamentos!$D:$D,I$2) -> 0 | J28: =SUMIFS(Pagamentos!$E:$E,Pagamentos!$F:$F,TRUE,Pagamentos!$C:$C,$C28,Pagamentos!$D:$D,J$2) -> 80 | K28: =SUMIFS(Pagamentos!$E:$E,Pagamentos!$F:$F,TRUE,Pagamentos!$C:$C,$C28,Pagamentos!$D:$D,K$2) -> 0 | L28: =SUMIFS(Pagamentos!$E:$E,Pagamentos!$F:$F,TRUE,Pagamentos!$C:$C,$C28,Pagamentos!$D:$D,L$2) -> 0 | ... P28: =SUMIFS(Pagamentos!$E:$E,Pagamentos!$F:$F,TRUE,Pagamentos!$C:$C,$C28,Pagamentos!$D:$D,P$2) -> 0 | Q28: 0 | R28: =IF(Q28="","",((SUM(E28:P28)-$S$2)/20)+Q28) -> -1 | S28: =IFERROR(__xludf.DUMMYFUNCTION("SPARKLINE(SUM(E28:P28),{""charttype"",""bar"";""max"",$S$2})"),"")
B29: {=IFERROR(INDEX(#REF!,MATCH(C29,#REF!,0)),"")} | C29: =IFERROR(__xludf.DUMMYFUNCTION("""COMPUTED_VALUE"""),"Mithel") -> Mithel | D29: =IFERROR(__xludf.DUMMYFUNCTION("""COMPUTED_VALUE"""),"Mithel Evergisto de Lima") -> Mithel Evergisto de Lima | E29: =SUMIFS(Pagamentos!$E:$E,Pagamentos!$F:$F,TRUE,Pagamentos!$C:$C,$C29,Pagamentos!$D:$D,E$2) -> 0 | F29: =SUMIFS(Pagamentos!$E:$E,Pagamentos!$F:$F,TRUE,Pagamentos!$C:$C,$C29,Pagamentos!$D:$D,F$2) -> 0 | G29: =SUMIFS(Pagamentos!$E:$E,Pagamentos!$F:$F,TRUE,Pagamentos!$C:$C,$C29,Pagamentos!$D:$D,G$2) -> 100 | H29: =SUMIFS(Pagamentos!$E:$E,Pagamentos!$F:$F,TRUE,Pagamentos!$C:$C,$C29,Pagamentos!$D:$D,H$2) -> 0 | I29: =SUMIFS(Pagamentos!$E:$E,Pagamentos!$F:$F,TRUE,Pagamentos!$C:$C,$C29,Pagamentos!$D:$D,I$2) -> 0 | J29: =SUMIFS(Pagamentos!$E:$E,Pagamentos!$F:$F,TRUE,Pagamentos!$C:$C,$C29,Pagamentos!$D:$D,J$2) -> 0 | K29: =SUMIFS(Pagamentos!$E:$E,Pagamentos!$F:$F,TRUE,Pagamentos!$C:$C,$C29,Pagamentos!$D:$D,K$2) -> 0 | L29: =SUMIFS(Pagamentos!$E:$E,Pagamentos!$F:$F,TRUE,Pagamentos!$C:$C,$C29,Pagamentos!$D:$D,L$2) -> 0 | ... P29: =SUMIFS(Pagamentos!$E:$E,Pagamentos!$F:$F,TRUE,Pagamentos!$C:$C,$C29,Pagamentos!$D:$D,P$2) -> 0 | Q29: 0 | R29: =IF(Q29="","",((SUM(E29:P29)-$S$2)/20)+Q29) -> -3 | S29: =IFERROR(__xludf.DUMMYFUNCTION("SPARKLINE(SUM(E29:P29),{""charttype"",""bar"";""max"",$S$2})"),"")
B30: {=IFERROR(INDEX(#REF!,MATCH(C30,#REF!,0)),"")} | C30: =IFERROR(__xludf.DUMMYFUNCTION("""COMPUTED_VALUE"""),"Natayan") -> Natayan | D30: =IFERROR(__xludf.DUMMYFUNCTION("""COMPUTED_VALUE"""),"Raphael Natayan Nilsen") -> Raphael Natayan Nilsen | E30: =SUMIFS(Pagamentos!$E:$E,Pagamentos!$F:$F,TRUE,Pagamentos!$C:$C,$C30,Pagamentos!$D:$D,E$2) -> 40 | F30: =SUMIFS(Pagamentos!$E:$E,Pagamentos!$F:$F,TRUE,Pagamentos!$C:$C,$C30,Pagamentos!$D:$D,F$2) -> 0 | G30: =SUMIFS(Pagamentos!$E:$E,Pagamentos!$F:$F,TRUE,Pagamentos!$C:$C,$C30,Pagamentos!$D:$D,G$2) -> 20 | H30: =SUMIFS(Pagamentos!$E:$E,Pagamentos!$F:$F,TRUE,Pagamentos!$C:$C,$C30,Pagamentos!$D:$D,H$2) -> 20 | I30: =SUMIFS(Pagamentos!$E:$E,Pagamentos!$F:$F,TRUE,Pagamentos!$C:$C,$C30,Pagamentos!$D:$D,I$2) -> 20 | J30: =SUMIFS(Pagamentos!$E:$E,Pagamentos!$F:$F,TRUE,Pagamentos!$C:$C,$C30,Pagamentos!$D:$D,J$2) -> 20 | K30: =SUMIFS(Pagamentos!$E:$E,Pagamentos!$F:$F,TRUE,Pagamentos!$C:$C,$C30,Pagamentos!$D:$D,K$2) -> 20 | L30: =SUMIFS(Pagamentos!$E:$E,Pagamentos!$F:$F,TRUE,Pagamentos!$C:$C,$C30,Pagamentos!$D:$D,L$2) -> 0 | ... P30: =SUMIFS(Pagamentos!$E:$E,Pagamentos!$F:$F,TRUE,Pagamentos!$C:$C,$C30,Pagamentos!$D:$D,P$2) -> 0 | Q30: 0 | R30: =IF(Q30="","",((SUM(E30:P30)-$S$2)/20)+Q30) -> -1 | S30: =IFERROR(__xludf.DUMMYFUNCTION("SPARKLINE(SUM(E30:P30),{""charttype"",""bar"";""max"",$S$2})"),"")
B31: {=IFERROR(INDEX(#REF!,MATCH(C31,#REF!,0)),"")} | C31: =IFERROR(__xludf.DUMMYFUNCTION("""COMPUTED_VALUE"""),"Nery") -> Nery | D31: =IFERROR(__xludf.DUMMYFUNCTION("""COMPUTED_VALUE"""),"Gabriel Nery Cristiano ") -> Gabriel Nery Cristiano | E31: =SUMIFS(Pagamentos!$E:$E,Pagamentos!$F:$F,TRUE,Pagamentos!$C:$C,$C31,Pagamentos!$D:$D,E$2) -> 0 | F31: =SUMIFS(Pagamentos!$E:$E,Pagamentos!$F:$F,TRUE,Pagamentos!$C:$C,$C31,Pagamentos!$D:$D,F$2) -> 0 | G31: =SUMIFS(Pagamentos!$E:$E,Pagamentos!$F:$F,TRUE,Pagamentos!$C:$C,$C31,Pagamentos!$D:$D,G$2) -> 0 | H31: =SUMIFS(Pagamentos!$E:$E,Pagamentos!$F:$F,TRUE,Pagamentos!$C:$C,$C31,Pagamentos!$D:$D,H$2) -> 0 | I31: =SUMIFS(Pagamentos!$E:$E,Pagamentos!$F:$F,TRUE,Pagamentos!$C:$C,$C31,Pagamentos!$D:$D,I$2) -> 80 | J31: =SUMIFS(Pagamentos!$E:$E,Pagamentos!$F:$F,TRUE,Pagamentos!$C:$C,$C31,Pagamentos!$D:$D,J$2) -> 40 | K31: =SUMIFS(Pagamentos!$E:$E,Pagamentos!$F:$F,TRUE,Pagamentos!$C:$C,$C31,Pagamentos!$D:$D,K$2) -> 20 | L31: =SUMIFS(Pagamentos!$E:$E,Pagamentos!$F:$F,TRUE,Pagamentos!$C:$C,$C31,Pagamentos!$D:$D,L$2) -> 0 | ... P31: =SUMIFS(Pagamentos!$E:$E,Pagamentos!$F:$F,TRUE,Pagamentos!$C:$C,$C31,Pagamentos!$D:$D,P$2) -> 0 | Q31: 0 | R31: =IF(Q31="","",((SUM(E31:P31)-$S$2)/20)+Q31) -> -1 | S31: =IFERROR(__xludf.DUMMYFUNCTION("SPARKLINE(SUM(E31:P31),{""charttype"",""bar"";""max"",$S$2})"),"")
B32: {=IFERROR(INDEX(#REF!,MATCH(C32,#REF!,0)),"")} | C32: =IFERROR(__xludf.DUMMYFUNCTION("""COMPUTED_VALUE"""),"Oliveira") -> Oliveira | D32: =IFERROR(__xludf.DUMMYFUNCTION("""COMPUTED_VALUE"""),"Marcelo luiz de Oliveira") -> Marcelo luiz de Oliveira | E32: =SUMIFS(Pagamentos!$E:$E,Pagamentos!$F:$F,TRUE,Pagamentos!$C:$C,$C32,Pagamentos!$D:$D,E$2) -> 0 | F32: =SUMIFS(Pagamentos!$E:$E,Pagamentos!$F:$F,TRUE,Pagamentos!$C:$C,$C32,Pagamentos!$D:$D,F$2) -> 0 | G32: =SUMIFS(Pagamentos!$E:$E,Pagamentos!$F:$F,TRUE,Pagamentos!$C:$C,$C32,Pagamentos!$D:$D,G$2) -> 40 | H32: =SUMIFS(Pagamentos!$E:$E,Pagamentos!$F:$F,TRUE,Pagamentos!$C:$C,$C32,Pagamentos!$D:$D,H$2) -> 0 | I32: =SUMIFS(Pagamentos!$E:$E,Pagamentos!$F:$F,TRUE,Pagamentos!$C:$C,$C32,Pagamentos!$D:$D,I$2) -> 80 | J32: =SUMIFS(Pagamentos!$E:$E,Pagamentos!$F:$F,TRUE,Pagamentos!$C:$C,$C32,Pagamentos!$D:$D,J$2) -> 0 | K32: =SUMIFS(Pagamentos!$E:$E,Pagamentos!$F:$F,TRUE,Pagamentos!$C:$C,$C32,Pagamentos!$D:$D,K$2) -> 20 | L32: =SUMIFS(Pagamentos!$E:$E,Pagamentos!$F:$F,TRUE,Pagamentos!$C:$C,$C32,Pagamentos!$D:$D,L$2) -> 0 | ... P32: =SUMIFS(Pagamentos!$E:$E,Pagamentos!$F:$F,TRUE,Pagamentos!$C:$C,$C32,Pagamentos!$D:$D,P$2) -> 0 | Q32: -1 | R32: =IF(Q32="","",((SUM(E32:P32)-$S$2)/20)+Q32) -> -2 | S32: =IFERROR(__xludf.DUMMYFUNCTION("SPARKLINE(SUM(E32:P32),{""charttype"",""bar"";""max"",$S$2})"),"")
B33: {=IFERROR(INDEX(#REF!,MATCH(C33,#REF!,0)),"")} | C33: =IFERROR(__xludf.DUMMYFUNCTION("""COMPUTED_VALUE"""),"Ozol") -> Ozol | D33: =IFERROR(__xludf.DUMMYFUNCTION("""COMPUTED_VALUE"""),"Guilherme Ozol de Assunção ") -> Guilherme Ozol de Assunção | E33: =SUMIFS(Pagamentos!$E:$E,Pagamentos!$F:$F,TRUE,Pagamentos!$C:$C,$C33,Pagamentos!$D:$D,E$2) -> 0 | F33: =SUMIFS(Pagamentos!$E:$E,Pagamentos!$F:$F,TRUE,Pagamentos!$C:$C,$C33,Pagamentos!$D:$D,F$2) -> 0 | G33: =SUMIFS(Pagamentos!$E:$E,Pagamentos!$F:$F,TRUE,Pagamentos!$C:$C,$C33,Pagamentos!$D:$D,G$2) -> 60 | H33: =SUMIFS(Pagamentos!$E:$E,Pagamentos!$F:$F,TRUE,Pagamentos!$C:$C,$C33,Pagamentos!$D:$D,H$2) -> 0 | I33: =SUMIFS(Pagamentos!$E:$E,Pagamentos!$F:$F,TRUE,Pagamentos!$C:$C,$C33,Pagamentos!$D:$D,I$2) -> 0 | J33: =SUMIFS(Pagamentos!$E:$E,Pagamentos!$F:$F,TRUE,Pagamentos!$C:$C,$C33,Pagamentos!$D:$D,J$2) -> 0 | K33: =SUMIFS(Pagamentos!$E:$E,Pagamentos!$F:$F,TRUE,Pagamentos!$C:$C,$C33,Pagamentos!$D:$D,K$2) -> 0 | L33: =SUMIFS(Pagamentos!$E:$E,Pagamentos!$F:$F,TRUE,Pagamentos!$C:$C,$C33,Pagamentos!$D:$D,L$2) -> 0 | ... P33: =SUMIFS(Pagamentos!$E:$E,Pagamentos!$F:$F,TRUE,Pagamentos!$C:$C,$C33,Pagamentos!$D:$D,P$2) -> 0 | Q33: 0 | R33: =IF(Q33="","",((SUM(E33:P33)-$S$2)/20)+Q33) -> -5 | S33: =IFERROR(__xludf.DUMMYFUNCTION("SPARKLINE(SUM(E33:P33),{""charttype"",""bar"";""max"",$S$2})"),"")
B34: {=IFERROR(INDEX(#REF!,MATCH(C34,#REF!,0)),"")} | C34: =IFERROR(__xludf.DUMMYFUNCTION("""COMPUTED_VALUE"""),"Pereira") -> Pereira | D34: =IFERROR(__xludf.DUMMYFUNCTION("""COMPUTED_VALUE"""),"Emerson Pereira") -> Emerson Pereira | E34: =SUMIFS(Pagamentos!$E:$E,Pagamentos!$F:$F,TRUE,Pagamentos!$C:$C,$C34,Pagamentos!$D:$D,E$2) -> 0 | F34: =SUMIFS(Pagamentos!$E:$E,Pagamentos!$F:$F,TRUE,Pagamentos!$C:$C,$C34,Pagamentos!$D:$D,F$2) -> 80 | G34: =SUMIFS(Pagamentos!$E:$E,Pagamentos!$F:$F,TRUE,Pagamentos!$C:$C,$C34,Pagamentos!$D:$D,G$2) -> 0 | H34: =SUMIFS(Pagamentos!$E:$E,Pagamentos!$F:$F,TRUE,Pagamentos!$C:$C,$C34,Pagamentos!$D:$D,H$2) -> 0 | I34: =SUMIFS(Pagamentos!$E:$E,Pagamentos!$F:$F,TRUE,Pagamentos!$C:$C,$C34,Pagamentos!$D:$D,I$2) -> 0 | J34: =SUMIFS(Pagamentos!$E:$E,Pagamentos!$F:$F,TRUE,Pagamentos!$C:$C,$C34,Pagamentos!$D:$D,J$2) -> 0 | K34: =SUMIFS(Pagamentos!$E:$E,Pagamentos!$F:$F,TRUE,Pagamentos!$C:$C,$C34,Pagamentos!$D:$D,K$2) -> 180 | L34: =SUMIFS(Pagamentos!$E:$E,Pagamentos!$F:$F,TRUE,Pagamentos!$C:$C,$C34,Pagamentos!$D:$D,L$2) -> 0 | ... P34: =SUMIFS(Pagamentos!$E:$E,Pagamentos!$F:$F,TRUE,Pagamentos!$C:$C,$C34,Pagamentos!$D:$D,P$2) -> 0 | Q34: 0 | R34: =IF(Q34="","",((SUM(E34:P34)-$S$2)/20)+Q34) -> 5 | S34: =IFERROR(__xludf.DUMMYFUNCTION("SPARKLINE(SUM(E34:P34),{""charttype"",""bar"";""max"",$S$2})"),"")
B35: {=IFERROR(INDEX(#REF!,MATCH(C35,#REF!,0)),"")} | C35: =IFERROR(__xludf.DUMMYFUNCTION("""COMPUTED_VALUE"""),"Ravache") -> Ravache | D35: =IFERROR(__xludf.DUMMYFUNCTION("""COMPUTED_VALUE"""),"Caio Passold Ravache") -> Caio Passold Ravache | E35: =SUMIFS(Pagamentos!$E:$E,Pagamentos!$F:$F,TRUE,Pagamentos!$C:$C,$C35,Pagamentos!$D:$D,E$2) -> 0 | F35: =SUMIFS(Pagamentos!$E:$E,Pagamentos!$F:$F,TRUE,Pagamentos!$C:$C,$C35,Pagamentos!$D:$D,F$2) -> 0 | G35: =SUMIFS(Pagamentos!$E:$E,Pagamentos!$F:$F,TRUE,Pagamentos!$C:$C,$C35,Pagamentos!$D:$D,G$2) -> 0 | H35: =SUMIFS(Pagamentos!$E:$E,Pagamentos!$F:$F,TRUE,Pagamentos!$C:$C,$C35,Pagamentos!$D:$D,H$2) -> 0 | I35: =SUMIFS(Pagamentos!$E:$E,Pagamentos!$F:$F,TRUE,Pagamentos!$C:$C,$C35,Pagamentos!$D:$D,I$2) -> 0 | J35: =SUMIFS(Pagamentos!$E:$E,Pagamentos!$F:$F,TRUE,Pagamentos!$C:$C,$C35,Pagamentos!$D:$D,J$2) -> 0 | K35: =SUMIFS(Pagamentos!$E:$E,Pagamentos!$F:$F,TRUE,Pagamentos!$C:$C,$C35,Pagamentos!$D:$D,K$2) -> 0 | L35: =SUMIFS(Pagamentos!$E:$E,Pagamentos!$F:$F,TRUE,Pagamentos!$C:$C,$C35,Pagamentos!$D:$D,L$2) -> 0 | ... P35: =SUMIFS(Pagamentos!$E:$E,Pagamentos!$F:$F,TRUE,Pagamentos!$C:$C,$C35,Pagamentos!$D:$D,P$2) -> 0 | Q35: 0 | R35: =IF(Q35="","",((SUM(E35:P35)-$S$2)/20)+Q35) -> -8 | S35: =IFERROR(__xludf.DUMMYFUNCTION("SPARKLINE(SUM(E35:P35),{""charttype"",""bar"";""max"",$S$2})"),"")
B36: {=IFERROR(INDEX(#REF!,MATCH(C36,#REF!,0)),"")} | C36: =IFERROR(__xludf.DUMMYFUNCTION("""COMPUTED_VALUE"""),"Santana") -> Santana | D36: =IFERROR(__xludf.DUMMYFUNCTION("""COMPUTED_VALUE"""),"Michele Santana Quint") -> Michele Santana Quint | E36: =SUMIFS(Pagamentos!$E:$E,Pagamentos!$F:$F,TRUE,Pagamentos!$C:$C,$C36,Pagamentos!$D:$D,E$2) -> 0 | F36: =SUMIFS(Pagamentos!$E:$E,Pagamentos!$F:$F,TRUE,Pagamentos!$C:$C,$C36,Pagamentos!$D:$D,F$2) -> 0 | G36: =SUMIFS(Pagamentos!$E:$E,Pagamentos!$F:$F,TRUE,Pagamentos!$C:$C,$C36,Pagamentos!$D:$D,G$2) -> 60 | H36: =SUMIFS(Pagamentos!$E:$E,Pagamentos!$F:$F,TRUE,Pagamentos!$C:$C,$C36,Pagamentos!$D:$D,H$2) -> 0 | I36: =SUMIFS(Pagamentos!$E:$E,Pagamentos!$F:$F,TRUE,Pagamentos!$C:$C,$C36,Pagamentos!$D:$D,I$2) -> 0 | J36: =SUMIFS(Pagamentos!$E:$E,Pagamentos!$F:$F,TRUE,Pagamentos!$C:$C,$C36,Pagamentos!$D:$D,J$2) -> 0 | K36: =SUMIFS(Pagamentos!$E:$E,Pagamentos!$F:$F,TRUE,Pagamentos!$C:$C,$C36,Pagamentos!$D:$D,K$2) -> 0 | L36: =SUMIFS(Pagamentos!$E:$E,Pagamentos!$F:$F,TRUE,Pagamentos!$C:$C,$C36,Pagamentos!$D:$D,L$2) -> 0 | ... P36: =SUMIFS(Pagamentos!$E:$E,Pagamentos!$F:$F,TRUE,Pagamentos!$C:$C,$C36,Pagamentos!$D:$D,P$2) -> 0 | Q36: 0 | R36: =IF(Q36="","",((SUM(E36:P36)-$S$2)/20)+Q36) -> -5 | S36: =IFERROR(__xludf.DUMMYFUNCTION("SPARKLINE(SUM(E36:P36),{""charttype"",""bar"";""max"",$S$2})"),"")
B37: {=IFERROR(INDEX(#REF!,MATCH(C37,#REF!,0)),"")} | C37: =IFERROR(__xludf.DUMMYFUNCTION("""COMPUTED_VALUE"""),"Sardá") -> Sardá | D37: =IFERROR(__xludf.DUMMYFUNCTION("""COMPUTED_VALUE"""),"Julia da Silva Sardá ") -> Julia da Silva Sardá | E37: =SUMIFS(Pagamentos!$E:$E,Pagamentos!$F:$F,TRUE,Pagamentos!$C:$C,$C37,Pagamentos!$D:$D,E$2) -> 0 | F37: =SUMIFS(Pagamentos!$E:$E,Pagamentos!$F:$F,TRUE,Pagamentos!$C:$C,$C37,Pagamentos!$D:$D,F$2) -> 0 | G37: =SUMIFS(Pagamentos!$E:$E,Pagamentos!$F:$F,TRUE,Pagamentos!$C:$C,$C37,Pagamentos!$D:$D,G$2) -> 60 | H37: =SUMIFS(Pagamentos!$E:$E,Pagamentos!$F:$F,TRUE,Pagamentos!$C:$C,$C37,Pagamentos!$D:$D,H$2) -> 20 | I37: =SUMIFS(Pagamentos!$E:$E,Pagamentos!$F:$F,TRUE,Pagamentos!$C:$C,$C37,Pagamentos!$D:$D,I$2) -> 0 | J37: =SUMIFS(Pagamentos!$E:$E,Pagamentos!$F:$F,TRUE,Pagamentos!$C:$C,$C37,Pagamentos!$D:$D,J$2) -> 0 | K37: =SUMIFS(Pagamentos!$E:$E,Pagamentos!$F:$F,TRUE,Pagamentos!$C:$C,$C37,Pagamentos!$D:$D,K$2) -> 0 | L37: =SUMIFS(Pagamentos!$E:$E,Pagamentos!$F:$F,TRUE,Pagamentos!$C:$C,$C37,Pagamentos!$D:$D,L$2) -> 0 | ... P37: =SUMIFS(Pagamentos!$E:$E,Pagamentos!$F:$F,TRUE,Pagamentos!$C:$C,$C37,Pagamentos!$D:$D,P$2) -> 0 | Q37: 0 | R37: =IF(Q37="","",((SUM(E37:P37)-$S$2)/20)+Q37) -> -4 | S37: =IFERROR(__xludf.DUMMYFUNCTION("SPARKLINE(SUM(E37:P37),{""charttype"",""bar"";""max"",$S$2})"),"")
B38: {=IFERROR(INDEX(#REF!,MATCH(C38,#REF!,0)),"")} | C38: =IFERROR(__xludf.DUMMYFUNCTION("""COMPUTED_VALUE"""),"Schmitt") -> Schmitt | D38: =IFERROR(__xludf.DUMMYFUNCTION("""COMPUTED_VALUE"""),"André Luiz Schmitt") -> André Luiz Schmitt | E38: =SUMIFS(Pagamentos!$E:$E,Pagamentos!$F:$F,TRUE,Pagamentos!$C:$C,$C38,Pagamentos!$D:$D,E$2) -> 0 | F38: =SUMIFS(Pagamentos!$E:$E,Pagamentos!$F:$F,TRUE,Pagamentos!$C:$C,$C38,Pagamentos!$D:$D,F$2) -> 0 | G38: =SUMIFS(Pagamentos!$E:$E,Pagamentos!$F:$F,TRUE,Pagamentos!$C:$C,$C38,Pagamentos!$D:$D,G$2) -> 100 | H38: =SUMIFS(Pagamentos!$E:$E,Pagamentos!$F:$F,TRUE,Pagamentos!$C:$C,$C38,Pagamentos!$D:$D,H$2) -> 0 | I38: =SUMIFS(Pagamentos!$E:$E,Pagamentos!$F:$F,TRUE,Pagamentos!$C:$C,$C38,Pagamentos!$D:$D,I$2) -> 0 | J38: =SUMIFS(Pagamentos!$E:$E,Pagamentos!$F:$F,TRUE,Pagamentos!$C:$C,$C38,Pagamentos!$D:$D,J$2) -> 0 | K38: =SUMIFS(Pagamentos!$E:$E,Pagamentos!$F:$F,TRUE,Pagamentos!$C:$C,$C38,Pagamentos!$D:$D,K$2) -> 0 | L38: =SUMIFS(Pagamentos!$E:$E,Pagamentos!$F:$F,TRUE,Pagamentos!$C:$C,$C38,Pagamentos!$D:$D,L$2) -> 0 | ... P38: =SUMIFS(Pagamentos!$E:$E,Pagamentos!$F:$F,TRUE,Pagamentos!$C:$C,$C38,Pagamentos!$D:$D,P$2) -> 0 | Q38: -1 | R38: =IF(Q38="","",((SUM(E38:P38)-$S$2)/20)+Q38) -> -4 | S38: =IFERROR(__xludf.DUMMYFUNCTION("SPARKLINE(SUM(E38:P38),{""charttype"",""bar"";""max"",$S$2})"),"")
B39: {=IFERROR(INDEX(#REF!,MATCH(C39,#REF!,0)),"")} | C39: =IFERROR(__xludf.DUMMYFUNCTION("""COMPUTED_VALUE"""),"Spotti") -> Spotti | D39: =IFERROR(__xludf.DUMMYFUNCTION("""COMPUTED_VALUE"""),"Kleber Spotti Rodrigues") -> Kleber Spotti Rodrigues | E39: =SUMIFS(Pagamentos!$E:$E,Pagamentos!$F:$F,TRUE,Pagamentos!$C:$C,$C39,Pagamentos!$D:$D,E$2) -> 0 | F39: =SUMIFS(Pagamentos!$E:$E,Pagamentos!$F:$F,TRUE,Pagamentos!$C:$C,$C39,Pagamentos!$D:$D,F$2) -> 0 | G39: =SUMIFS(Pagamentos!$E:$E,Pagamentos!$F:$F,TRUE,Pagamentos!$C:$C,$C39,Pagamentos!$D:$D,G$2) -> 100 | H39: =SUMIFS(Pagamentos!$E:$E,Pagamentos!$F:$F,TRUE,Pagamentos!$C:$C,$C39,Pagamentos!$D:$D,H$2) -> 0 | I39: =SUMIFS(Pagamentos!$E:$E,Pagamentos!$F:$F,TRUE,Pagamentos!$C:$C,$C39,Pagamentos!$D:$D,I$2) -> 0 | J39: =SUMIFS(Pagamentos!$E:$E,Pagamentos!$F:$F,TRUE,Pagamentos!$C:$C,$C39,Pagamentos!$D:$D,J$2) -> 0 | K39: =SUMIFS(Pagamentos!$E:$E,Pagamentos!$F:$F,TRUE,Pagamentos!$C:$C,$C39,Pagamentos!$D:$D,K$2) -> 0 | L39: =SUMIFS(Pagamentos!$E:$E,Pagamentos!$F:$F,TRUE,Pagamentos!$C:$C,$C39,Pagamentos!$D:$D,L$2) -> 100 | ... P39: =SUMIFS(Pagamentos!$E:$E,Pagamentos!$F:$F,TRUE,Pagamentos!$C:$C,$C39,Pagamentos!$D:$D,P$2) -> 0 | Q39: 2 | R39: =IF(Q39="","",((SUM(E39:P39)-$S$2)/20)+Q39) -> 4 | S39: =IFERROR(__xludf.DUMMYFUNCTION("SPARKLINE(SUM(E39:P39),{""charttype"",""bar"";""max"",$S$2})"),"")
B40: {=IFERROR(INDEX(#REF!,MATCH(C40,#REF!,0)),"")} | C40: =IFERROR(__xludf.DUMMYFUNCTION("""COMPUTED_VALUE"""),"Alves") -> Alves | D40: =IFERROR(__xludf.DUMMYFUNCTION("""COMPUTED_VALUE"""),"Uelder Alves Da Costa") -> Uelder Alves Da Costa | E40: =SUMIFS(Pagamentos!$E:$E,Pagamentos!$F:$F,TRUE,Pagamentos!$C:$C,$C40,Pagamentos!$D:$D,E$2) -> 0 | F40: =SUMIFS(Pagamentos!$E:$E,Pagamentos!$F:$F,TRUE,Pagamentos!$C:$C,$C40,Pagamentos!$D:$D,F$2) -> 240 | G40: =SUMIFS(Pagamentos!$E:$E,Pagamentos!$F:$F,TRUE,Pagamentos!$C:$C,$C40,Pagamentos!$D:$D,G$2) -> 0 | H40: =SUMIFS(Pagamentos!$E:$E,Pagamentos!$F:$F,TRUE,Pagamentos!$C:$C,$C40,Pagamentos!$D:$D,H$2) -> 0 | I40: =SUMIFS(Pagamentos!$E:$E,Pagamentos!$F:$F,TRUE,Pagamentos!$C:$C,$C40,Pagamentos!$D:$D,I$2) -> 0 | J40: =SUMIFS(Pagamentos!$E:$E,Pagamentos!$F:$F,TRUE,Pagamentos!$C:$C,$C40,Pagamentos!$D:$D,J$2) -> 0 | K40: =SUMIFS(Pagamentos!$E:$E,Pagamentos!$F:$F,TRUE,Pagamentos!$C:$C,$C40,Pagamentos!$D:$D,K$2) -> 0 | L40: =SUMIFS(Pagamentos!$E:$E,Pagamentos!$F:$F,TRUE,Pagamentos!$C:$C,$C40,Pagamentos!$D:$D,L$2) -> 0 | ... P40: =SUMIFS(Pagamentos!$E:$E,Pagamentos!$F:$F,TRUE,Pagamentos!$C:$C,$C40,Pagamentos!$D:$D,P$2) -> 0 | Q40: 0 | R40: =IF(Q40="","",((SUM(E40:P40)-$S$2)/20)+Q40) -> 4 | S40: =IFERROR(__xludf.DUMMYFUNCTION("SPARKLINE(SUM(E40:P40),{""charttype"",""bar"";""max"",$S$2})"),"")
B41: {=IFERROR(INDEX(#REF!,MATCH(C41,#REF!,0)),"")} | C41: =IFERROR(__xludf.DUMMYFUNCTION("""COMPUTED_VALUE"""),"Ulysséia") -> Ulysséia | D41: =IFERROR(__xludf.DUMMYFUNCTION("""COMPUTED_VALUE"""),"Ismael Vieira da Rosa Ulysséia") -> Ismael Vieira da Rosa Ulysséia | E41: =SUMIFS(Pagamentos!$E:$E,Pagamentos!$F:$F,TRUE,Pagamentos!$C:$C,$C41,Pagamentos!$D:$D,E$2) -> 0 | F41: =SUMIFS(Pagamentos!$E:$E,Pagamentos!$F:$F,TRUE,Pagamentos!$C:$C,$C41,Pagamentos!$D:$D,F$2) -> 0 | G41: =SUMIFS(Pagamentos!$E:$E,Pagamentos!$F:$F,TRUE,Pagamentos!$C:$C,$C41,Pagamentos!$D:$D,G$2) -> 100 | H41: =SUMIFS(Pagamentos!$E:$E,Pagamentos!$F:$F,TRUE,Pagamentos!$C:$C,$C41,Pagamentos!$D:$D,H$2) -> 0 | I41: =SUMIFS(Pagamentos!$E:$E,Pagamentos!$F:$F,TRUE,Pagamentos!$C:$C,$C41,Pagamentos!$D:$D,I$2) -> 0 | J41: =SUMIFS(Pagamentos!$E:$E,Pagamentos!$F:$F,TRUE,Pagamentos!$C:$C,$C41,Pagamentos!$D:$D,J$2) -> 100 | K41: =SUMIFS(Pagamentos!$E:$E,Pagamentos!$F:$F,TRUE,Pagamentos!$C:$C,$C41,Pagamentos!$D:$D,K$2) -> 0 | L41: =SUMIFS(Pagamentos!$E:$E,Pagamentos!$F:$F,TRUE,Pagamentos!$C:$C,$C41,Pagamentos!$D:$D,L$2) -> 0 | ... P41: =SUMIFS(Pagamentos!$E:$E,Pagamentos!$F:$F,TRUE,Pagamentos!$C:$C,$C41,Pagamentos!$D:$D,P$2) -> 0 | Q41: 0 | R41: =IF(Q41="","",((SUM(E41:P41)-$S$2)/20)+Q41) -> 2 | S41: =IFERROR(__xludf.DUMMYFUNCTION("SPARKLINE(SUM(E41:P41),{""charttype"",""bar"";""max"",$S$2})"),"")
B42: {=IFERROR(INDEX(#REF!,MATCH(C42,#REF!,0)),"")} | C42: =IFERROR(__xludf.DUMMYFUNCTION("""COMPUTED_VALUE"""),"Yanka") -> Yanka | D42: =IFERROR(__xludf.DUMMYFUNCTION("""COMPUTED_VALUE"""),"Yanka Caroliny Luciano") -> Yanka Caroliny Luciano | E42: =SUMIFS(Pagamentos!$E:$E,Pagamentos!$F:$F,TRUE,Pagamentos!$C:$C,$C42,Pagamentos!$D:$D,E$2) -> 20 | F42: =SUMIFS(Pagamentos!$E:$E,Pagamentos!$F:$F,TRUE,Pagamentos!$C:$C,$C42,Pagamentos!$D:$D,F$2) -> 20 | G42: =SUMIFS(Pagamentos!$E:$E,Pagamentos!$F:$F,TRUE,Pagamentos!$C:$C,$C42,Pagamentos!$D:$D,G$2) -> 0 | H42: =SUMIFS(Pagamentos!$E:$E,Pagamentos!$F:$F,TRUE,Pagamentos!$C:$C,$C42,Pagamentos!$D:$D,H$2) -> 60 | I42: =SUMIFS(Pagamentos!$E:$E,Pagamentos!$F:$F,TRUE,Pagamentos!$C:$C,$C42,Pagamentos!$D:$D,I$2) -> 20 | J42: =SUMIFS(Pagamentos!$E:$E,Pagamentos!$F:$F,TRUE,Pagamentos!$C:$C,$C42,Pagamentos!$D:$D,J$2) -> 20 | K42: =SUMIFS(Pagamentos!$E:$E,Pagamentos!$F:$F,TRUE,Pagamentos!$C:$C,$C42,Pagamentos!$D:$D,K$2) -> 20 | L42: =SUMIFS(Pagamentos!$E:$E,Pagamentos!$F:$F,TRUE,Pagamentos!$C:$C,$C42,Pagamentos!$D:$D,L$2) -> 0 | ... P42: =SUMIFS(Pagamentos!$E:$E,Pagamentos!$F:$F,TRUE,Pagamentos!$C:$C,$C42,Pagamentos!$D:$D,P$2) -> 0 | Q42: 0 | R42: =IF(Q42="","",((SUM(E42:P42)-$S$2)/20)+Q42) -> 0 | S42: =IFERROR(__xludf.DUMMYFUNCTION("SPARKLINE(SUM(E42:P42),{""charttype"",""bar"";""max"",$S$2})"),"")
B43: {=IFERROR(INDEX(#REF!,MATCH(C43,#REF!,0)),"")} | C43: =IFERROR(__xludf.DUMMYFUNCTION("""COMPUTED_VALUE"""),"Yuri") -> Yuri | D43: =IFERROR(__xludf.DUMMYFUNCTION("""COMPUTED_VALUE"""),"Yuri Esmerio dos Santos ") -> Yuri Esmerio dos Santos | E43: =SUMIFS(Pagamentos!$E:$E,Pagamentos!$F:$F,TRUE,Pagamentos!$C:$C,$C43,Pagamentos!$D:$D,E$2) -> 20 | F43: =SUMIFS(Pagamentos!$E:$E,Pagamentos!$F:$F,TRUE,Pagamentos!$C:$C,$C43,Pagamentos!$D:$D,F$2) -> 20 | G43: =SUMIFS(Pagamentos!$E:$E,Pagamentos!$F:$F,TRUE,Pagamentos!$C:$C,$C43,Pagamentos!$D:$D,G$2) -> 40 | H43: =SUMIFS(Pagamentos!$E:$E,Pagamentos!$F:$F,TRUE,Pagamentos!$C:$C,$C43,Pagamentos!$D:$D,H$2) -> 0 | I43: =SUMIFS(Pagamentos!$E:$E,Pagamentos!$F:$F,TRUE,Pagamentos!$C:$C,$C43,Pagamentos!$D:$D,I$2) -> 20 | J43: =SUMIFS(Pagamentos!$E:$E,Pagamentos!$F:$F,TRUE,Pagamentos!$C:$C,$C43,Pagamentos!$D:$D,J$2) -> 20 | K43: =SUMIFS(Pagamentos!$E:$E,Pagamentos!$F:$F,TRUE,Pagamentos!$C:$C,$C43,Pagamentos!$D:$D,K$2) -> 20 | L43: =SUMIFS(Pagamentos!$E:$E,Pagamentos!$F:$F,TRUE,Pagamentos!$C:$C,$C43,Pagamentos!$D:$D,L$2) -> 0 | ... P43: =SUMIFS(Pagamentos!$E:$E,Pagamentos!$F:$F,TRUE,Pagamentos!$C:$C,$C43,Pagamentos!$D:$D,P$2) -> 0 | Q43: 0 | R43: =IF(Q43="","",((SUM(E43:P43)-$S$2)/20)+Q43) -> -1 | S43: =IFERROR(__xludf.DUMMYFUNCTION("SPARKLINE(SUM(E43:P43),{""charttype"",""bar"";""max"",$S$2})"),"")
B44: {=IFERROR(INDEX(#REF!,MATCH(C44,#REF!,0)),"")} | C44: =IFERROR(__xludf.DUMMYFUNCTION("""COMPUTED_VALUE"""),"Fortkamp") -> Fortkamp | D44: =IFERROR(__xludf.DUMMYFUNCTION("""COMPUTED_VALUE"""),"Markian da Silveira Fortkamp") -> Markian da Silveira Fortkamp | E44: =SUMIFS(Pagamentos!$E:$E,Pagamentos!$F:$F,TRUE,Pagamentos!$C:$C,$C44,Pagamentos!$D:$D,E$2) -> 0 | F44: =SUMIFS(Pagamentos!$E:$E,Pagamentos!$F:$F,TRUE,Pagamentos!$C:$C,$C44,Pagamentos!$D:$D,F$2) -> 20 | G44: =SUMIFS(Pagamentos!$E:$E,Pagamentos!$F:$F,TRUE,Pagamentos!$C:$C,$C44,Pagamentos!$D:$D,G$2) -> 40 | H44: =SUMIFS(Pagamentos!$E:$E,Pagamentos!$F:$F,TRUE,Pagamentos!$C:$C,$C44,Pagamentos!$D:$D,H$2) -> 20 | I44: =SUMIFS(Pagamentos!$E:$E,Pagamentos!$F:$F,TRUE,Pagamentos!$C:$C,$C44,Pagamentos!$D:$D,I$2) -> 0 | J44: =SUMIFS(Pagamentos!$E:$E,Pagamentos!$F:$F,TRUE,Pagamentos!$C:$C,$C44,Pagamentos!$D:$D,J$2) -> 20 | K44: =SUMIFS(Pagamentos!$E:$E,Pagamentos!$F:$F,TRUE,Pagamentos!$C:$C,$C44,Pagamentos!$D:$D,K$2) -> 20 | L44: =SUMIFS(Pagamentos!$E:$E,Pagamentos!$F:$F,TRUE,Pagamentos!$C:$C,$C44,Pagamentos!$D:$D,L$2) -> 0 | ... P44: =SUMIFS(Pagamentos!$E:$E,Pagamentos!$F:$F,TRUE,Pagamentos!$C:$C,$C44,Pagamentos!$D:$D,P$2) -> 0 | Q44: 0 | R44: =IF(Q44="","",((SUM(E44:P44)-$S$2)/20)+Q44) -> -2 | S44: =IFERROR(__xludf.DUMMYFUNCTION("SPARKLINE(SUM(E44:P44),{""charttype"",""bar"";""max"",$S$2})"),"")
B45: {=IFERROR(INDEX(#REF!,MATCH(C45,#REF!,0)),"")} | C45: =IFERROR(__xludf.DUMMYFUNCTION("""COMPUTED_VALUE"""),"Jesus") -> Jesus | D45: =IFERROR(__xludf.DUMMYFUNCTION("""COMPUTED_VALUE"""),"Karina Maria de Jesus Sobrinho") -> Karina Maria de Jesus Sobrinho | E45: =SUMIFS(Pagamentos!$E:$E,Pagamentos!$F:$F,TRUE,Pagamentos!$C:$C,$C45,Pagamentos!$D:$D,E$2) -> 20 | F45: =SUMIFS(Pagamentos!$E:$E,Pagamentos!$F:$F,TRUE,Pagamentos!$C:$C,$C45,Pagamentos!$D:$D,F$2) -> 0 | G45: =SUMIFS(Pagamentos!$E:$E,Pagamentos!$F:$F,TRUE,Pagamentos!$C:$C,$C45,Pagamentos!$D:$D,G$2) -> 40 | H45: =SUMIFS(Pagamentos!$E:$E,Pagamentos!$F:$F,TRUE,Pagamentos!$C:$C,$C45,Pagamentos!$D:$D,H$2) -> 0 | I45: =SUMIFS(Pagamentos!$E:$E,Pagamentos!$F:$F,TRUE,Pagamentos!$C:$C,$C45,Pagamentos!$D:$D,I$2) -> 0 | J45: =SUMIFS(Pagamentos!$E:$E,Pagamentos!$F:$F,TRUE,Pagamentos!$C:$C,$C45,Pagamentos!$D:$D,J$2) -> 60 | K45: =SUMIFS(Pagamentos!$E:$E,Pagamentos!$F:$F,TRUE,Pagamentos!$C:$C,$C45,Pagamentos!$D:$D,K$2) -> 0 | L45: =SUMIFS(Pagamentos!$E:$E,Pagamentos!$F:$F,TRUE,Pagamentos!$C:$C,$C45,Pagamentos!$D:$D,L$2) -> 0 | ... P45: =SUMIFS(Pagamentos!$E:$E,Pagamentos!$F:$F,TRUE,Pagamentos!$C:$C,$C45,Pagamentos!$D:$D,P$2) -> 0 | Q45: 0 | R45: =IF(Q45="","",((SUM(E45:P45)-$S$2)/20)+Q45) -> -2 | S45: =IFERROR(__xludf.DUMMYFUNCTION("SPARKLINE(SUM(E45:P45),{""charttype"",""bar"";""max"",$S$2})"),"")
B46: {=IFERROR(INDEX(#REF!,MATCH(C46,#REF!,0)),"")} | C46: =IFERROR(__xludf.DUMMYFUNCTION("""COMPUTED_VALUE"""),"Nakata") -> Nakata | D46: =IFERROR(__xludf.DUMMYFUNCTION("""COMPUTED_VALUE"""),"Nakata Garra Gomes") -> Nakata Garra Gomes | E46: =SUMIFS(Pagamentos!$E:$E,Pagamentos!$F:$F,TRUE,Pagamentos!$C:$C,$C46,Pagamentos!$D:$D,E$2) -> 40 | F46: =SUMIFS(Pagamentos!$E:$E,Pagamentos!$F:$F,TRUE,Pagamentos!$C:$C,$C46,Pagamentos!$D:$D,F$2) -> 20 | G46: =SUMIFS(Pagamentos!$E:$E,Pagamentos!$F:$F,TRUE,Pagamentos!$C:$C,$C46,Pagamentos!$D:$D,G$2) -> 20 | H46: =SUMIFS(Pagamentos!$E:$E,Pagamentos!$F:$F,TRUE,Pagamentos!$C:$C,$C46,Pagamentos!$D:$D,H$2) -> 20 | I46: =SUMIFS(Pagamentos!$E:$E,Pagamentos!$F:$F,TRUE,Pagamentos!$C:$C,$C46,Pagamentos!$D:$D,I$2) -> 0 | J46: =SUMIFS(Pagamentos!$E:$E,Pagamentos!$F:$F,TRUE,Pagamentos!$C:$C,$C46,Pagamentos!$D:$D,J$2) -> 0 | K46: =SUMIFS(Pagamentos!$E:$E,Pagamentos!$F:$F,TRUE,Pagamentos!$C:$C,$C46,Pagamentos!$D:$D,K$2) -> 0 | L46: =SUMIFS(Pagamentos!$E:$E,Pagamentos!$F:$F,TRUE,Pagamentos!$C:$C,$C46,Pagamentos!$D:$D,L$2) -> 0 | ... P46: =SUMIFS(Pagamentos!$E:$E,Pagamentos!$F:$F,TRUE,Pagamentos!$C:$C,$C46,Pagamentos!$D:$D,P$2) -> 0 | Q46: -1 | R46: =IF(Q46="","",((SUM(E46:P46)-$S$2)/20)+Q46) -> -4 | S46: =IFERROR(__xludf.DUMMYFUNCTION("SPARKLINE(SUM(E46:P46),{""charttype"",""bar"";""max"",$S$2})"),"")
B47: {=IFERROR(INDEX(#REF!,MATCH(C47,#REF!,0)),"")} | C47: =IFERROR(__xludf.DUMMYFUNCTION("""COMPUTED_VALUE"""),"Weverton ") -> Weverton | D47: =IFERROR(__xludf.DUMMYFUNCTION("""COMPUTED_VALUE"""),"Weverton José Machado ") -> Weverton José Machado | E47: =SUMIFS(Pagamentos!$E:$E,Pagamentos!$F:$F,TRUE,Pagamentos!$C:$C,$C47,Pagamentos!$D:$D,E$2) -> 0 | F47: =SUMIFS(Pagamentos!$E:$E,Pagamentos!$F:$F,TRUE,Pagamentos!$C:$C,$C47,Pagamentos!$D:$D,F$2) -> 0 | G47: =SUMIFS(Pagamentos!$E:$E,Pagamentos!$F:$F,TRUE,Pagamentos!$C:$C,$C47,Pagamentos!$D:$D,G$2) -> 100 | H47: =SUMIFS(Pagamentos!$E:$E,Pagamentos!$F:$F,TRUE,Pagamentos!$C:$C,$C47,Pagamentos!$D:$D,H$2) -> 0 | I47: =SUMIFS(Pagamentos!$E:$E,Pagamentos!$F:$F,TRUE,Pagamentos!$C:$C,$C47,Pagamentos!$D:$D,I$2) -> 0 | J47: =SUMIFS(Pagamentos!$E:$E,Pagamentos!$F:$F,TRUE,Pagamentos!$C:$C,$C47,Pagamentos!$D:$D,J$2) -> 0 | K47: =SUMIFS(Pagamentos!$E:$E,Pagamentos!$F:$F,TRUE,Pagamentos!$C:$C,$C47,Pagamentos!$D:$D,K$2) -> 0 | L47: =SUMIFS(Pagamentos!$E:$E,Pagamentos!$F:$F,TRUE,Pagamentos!$C:$C,$C47,Pagamentos!$D:$D,L$2) -> 0 | ... P47: =SUMIFS(Pagamentos!$E:$E,Pagamentos!$F:$F,TRUE,Pagamentos!$C:$C,$C47,Pagamentos!$D:$D,P$2) -> 0 | Q47: -2 | R47: =IF(Q47="","",((SUM(E47:P47)-$S$2)/20)+Q47) -> -5 | S47: =IFERROR(__xludf.DUMMYFUNCTION("SPARKLINE(SUM(E47:P47),{""charttype"",""bar"";""max"",$S$2})"),"")
B48: {=IFERROR(INDEX(#REF!,MATCH(C48,#REF!,0)),"")} | C48: =IFERROR(__xludf.DUMMYFUNCTION("""COMPUTED_VALUE"""),"Martins") -> Martins | D48: =IFERROR(__xludf.DUMMYFUNCTION("""COMPUTED_VALUE"""),"Alexandre Vinicius Martins ") -> Alexandre Vinicius Martins | E48: =SUMIFS(Pagamentos!$E:$E,Pagamentos!$F:$F,TRUE,Pagamentos!$C:$C,$C48,Pagamentos!$D:$D,E$2) -> 20 | F48: =SUMIFS(Pagamentos!$E:$E,Pagamentos!$F:$F,TRUE,Pagamentos!$C:$C,$C48,Pagamentos!$D:$D,F$2) -> 20 | G48: =SUMIFS(Pagamentos!$E:$E,Pagamentos!$F:$F,TRUE,Pagamentos!$C:$C,$C48,Pagamentos!$D:$D,G$2) -> 20 | H48: =SUMIFS(Pagamentos!$E:$E,Pagamentos!$F:$F,TRUE,Pagamentos!$C:$C,$C48,Pagamentos!$D:$D,H$2) -> 40 | I48: =SUMIFS(Pagamentos!$E:$E,Pagamentos!$F:$F,TRUE,Pagamentos!$C:$C,$C48,Pagamentos!$D:$D,I$2) -> 20 | J48: =SUMIFS(Pagamentos!$E:$E,Pagamentos!$F:$F,TRUE,Pagamentos!$C:$C,$C48,Pagamentos!$D:$D,J$2) -> 20 | K48: =SUMIFS(Pagamentos!$E:$E,Pagamentos!$F:$F,TRUE,Pagamentos!$C:$C,$C48,Pagamentos!$D:$D,K$2) -> 20 | L48: =SUMIFS(Pagamentos!$E:$E,Pagamentos!$F:$F,TRUE,Pagamentos!$C:$C,$C48,Pagamentos!$D:$D,L$2) -> 0 | ... P48: =SUMIFS(Pagamentos!$E:$E,Pagamentos!$F:$F,TRUE,Pagamentos!$C:$C,$C48,Pagamentos!$D:$D,P$2) -> 0 | Q48: -1 | R48: =IF(Q48="","",((SUM(E48:P48)-$S$2)/20)+Q48) -> -1 | S48: =IFERROR(__xludf.DUMMYFUNCTION("SPARKLINE(SUM(E48:P48),{""charttype"",""bar"";""max"",$S$2})"),"")
B49: {=IFERROR(INDEX(#REF!,MATCH(C49,#REF!,0)),"")} | C49: =IFERROR(__xludf.DUMMYFUNCTION("""COMPUTED_VALUE"""),"Ana Carolina ") -> Ana Carolina | D49: =IFERROR(__xludf.DUMMYFUNCTION("""COMPUTED_VALUE"""),"Ana Carolina Nascimento ") -> Ana Carolina Nascimento | E49: =SUMIFS(Pagamentos!$E:$E,Pagamentos!$F:$F,TRUE,Pagamentos!$C:$C,$C49,Pagamentos!$D:$D,E$2) -> 0 | F49: =SUMIFS(Pagamentos!$E:$E,Pagamentos!$F:$F,TRUE,Pagamentos!$C:$C,$C49,Pagamentos!$D:$D,F$2) -> 60 | G49: =SUMIFS(Pagamentos!$E:$E,Pagamentos!$F:$F,TRUE,Pagamentos!$C:$C,$C49,Pagamentos!$D:$D,G$2) -> 20 | H49: =SUMIFS(Pagamentos!$E:$E,Pagamentos!$F:$F,TRUE,Pagamentos!$C:$C,$C49,Pagamentos!$D:$D,H$2) -> 40 | I49: =SUMIFS(Pagamentos!$E:$E,Pagamentos!$F:$F,TRUE,Pagamentos!$C:$C,$C49,Pagamentos!$D:$D,I$2) -> 0 | J49: =SUMIFS(Pagamentos!$E:$E,Pagamentos!$F:$F,TRUE,Pagamentos!$C:$C,$C49,Pagamentos!$D:$D,J$2) -> 20 | K49: =SUMIFS(Pagamentos!$E:$E,Pagamentos!$F:$F,TRUE,Pagamentos!$C:$C,$C49,Pagamentos!$D:$D,K$2) -> 0 | L49: =SUMIFS(Pagamentos!$E:$E,Pagamentos!$F:$F,TRUE,Pagamentos!$C:$C,$C49,Pagamentos!$D:$D,L$2) -> 0 | ... P49: =SUMIFS(Pagamentos!$E:$E,Pagamentos!$F:$F,TRUE,Pagamentos!$C:$C,$C49,Pagamentos!$D:$D,P$2) -> 0 | Q49: 0 | R49: =IF(Q49="","",((SUM(E49:P49)-$S$2)/20)+Q49) -> -1 | S49: =IFERROR(__xludf.DUMMYFUNCTION("SPARKLINE(SUM(E49:P49),{""charttype"",""bar"";""max"",$S$2})"),"")
B50: {=IFERROR(INDEX(#REF!,MATCH(C50,#REF!,0)),"")} | C50: =IFERROR(__xludf.DUMMYFUNCTION("""COMPUTED_VALUE"""),"Andréia M") -> Andréia M | D50: =IFERROR(__xludf.DUMMYFUNCTION("""COMPUTED_VALUE"""),"Andréia Martins dos Santos") -> Andréia Martins dos Santos | E50: =SUMIFS(Pagamentos!$E:$E,Pagamentos!$F:$F,TRUE,Pagamentos!$C:$C,$C50,Pagamentos!$D:$D,E$2) -> 0 | F50: =SUMIFS(Pagamentos!$E:$E,Pagamentos!$F:$F,TRUE,Pagamentos!$C:$C,$C50,Pagamentos!$D:$D,F$2) -> 40 | G50: =SUMIFS(Pagamentos!$E:$E,Pagamentos!$F:$F,TRUE,Pagamentos!$C:$C,$C50,Pagamentos!$D:$D,G$2) -> 20 | H50: =SUMIFS(Pagamentos!$E:$E,Pagamentos!$F:$F,TRUE,Pagamentos!$C:$C,$C50,Pagamentos!$D:$D,H$2) -> 20 | I50: =SUMIFS(Pagamentos!$E:$E,Pagamentos!$F:$F,TRUE,Pagamentos!$C:$C,$C50,Pagamentos!$D:$D,I$2) -> 20 | J50: =SUMIFS(Pagamentos!$E:$E,Pagamentos!$F:$F,TRUE,Pagamentos!$C:$C,$C50,Pagamentos!$D:$D,J$2) -> 20 | K50: =SUMIFS(Pagamentos!$E:$E,Pagamentos!$F:$F,TRUE,Pagamentos!$C:$C,$C50,Pagamentos!$D:$D,K$2) -> 20 | L50: =SUMIFS(Pagamentos!$E:$E,Pagamentos!$F:$F,TRUE,Pagamentos!$C:$C,$C50,Pagamentos!$D:$D,L$2) -> 20 | ... P50: =SUMIFS(Pagamentos!$E:$E,Pagamentos!$F:$F,TRUE,Pagamentos!$C:$C,$C50,Pagamentos!$D:$D,P$2) -> 0 | Q50: 0 | R50: =IF(Q50="","",((SUM(E50:P50)-$S$2)/20)+Q50) -> 0 | S50: =IFERROR(__xludf.DUMMYFUNCTION("SPARKLINE(SUM(E50:P50),{""charttype"",""bar"";""max"",$S$2})"),"")
B51: {=IFERROR(INDEX(#REF!,MATCH(C51,#REF!,0)),"")} | C51: =IFERROR(__xludf.DUMMYFUNCTION("""COMPUTED_VALUE"""),"Siqueira") -> Siqueira | D51: =IFERROR(__xludf.DUMMYFUNCTION("""COMPUTED_VALUE"""),"Fernando Pereira Siqueira Junior ") -> Fernando Pereira Siqueira Junior | E51: =SUMIFS(Pagamentos!$E:$E,Pagamentos!$F:$F,TRUE,Pagamentos!$C:$C,$C51,Pagamentos!$D:$D,E$2) -> 20 | F51: =SUMIFS(Pagamentos!$E:$E,Pagamentos!$F:$F,TRUE,Pagamentos!$C:$C,$C51,Pagamentos!$D:$D,F$2) -> 20 | G51: =SUMIFS(Pagamentos!$E:$E,Pagamentos!$F:$F,TRUE,Pagamentos!$C:$C,$C51,Pagamentos!$D:$D,G$2) -> 20 | H51: =SUMIFS(Pagamentos!$E:$E,Pagamentos!$F:$F,TRUE,Pagamentos!$C:$C,$C51,Pagamentos!$D:$D,H$2) -> 20 | I51: =SUMIFS(Pagamentos!$E:$E,Pagamentos!$F:$F,TRUE,Pagamentos!$C:$C,$C51,Pagamentos!$D:$D,I$2) -> 20 | J51: =SUMIFS(Pagamentos!$E:$E,Pagamentos!$F:$F,TRUE,Pagamentos!$C:$C,$C51,Pagamentos!$D:$D,J$2) -> 20 | K51: =SUMIFS(Pagamentos!$E:$E,Pagamentos!$F:$F,TRUE,Pagamentos!$C:$C,$C51,Pagamentos!$D:$D,K$2) -> 20 | L51: =SUMIFS(Pagamentos!$E:$E,Pagamentos!$F:$F,TRUE,Pagamentos!$C:$C,$C51,Pagamentos!$D:$D,L$2) -> 0 | ... P51: =SUMIFS(Pagamentos!$E:$E,Pagamentos!$F:$F,TRUE,Pagamentos!$C:$C,$C51,Pagamentos!$D:$D,P$2) -> 0 | Q51: 1 | R51: =IF(Q51="","",((SUM(E51:P51)-$S$2)/20)+Q51) -> 0 | S51: =IFERROR(__xludf.DUMMYFUNCTION("SPARKLINE(SUM(E51:P51),{""charttype"",""bar"";""max"",$S$2})"),"")
B52: {=IFERROR(INDEX(#REF!,MATCH(C52,#REF!,0)),"")} | C52: =IFERROR(__xludf.DUMMYFUNCTION("""COMPUTED_VALUE"""),"Gonçalves ") -> Gonçalves | D52: =IFERROR(__xludf.DUMMYFUNCTION("""COMPUTED_VALUE"""),"Alessandro da Costa Gonçalves ") -> Alessandro da Costa Gonçalves | E52: =SUMIFS(Pagamentos!$E:$E,Pagamentos!$F:$F,TRUE,Pagamentos!$C:$C,$C52,Pagamentos!$D:$D,E$2) -> 0 | F52: =SUMIFS(Pagamentos!$E:$E,Pagamentos!$F:$F,TRUE,Pagamentos!$C:$C,$C52,Pagamentos!$D:$D,F$2) -> 0 | G52: =SUMIFS(Pagamentos!$E:$E,Pagamentos!$F:$F,TRUE,Pagamentos!$C:$C,$C52,Pagamentos!$D:$D,G$2) -> 0 | H52: =SUMIFS(Pagamentos!$E:$E,Pagamentos!$F:$F,TRUE,Pagamentos!$C:$C,$C52,Pagamentos!$D:$D,H$2) -> 0 | I52: =SUMIFS(Pagamentos!$E:$E,Pagamentos!$F:$F,TRUE,Pagamentos!$C:$C,$C52,Pagamentos!$D:$D,I$2) -> 100 | J52: =SUMIFS(Pagamentos!$E:$E,Pagamentos!$F:$F,TRUE,Pagamentos!$C:$C,$C52,Pagamentos!$D:$D,J$2) -> 0 | K52: =SUMIFS(Pagamentos!$E:$E,Pagamentos!$F:$F,TRUE,Pagamentos!$C:$C,$C52,Pagamentos!$D:$D,K$2) -> 0 | L52: =SUMIFS(Pagamentos!$E:$E,Pagamentos!$F:$F,TRUE,Pagamentos!$C:$C,$C52,Pagamentos!$D:$D,L$2) -> 0 | ... P52: =SUMIFS(Pagamentos!$E:$E,Pagamentos!$F:$F,TRUE,Pagamentos!$C:$C,$C52,Pagamentos!$D:$D,P$2) -> 0 | Q52: 0 | R52: =IF(Q52="","",((SUM(E52:P52)-$S$2)/20)+Q52) -> -3 | S52: =IFERROR(__xludf.DUMMYFUNCTION("SPARKLINE(SUM(E52:P52),{""charttype"",""bar"";""max"",$S$2})"),"")
B53: {=IFERROR(INDEX(#REF!,MATCH(C53,#REF!,0)),"")} | C53: =IFERROR(__xludf.DUMMYFUNCTION("""COMPUTED_VALUE"""),"Neumann ") -> Neumann | D53: =IFERROR(__xludf.DUMMYFUNCTION("""COMPUTED_VALUE"""),"Misael Dias Neumann ") -> Misael Dias Neumann | E53: =SUMIFS(Pagamentos!$E:$E,Pagamentos!$F:$F,TRUE,Pagamentos!$C:$C,$C53,Pagamentos!$D:$D,E$2) -> 20 | F53: =SUMIFS(Pagamentos!$E:$E,Pagamentos!$F:$F,TRUE,Pagamentos!$C:$C,$C53,Pagamentos!$D:$D,F$2) -> 20 | G53: =SUMIFS(Pagamentos!$E:$E,Pagamentos!$F:$F,TRUE,Pagamentos!$C:$C,$C53,Pagamentos!$D:$D,G$2) -> 20 | H53: =SUMIFS(Pagamentos!$E:$E,Pagamentos!$F:$F,TRUE,Pagamentos!$C:$C,$C53,Pagamentos!$D:$D,H$2) -> 0 | I53: =SUMIFS(Pagamentos!$E:$E,Pagamentos!$F:$F,TRUE,Pagamentos!$C:$C,$C53,Pagamentos!$D:$D,I$2) -> 20 | J53: =SUMIFS(Pagamentos!$E:$E,Pagamentos!$F:$F,TRUE,Pagamentos!$C:$C,$C53,Pagamentos!$D:$D,J$2) -> 0 | K53: =SUMIFS(Pagamentos!$E:$E,Pagamentos!$F:$F,TRUE,Pagamentos!$C:$C,$C53,Pagamentos!$D:$D,K$2) -> 0 | L53: =SUMIFS(Pagamentos!$E:$E,Pagamentos!$F:$F,TRUE,Pagamentos!$C:$C,$C53,Pagamentos!$D:$D,L$2) -> 20 | ... P53: =SUMIFS(Pagamentos!$E:$E,Pagamentos!$F:$F,TRUE,Pagamentos!$C:$C,$C53,Pagamentos!$D:$D,P$2) -> 0 | Q53: 1 | R53: =IF(Q53="","",((SUM(E53:P53)-$S$2)/20)+Q53) -> -2 | S53: =IFERROR(__xludf.DUMMYFUNCTION("SPARKLINE(SUM(E53:P53),{""charttype"",""bar"";""max"",$S$2})"),"")
B54: {=IFERROR(INDEX(#REF!,MATCH(C54,#REF!,0)),"")} | C54: =IFERROR(__xludf.DUMMYFUNCTION("""COMPUTED_VALUE"""),"Luiz") -> Luiz | D54: =IFERROR(__xludf.DUMMYFUNCTION("""COMPUTED_VALUE"""),"Luiz Fernando da Silva ") -> Luiz Fernando da Silva | E54: =SUMIFS(Pagamentos!$E:$E,Pagamentos!$F:$F,TRUE,Pagamentos!$C:$C,$C54,Pagamentos!$D:$D,E$2) -> 20 | F54: =SUMIFS(Pagamentos!$E:$E,Pagamentos!$F:$F,TRUE,Pagamentos!$C:$C,$C54,Pagamentos!$D:$D,F$2) -> 20 | G54: =SUMIFS(Pagamentos!$E:$E,Pagamentos!$F:$F,TRUE,Pagamentos!$C:$C,$C54,Pagamentos!$D:$D,G$2) -> 20 | H54: =SUMIFS(Pagamentos!$E:$E,Pagamentos!$F:$F,TRUE,Pagamentos!$C:$C,$C54,Pagamentos!$D:$D,H$2) -> 20 | I54: =SUMIFS(Pagamentos!$E:$E,Pagamentos!$F:$F,TRUE,Pagamentos!$C:$C,$C54,Pagamentos!$D:$D,I$2) -> 20 | J54: =SUMIFS(Pagamentos!$E:$E,Pagamentos!$F:$F,TRUE,Pagamentos!$C:$C,$C54,Pagamentos!$D:$D,J$2) -> 20 | K54: =SUMIFS(Pagamentos!$E:$E,Pagamentos!$F:$F,TRUE,Pagamentos!$C:$C,$C54,Pagamentos!$D:$D,K$2) -> 20 | L54: =SUMIFS(Pagamentos!$E:$E,Pagamentos!$F:$F,TRUE,Pagamentos!$C:$C,$C54,Pagamentos!$D:$D,L$2) -> 20 | ... P54: =SUMIFS(Pagamentos!$E:$E,Pagamentos!$F:$F,TRUE,Pagamentos!$C:$C,$C54,Pagamentos!$D:$D,P$2) -> 0 | Q54: 0 | R54: =IF(Q54="","",((SUM(E54:P54)-$S$2)/20)+Q54) -> 0 | S54: =IFERROR(__xludf.DUMMYFUNCTION("SPARKLINE(SUM(E54:P54),{""charttype"",""bar"";""max"",$S$2})"),"")
B55: {=IFERROR(INDEX(#REF!,MATCH(C55,#REF!,0)),"")} | C55: =IFERROR(__xludf.DUMMYFUNCTION("""COMPUTED_VALUE"""),"Figueiredo") -> Figueiredo | D55: =IFERROR(__xludf.DUMMYFUNCTION("""COMPUTED_VALUE"""),"João Victor Figueiredo Chrostowski") -> João Victor Figueiredo Chrostowski | E55: =SUMIFS(Pagamentos!$E:$E,Pagamentos!$F:$F,TRUE,Pagamentos!$C:$C,$C55,Pagamentos!$D:$D,E$2) -> 0 | F55: =SUMIFS(Pagamentos!$E:$E,Pagamentos!$F:$F,TRUE,Pagamentos!$C:$C,$C55,Pagamentos!$D:$D,F$2) -> 20 | G55: =SUMIFS(Pagamentos!$E:$E,Pagamentos!$F:$F,TRUE,Pagamentos!$C:$C,$C55,Pagamentos!$D:$D,G$2) -> 20 | H55: =SUMIFS(Pagamentos!$E:$E,Pagamentos!$F:$F,TRUE,Pagamentos!$C:$C,$C55,Pagamentos!$D:$D,H$2) -> 0 | I55: =SUMIFS(Pagamentos!$E:$E,Pagamentos!$F:$F,TRUE,Pagamentos!$C:$C,$C55,Pagamentos!$D:$D,I$2) -> 20 | J55: =SUMIFS(Pagamentos!$E:$E,Pagamentos!$F:$F,TRUE,Pagamentos!$C:$C,$C55,Pagamentos!$D:$D,J$2) -> 40 | K55: =SUMIFS(Pagamentos!$E:$E,Pagamentos!$F:$F,TRUE,Pagamentos!$C:$C,$C55,Pagamentos!$D:$D,K$2) -> 0 | L55: =SUMIFS(Pagamentos!$E:$E,Pagamentos!$F:$F,TRUE,Pagamentos!$C:$C,$C55,Pagamentos!$D:$D,L$2) -> 0 | ... P55: =SUMIFS(Pagamentos!$E:$E,Pagamentos!$F:$F,TRUE,Pagamentos!$C:$C,$C55,Pagamentos!$D:$D,P$2) -> 0 | Q55: 1 | R55: =IF(Q55="","",((SUM(E55:P55)-$S$2)/20)+Q55) -> -2 | S55: =IFERROR(__xludf.DUMMYFUNCTION("SPARKLINE(SUM(E55:P55),{""charttype"",""bar"";""max"",$S$2})"),"")
B56: {=IFERROR(INDEX(#REF!,MATCH(C56,#REF!,0)),"")} | C56: =IFERROR(__xludf.DUMMYFUNCTION("""COMPUTED_VALUE"""),"Luciano") -> Luciano | D56: =IFERROR(__xludf.DUMMYFUNCTION("""COMPUTED_VALUE"""),"LUCIANO PEREIRA") -> LUCIANO PEREIRA | E56: =SUMIFS(Pagamentos!$E:$E,Pagamentos!$F:$F,TRUE,Pagamentos!$C:$C,$C56,Pagamentos!$D:$D,E$2) -> 0 | F56: =SUMIFS(Pagamentos!$E:$E,Pagamentos!$F:$F,TRUE,Pagamentos!$C:$C,$C56,Pagamentos!$D:$D,F$2) -> 0 | G56: =SUMIFS(Pagamentos!$E:$E,Pagamentos!$F:$F,TRUE,Pagamentos!$C:$C,$C56,Pagamentos!$D:$D,G$2) -> 40 | H56: =SUMIFS(Pagamentos!$E:$E,Pagamentos!$F:$F,TRUE,Pagamentos!$C:$C,$C56,Pagamentos!$D:$D,H$2) -> 0 | I56: =SUMIFS(Pagamentos!$E:$E,Pagamentos!$F:$F,TRUE,Pagamentos!$C:$C,$C56,Pagamentos!$D:$D,I$2) -> 80 | J56: =SUMIFS(Pagamentos!$E:$E,Pagamentos!$F:$F,TRUE,Pagamentos!$C:$C,$C56,Pagamentos!$D:$D,J$2) -> 60 | K56: =SUMIFS(Pagamentos!$E:$E,Pagamentos!$F:$F,TRUE,Pagamentos!$C:$C,$C56,Pagamentos!$D:$D,K$2) -> 0 | L56: =SUMIFS(Pagamentos!$E:$E,Pagamentos!$F:$F,TRUE,Pagamentos!$C:$C,$C56,Pagamentos!$D:$D,L$2) -> 0 | ... P56: =SUMIFS(Pagamentos!$E:$E,Pagamentos!$F:$F,TRUE,Pagamentos!$C:$C,$C56,Pagamentos!$D:$D,P$2) -> 0 | Q56: 1 | R56: =IF(Q56="","",((SUM(E56:P56)-$S$2)/20)+Q56) -> 2 | S56: =IFERROR(__xludf.DUMMYFUNCTION("SPARKLINE(SUM(E56:P56),{""charttype"",""bar"";""max"",$S$2})"),"")
B57: {=IFERROR(INDEX(#REF!,MATCH(C57,#REF!,0)),"")} | C57: =IFERROR(__xludf.DUMMYFUNCTION("""COMPUTED_VALUE"""),"Cardoso") -> Cardoso | D57: =IFERROR(__xludf.DUMMYFUNCTION("""COMPUTED_VALUE"""),"Claudio cardoso") -> Claudio cardoso | E57: =SUMIFS(Pagamentos!$E:$E,Pagamentos!$F:$F,TRUE,Pagamentos!$C:$C,$C57,Pagamentos!$D:$D,E$2) -> 0 | F57: =SUMIFS(Pagamentos!$E:$E,Pagamentos!$F:$F,TRUE,Pagamentos!$C:$C,$C57,Pagamentos!$D:$D,F$2) -> 20 | G57: =SUMIFS(Pagamentos!$E:$E,Pagamentos!$F:$F,TRUE,Pagamentos!$C:$C,$C57,Pagamentos!$D:$D,G$2) -> 20 | H57: =SUMIFS(Pagamentos!$E:$E,Pagamentos!$F:$F,TRUE,Pagamentos!$C:$C,$C57,Pagamentos!$D:$D,H$2) -> 20 | I57: =SUMIFS(Pagamentos!$E:$E,Pagamentos!$F:$F,TRUE,Pagamentos!$C:$C,$C57,Pagamentos!$D:$D,I$2) -> 0 | J57: =SUMIFS(Pagamentos!$E:$E,Pagamentos!$F:$F,TRUE,Pagamentos!$C:$C,$C57,Pagamentos!$D:$D,J$2) -> 80 | K57: =SUMIFS(Pagamentos!$E:$E,Pagamentos!$F:$F,TRUE,Pagamentos!$C:$C,$C57,Pagamentos!$D:$D,K$2) -> 0 | L57: =SUMIFS(Pagamentos!$E:$E,Pagamentos!$F:$F,TRUE,Pagamentos!$C:$C,$C57,Pagamentos!$D:$D,L$2) -> 0 | ... P57: =SUMIFS(Pagamentos!$E:$E,Pagamentos!$F:$F,TRUE,Pagamentos!$C:$C,$C57,Pagamentos!$D:$D,P$2) -> 0 | Q57: 1 | R57: =IF(Q57="","",((SUM(E57:P57)-$S$2)/20)+Q57) -> 0 | S57: =IFERROR(__xludf.DUMMYFUNCTION("SPARKLINE(SUM(E57:P57),{""charttype"",""bar"";""max"",$S$2})"),"")
B58: {=IFERROR(INDEX(#REF!,MATCH(C58,#REF!,0)),"")} | C58: =IFERROR(__xludf.DUMMYFUNCTION("""COMPUTED_VALUE"""),"Carvalho ") -> Carvalho | D58: =IFERROR(__xludf.DUMMYFUNCTION("""COMPUTED_VALUE"""),"Diego Carvalho Cordova ") -> Diego Carvalho Cordova | E58: =SUMIFS(Pagamentos!$E:$E,Pagamentos!$F:$F,TRUE,Pagamentos!$C:$C,$C58,Pagamentos!$D:$D,E$2) -> 0 | F58: =SUMIFS(Pagamentos!$E:$E,Pagamentos!$F:$F,TRUE,Pagamentos!$C:$C,$C58,Pagamentos!$D:$D,F$2) -> 20 | G58: =SUMIFS(Pagamentos!$E:$E,Pagamentos!$F:$F,TRUE,Pagamentos!$C:$C,$C58,Pagamentos!$D:$D,G$2) -> 20 | H58: =SUMIFS(Pagamentos!$E:$E,Pagamentos!$F:$F,TRUE,Pagamentos!$C:$C,$C58,Pagamentos!$D:$D,H$2) -> 0 | I58: =SUMIFS(Pagamentos!$E:$E,Pagamentos!$F:$F,TRUE,Pagamentos!$C:$C,$C58,Pagamentos!$D:$D,I$2) -> 0 | J58: =SUMIFS(Pagamentos!$E:$E,Pagamentos!$F:$F,TRUE,Pagamentos!$C:$C,$C58,Pagamentos!$D:$D,J$2) -> 0 | K58: =SUMIFS(Pagamentos!$E:$E,Pagamentos!$F:$F,TRUE,Pagamentos!$C:$C,$C58,Pagamentos!$D:$D,K$2) -> 0 | L58: =SUMIFS(Pagamentos!$E:$E,Pagamentos!$F:$F,TRUE,Pagamentos!$C:$C,$C58,Pagamentos!$D:$D,L$2) -> 0 | ... P58: =SUMIFS(Pagamentos!$E:$E,Pagamentos!$F:$F,TRUE,Pagamentos!$C:$C,$C58,Pagamentos!$D:$D,P$2) -> 0 | Q58: 1 | R58: =IF(Q58="","",((SUM(E58:P58)-$S$2)/20)+Q58) -> -5 | S58: =IFERROR(__xludf.DUMMYFUNCTION("SPARKLINE(SUM(E58:P58),{""charttype"",""bar"";""max"",$S$2})"),"")
B59: {=IFERROR(INDEX(#REF!,MATCH(C59,#REF!,0)),"")} | C59: =IFERROR(__xludf.DUMMYFUNCTION("""COMPUTED_VALUE"""),"Bunn") -> Bunn | D59: =IFERROR(__xludf.DUMMYFUNCTION("""COMPUTED_VALUE"""),"João Pedro Pereira Bunn") -> João Pedro Pereira Bunn | E59: =SUMIFS(Pagamentos!$E:$E,Pagamentos!$F:$F,TRUE,Pagamentos!$C:$C,$C59,Pagamentos!$D:$D,E$2) -> 0 | F59: =SUMIFS(Pagamentos!$E:$E,Pagamentos!$F:$F,TRUE,Pagamentos!$C:$C,$C59,Pagamentos!$D:$D,F$2) -> 0 | G59: =SUMIFS(Pagamentos!$E:$E,Pagamentos!$F:$F,TRUE,Pagamentos!$C:$C,$C59,Pagamentos!$D:$D,G$2) -> 40 | H59: =SUMIFS(Pagamentos!$E:$E,Pagamentos!$F:$F,TRUE,Pagamentos!$C:$C,$C59,Pagamentos!$D:$D,H$2) -> 20 | I59: =SUMIFS(Pagamentos!$E:$E,Pagamentos!$F:$F,TRUE,Pagamentos!$C:$C,$C59,Pagamentos!$D:$D,I$2) -> 20 | J59: =SUMIFS(Pagamentos!$E:$E,Pagamentos!$F:$F,TRUE,Pagamentos!$C:$C,$C59,Pagamentos!$D:$D,J$2) -> 20 | K59: =SUMIFS(Pagamentos!$E:$E,Pagamentos!$F:$F,TRUE,Pagamentos!$C:$C,$C59,Pagamentos!$D:$D,K$2) -> 20 | L59: =SUMIFS(Pagamentos!$E:$E,Pagamentos!$F:$F,TRUE,Pagamentos!$C:$C,$C59,Pagamentos!$D:$D,L$2) -> 0 | ... P59: =SUMIFS(Pagamentos!$E:$E,Pagamentos!$F:$F,TRUE,Pagamentos!$C:$C,$C59,Pagamentos!$D:$D,P$2) -> 0 | Q59: 1 | R59: =IF(Q59="","",((SUM(E59:P59)-$S$2)/20)+Q59) -> -1 | S59: =IFERROR(__xludf.DUMMYFUNCTION("SPARKLINE(SUM(E59:P59),{""charttype"",""bar"";""max"",$S$2})"),"")
B60: {=IFERROR(INDEX(#REF!,MATCH(C60,#REF!,0)),"")} | C60: =IFERROR(__xludf.DUMMYFUNCTION("""COMPUTED_VALUE"""),"Costa ") -> Costa | D60: =IFERROR(__xludf.DUMMYFUNCTION("""COMPUTED_VALUE"""),"Vanessa David Costa ") -> Vanessa David Costa | E60: =SUMIFS(Pagamentos!$E:$E,Pagamentos!$F:$F,TRUE,Pagamentos!$C:$C,$C60,Pagamentos!$D:$D,E$2) -> 0 | F60: =SUMIFS(Pagamentos!$E:$E,Pagamentos!$F:$F,TRUE,Pagamentos!$C:$C,$C60,Pagamentos!$D:$D,F$2) -> 0 | G60: =SUMIFS(Pagamentos!$E:$E,Pagamentos!$F:$F,TRUE,Pagamentos!$C:$C,$C60,Pagamentos!$D:$D,G$2) -> 20 | H60: =SUMIFS(Pagamentos!$E:$E,Pagamentos!$F:$F,TRUE,Pagamentos!$C:$C,$C60,Pagamentos!$D:$D,H$2) -> 40 | I60: =SUMIFS(Pagamentos!$E:$E,Pagamentos!$F:$F,TRUE,Pagamentos!$C:$C,$C60,Pagamentos!$D:$D,I$2) -> 0 | J60: =SUMIFS(Pagamentos!$E:$E,Pagamentos!$F:$F,TRUE,Pagamentos!$C:$C,$C60,Pagamentos!$D:$D,J$2) -> 20 | K60: =SUMIFS(Pagamentos!$E:$E,Pagamentos!$F:$F,TRUE,Pagamentos!$C:$C,$C60,Pagamentos!$D:$D,K$2) -> 20 | L60: =SUMIFS(Pagamentos!$E:$E,Pagamentos!$F:$F,TRUE,Pagamentos!$C:$C,$C60,Pagamentos!$D:$D,L$2) -> 0 | ... P60: =SUMIFS(Pagamentos!$E:$E,Pagamentos!$F:$F,TRUE,Pagamentos!$C:$C,$C60,Pagamentos!$D:$D,P$2) -> 0 | Q60: 1 | R60: =IF(Q60="","",((SUM(E60:P60)-$S$2)/20)+Q60) -> -2 | S60: =IFERROR(__xludf.DUMMYFUNCTION("SPARKLINE(SUM(E60:P60),{""charttype"",""bar"";""max"",$S$2})"),"")
B61: {=IFERROR(INDEX(#REF!,MATCH(C61,#REF!,0)),"")} | C61: =IFERROR(__xludf.DUMMYFUNCTION("""COMPUTED_VALUE"""),"Sofie") -> Sofie | D61: =IFERROR(__xludf.DUMMYFUNCTION("""COMPUTED_VALUE"""),"Izabelle Sofie Luiz ") -> Izabelle Sofie Luiz | E61: =SUMIFS(Pagamentos!$E:$E,Pagamentos!$F:$F,TRUE,Pagamentos!$C:$C,$C61,Pagamentos!$D:$D,E$2) -> 0 | F61: =SUMIFS(Pagamentos!$E:$E,Pagamentos!$F:$F,TRUE,Pagamentos!$C:$C,$C61,Pagamentos!$D:$D,F$2) -> 0 | G61: =SUMIFS(Pagamentos!$E:$E,Pagamentos!$F:$F,TRUE,Pagamentos!$C:$C,$C61,Pagamentos!$D:$D,G$2) -> 40 | H61: =SUMIFS(Pagamentos!$E:$E,Pagamentos!$F:$F,TRUE,Pagamentos!$C:$C,$C61,Pagamentos!$D:$D,H$2) -> 20 | I61: =SUMIFS(Pagamentos!$E:$E,Pagamentos!$F:$F,TRUE,Pagamentos!$C:$C,$C61,Pagamentos!$D:$D,I$2) -> 20 | J61: =SUMIFS(Pagamentos!$E:$E,Pagamentos!$F:$F,TRUE,Pagamentos!$C:$C,$C61,Pagamentos!$D:$D,J$2) -> 20 | K61: =SUMIFS(Pagamentos!$E:$E,Pagamentos!$F:$F,TRUE,Pagamentos!$C:$C,$C61,Pagamentos!$D:$D,K$2) -> 20 | L61: =SUMIFS(Pagamentos!$E:$E,Pagamentos!$F:$F,TRUE,Pagamentos!$C:$C,$C61,Pagamentos!$D:$D,L$2) -> 20 | ... P61: =SUMIFS(Pagamentos!$E:$E,Pagamentos!$F:$F,TRUE,Pagamentos!$C:$C,$C61,Pagamentos!$D:$D,P$2) -> 0 | Q61: 1 | R61: =IF(Q61="","",((SUM(E61:P61)-$S$2)/20)+Q61) -> 0 | S61: =IFERROR(__xludf.DUMMYFUNCTION("SPARKLINE(SUM(E61:P61),{""charttype"",""bar"";""max"",$S$2})"),"")
B62: {=IFERROR(INDEX(#REF!,MATCH(C62,#REF!,0)),"")} | C62: =IFERROR(__xludf.DUMMYFUNCTION("""COMPUTED_VALUE"""),"Fabian") -> Fabian | D62: =IFERROR(__xludf.DUMMYFUNCTION("""COMPUTED_VALUE"""),"Fabian Henrique da Silva ") -> Fabian Henrique da Silva | E62: =SUMIFS(Pagamentos!$E:$E,Pagamentos!$F:$F,TRUE,Pagamentos!$C:$C,$C62,Pagamentos!$D:$D,E$2) -> 0 | F62: =SUMIFS(Pagamentos!$E:$E,Pagamentos!$F:$F,TRUE,Pagamentos!$C:$C,$C62,Pagamentos!$D:$D,F$2) -> 0 | G62: =SUMIFS(Pagamentos!$E:$E,Pagamentos!$F:$F,TRUE,Pagamentos!$C:$C,$C62,Pagamentos!$D:$D,G$2) -> 0 | H62: =SUMIFS(Pagamentos!$E:$E,Pagamentos!$F:$F,TRUE,Pagamentos!$C:$C,$C62,Pagamentos!$D:$D,H$2) -> 0 | I62: =SUMIFS(Pagamentos!$E:$E,Pagamentos!$F:$F,TRUE,Pagamentos!$C:$C,$C62,Pagamentos!$D:$D,I$2) -> 80 | J62: =SUMIFS(Pagamentos!$E:$E,Pagamentos!$F:$F,TRUE,Pagamentos!$C:$C,$C62,Pagamentos!$D:$D,J$2) -> 0 | K62: =SUMIFS(Pagamentos!$E:$E,Pagamentos!$F:$F,TRUE,Pagamentos!$C:$C,$C62,Pagamentos!$D:$D,K$2) -> 0 | L62: =SUMIFS(Pagamentos!$E:$E,Pagamentos!$F:$F,TRUE,Pagamentos!$C:$C,$C62,Pagamentos!$D:$D,L$2) -> 0 | ... P62: =SUMIFS(Pagamentos!$E:$E,Pagamentos!$F:$F,TRUE,Pagamentos!$C:$C,$C62,Pagamentos!$D:$D,P$2) -> 0 | Q62: 1 | R62: =IF(Q62="","",((SUM(E62:P62)-$S$2)/20)+Q62) -> -3 | S62: =IFERROR(__xludf.DUMMYFUNCTION("SPARKLINE(SUM(E62:P62),{""charttype"",""bar"";""max"",$S$2})"),"")
B63: {=IFERROR(INDEX(#REF!,MATCH(C63,#REF!,0)),"")} | C63: =IFERROR(__xludf.DUMMYFUNCTION("""COMPUTED_VALUE"""),"Levi") -> Levi | D63: =IFERROR(__xludf.DUMMYFUNCTION("""COMPUTED_VALUE"""),"Washington Levi Nascimento Dias") -> Washington Levi Nascimento Dias | E63: =SUMIFS(Pagamentos!$E:$E,Pagamentos!$F:$F,TRUE,Pagamentos!$C:$C,$C63,Pagamentos!$D:$D,E$2) -> 0 | F63: =SUMIFS(Pagamentos!$E:$E,Pagamentos!$F:$F,TRUE,Pagamentos!$C:$C,$C63,Pagamentos!$D:$D,F$2) -> 0 | G63: =SUMIFS(Pagamentos!$E:$E,Pagamentos!$F:$F,TRUE,Pagamentos!$C:$C,$C63,Pagamentos!$D:$D,G$2) -> 20 | H63: =SUMIFS(Pagamentos!$E:$E,Pagamentos!$F:$F,TRUE,Pagamentos!$C:$C,$C63,Pagamentos!$D:$D,H$2) -> 0 | I63: =SUMIFS(Pagamentos!$E:$E,Pagamentos!$F:$F,TRUE,Pagamentos!$C:$C,$C63,Pagamentos!$D:$D,I$2) -> 0 | J63: =SUMIFS(Pagamentos!$E:$E,Pagamentos!$F:$F,TRUE,Pagamentos!$C:$C,$C63,Pagamentos!$D:$D,J$2) -> 0 | K63: =SUMIFS(Pagamentos!$E:$E,Pagamentos!$F:$F,TRUE,Pagamentos!$C:$C,$C63,Pagamentos!$D:$D,K$2) -> 0 | L63: =SUMIFS(Pagamentos!$E:$E,Pagamentos!$F:$F,TRUE,Pagamentos!$C:$C,$C63,Pagamentos!$D:$D,L$2) -> 0 | ... P63: =SUMIFS(Pagamentos!$E:$E,Pagamentos!$F:$F,TRUE,Pagamentos!$C:$C,$C63,Pagamentos!$D:$D,P$2) -> 0 | Q63: 1 | R63: =IF(Q63="","",((SUM(E63:P63)-$S$2)/20)+Q63) -> -6 | S63: =IFERROR(__xludf.DUMMYFUNCTION("SPARKLINE(SUM(E63:P63),{""charttype"",""bar"";""max"",$S$2})"),"")
B64: {=IFERROR(INDEX(#REF!,MATCH(C64,#REF!,0)),"")} | C64: =IFERROR(__xludf.DUMMYFUNCTION("""COMPUTED_VALUE"""),"Joaber") -> Joaber | D64: =IFERROR(__xludf.DUMMYFUNCTION("""COMPUTED_VALUE"""),"Reinaldo Joaber de Araújo Spengler ") -> Reinaldo Joaber de Araújo Spengler | E64: =SUMIFS(Pagamentos!$E:$E,Pagamentos!$F:$F,TRUE,Pagamentos!$C:$C,$C64,Pagamentos!$D:$D,E$2) -> 0 | F64: =SUMIFS(Pagamentos!$E:$E,Pagamentos!$F:$F,TRUE,Pagamentos!$C:$C,$C64,Pagamentos!$D:$D,F$2) -> 20 | G64: =SUMIFS(Pagamentos!$E:$E,Pagamentos!$F:$F,TRUE,Pagamentos!$C:$C,$C64,Pagamentos!$D:$D,G$2) -> 20 | H64: =SUMIFS(Pagamentos!$E:$E,Pagamentos!$F:$F,TRUE,Pagamentos!$C:$C,$C64,Pagamentos!$D:$D,H$2) -> 20 | I64: =SUMIFS(Pagamentos!$E:$E,Pagamentos!$F:$F,TRUE,Pagamentos!$C:$C,$C64,Pagamentos!$D:$D,I$2) -> 0 | J64: =SUMIFS(Pagamentos!$E:$E,Pagamentos!$F:$F,TRUE,Pagamentos!$C:$C,$C64,Pagamentos!$D:$D,J$2) -> 40 | K64: =SUMIFS(Pagamentos!$E:$E,Pagamentos!$F:$F,TRUE,Pagamentos!$C:$C,$C64,Pagamentos!$D:$D,K$2) -> 0 | L64: =SUMIFS(Pagamentos!$E:$E,Pagamentos!$F:$F,TRUE,Pagamentos!$C:$C,$C64,Pagamentos!$D:$D,L$2) -> 0 | ... P64: =SUMIFS(Pagamentos!$E:$E,Pagamentos!$F:$F,TRUE,Pagamentos!$C:$C,$C64,Pagamentos!$D:$D,P$2) -> 0 | Q64: 1 | R64: =IF(Q64="","",((SUM(E64:P64)-$S$2)/20)+Q64) -> -2 | S64: =IFERROR(__xludf.DUMMYFUNCTION("SPARKLINE(SUM(E64:P64),{""charttype"",""bar"";""max"",$S$2})"),"")
B65: {=IFERROR(INDEX(#REF!,MATCH(C65,#REF!,0)),"")} | C65: =IFERROR(__xludf.DUMMYFUNCTION("""COMPUTED_VALUE"""),"Anderson ") -> Anderson | D65: =IFERROR(__xludf.DUMMYFUNCTION("""COMPUTED_VALUE"""),"Anderson Rafael Souza da Silva ") -> Anderson Rafael Souza da Silva | E65: =SUMIFS(Pagamentos!$E:$E,Pagamentos!$F:$F,TRUE,Pagamentos!$C:$C,$C65,Pagamentos!$D:$D,E$2) -> 0 | F65: =SUMIFS(Pagamentos!$E:$E,Pagamentos!$F:$F,TRUE,Pagamentos!$C:$C,$C65,Pagamentos!$D:$D,F$2) -> 0 | G65: =SUMIFS(Pagamentos!$E:$E,Pagamentos!$F:$F,TRUE,Pagamentos!$C:$C,$C65,Pagamentos!$D:$D,G$2) -> 20 | H65: =SUMIFS(Pagamentos!$E:$E,Pagamentos!$F:$F,TRUE,Pagamentos!$C:$C,$C65,Pagamentos!$D:$D,H$2) -> 0 | I65: =SUMIFS(Pagamentos!$E:$E,Pagamentos!$F:$F,TRUE,Pagamentos!$C:$C,$C65,Pagamentos!$D:$D,I$2) -> 20 | J65: =SUMIFS(Pagamentos!$E:$E,Pagamentos!$F:$F,TRUE,Pagamentos!$C:$C,$C65,Pagamentos!$D:$D,J$2) -> 20 | K65: =SUMIFS(Pagamentos!$E:$E,Pagamentos!$F:$F,TRUE,Pagamentos!$C:$C,$C65,Pagamentos!$D:$D,K$2) -> 20 | L65: =SUMIFS(Pagamentos!$E:$E,Pagamentos!$F:$F,TRUE,Pagamentos!$C:$C,$C65,Pagamentos!$D:$D,L$2) -> 0 | ... P65: =SUMIFS(Pagamentos!$E:$E,Pagamentos!$F:$F,TRUE,Pagamentos!$C:$C,$C65,Pagamentos!$D:$D,P$2) -> 0 | Q65: 2 | R65: =IF(Q65="","",((SUM(E65:P65)-$S$2)/20)+Q65) -> -2 | S65: =IFERROR(__xludf.DUMMYFUNCTION("SPARKLINE(SUM(E65:P65),{""charttype"",""bar"";""max"",$S$2})"),"")
B66: {=IFERROR(INDEX(#REF!,MATCH(C66,#REF!,0)),"")} | C66: =IFERROR(__xludf.DUMMYFUNCTION("""COMPUTED_VALUE"""),"Sadi") -> Sadi | D66: =IFERROR(__xludf.DUMMYFUNCTION("""COMPUTED_VALUE"""),"Washington sadi de jesus ") -> Washington sadi de jesus | E66: =SUMIFS(Pagamentos!$E:$E,Pagamentos!$F:$F,TRUE,Pagamentos!$C:$C,$C66,Pagamentos!$D:$D,E$2) -> 0 | F66: =SUMIFS(Pagamentos!$E:$E,Pagamentos!$F:$F,TRUE,Pagamentos!$C:$C,$C66,Pagamentos!$D:$D,F$2) -> 0 | G66: =SUMIFS(Pagamentos!$E:$E,Pagamentos!$F:$F,TRUE,Pagamentos!$C:$C,$C66,Pagamentos!$D:$D,G$2) -> 0 | H66: =SUMIFS(Pagamentos!$E:$E,Pagamentos!$F:$F,TRUE,Pagamentos!$C:$C,$C66,Pagamentos!$D:$D,H$2) -> 0 | I66: =SUMIFS(Pagamentos!$E:$E,Pagamentos!$F:$F,TRUE,Pagamentos!$C:$C,$C66,Pagamentos!$D:$D,I$2) -> 0 | J66: =SUMIFS(Pagamentos!$E:$E,Pagamentos!$F:$F,TRUE,Pagamentos!$C:$C,$C66,Pagamentos!$D:$D,J$2) -> 0 | K66: =SUMIFS(Pagamentos!$E:$E,Pagamentos!$F:$F,TRUE,Pagamentos!$C:$C,$C66,Pagamentos!$D:$D,K$2) -> 0 | L66: =SUMIFS(Pagamentos!$E:$E,Pagamentos!$F:$F,TRUE,Pagamentos!$C:$C,$C66,Pagamentos!$D:$D,L$2) -> 0 | ... P66: =SUMIFS(Pagamentos!$E:$E,Pagamentos!$F:$F,TRUE,Pagamentos!$C:$C,$C66,Pagamentos!$D:$D,P$2) -> 0 | Q66: 3 | R66: =IF(Q66="","",((SUM(E66:P66)-$S$2)/20)+Q66) -> -5 | S66: =IFERROR(__xludf.DUMMYFUNCTION("SPARKLINE(SUM(E66:P66),{""charttype"",""bar"";""max"",$S$2})"),"")
B67: {=IFERROR(INDEX(#REF!,MATCH(C67,#REF!,0)),"")} | C67: =IFERROR(__xludf.DUMMYFUNCTION("""COMPUTED_VALUE"""),"Perdoná ") -> Perdoná | D67: =IFERROR(__xludf.DUMMYFUNCTION("""COMPUTED_VALUE"""),"Pâmela Aparecida da Luz Perdoná ") -> Pâmela Aparecida da Luz Perdoná | E67: =SUMIFS(Pagamentos!$E:$E,Pagamentos!$F:$F,TRUE,Pagamentos!$C:$C,$C67,Pagamentos!$D:$D,E$2) -> 0 | F67: =SUMIFS(Pagamentos!$E:$E,Pagamentos!$F:$F,TRUE,Pagamentos!$C:$C,$C67,Pagamentos!$D:$D,F$2) -> 0 | G67: =SUMIFS(Pagamentos!$E:$E,Pagamentos!$F:$F,TRUE,Pagamentos!$C:$C,$C67,Pagamentos!$D:$D,G$2) -> 0 | H67: =SUMIFS(Pagamentos!$E:$E,Pagamentos!$F:$F,TRUE,Pagamentos!$C:$C,$C67,Pagamentos!$D:$D,H$2) -> 0 | I67: =SUMIFS(Pagamentos!$E:$E,Pagamentos!$F:$F,TRUE,Pagamentos!$C:$C,$C67,Pagamentos!$D:$D,I$2) -> 20 | J67: =SUMIFS(Pagamentos!$E:$E,Pagamentos!$F:$F,TRUE,Pagamentos!$C:$C,$C67,Pagamentos!$D:$D,J$2) -> 20 | K67: =SUMIFS(Pagamentos!$E:$E,Pagamentos!$F:$F,TRUE,Pagamentos!$C:$C,$C67,Pagamentos!$D:$D,K$2) -> 0 | L67: =SUMIFS(Pagamentos!$E:$E,Pagamentos!$F:$F,TRUE,Pagamentos!$C:$C,$C67,Pagamentos!$D:$D,L$2) -> 0 | ... P67: =SUMIFS(Pagamentos!$E:$E,Pagamentos!$F:$F,TRUE,Pagamentos!$C:$C,$C67,Pagamentos!$D:$D,P$2) -> 0 | Q67: 5 | R67: =IF(Q67="","",((SUM(E67:P67)-$S$2)/20)+Q67) -> -1 | S67: =IFERROR(__xludf.DUMMYFUNCTION("SPARKLINE(SUM(E67:P67),{""charttype"",""bar"";""max"",$S$2})"),"")
B68: {=IFERROR(INDEX(#REF!,MATCH(C68,#REF!,0)),"")} | C68: =IFERROR(__xludf.DUMMYFUNCTION("""COMPUTED_VALUE"""),"Viapiana ") -> Viapiana | D68: =IFERROR(__xludf.DUMMYFUNCTION("""COMPUTED_VALUE"""),"Otávio Augusto Viapiana") -> Otávio Augusto Viapiana | E68: =SUMIFS(Pagamentos!$E:$E,Pagamentos!$F:$F,TRUE,Pagamentos!$C:$C,$C68,Pagamentos!$D:$D,E$2) -> 0 | F68: =SUMIFS(Pagamentos!$E:$E,Pagamentos!$F:$F,TRUE,Pagamentos!$C:$C,$C68,Pagamentos!$D:$D,F$2) -> 0 | G68: =SUMIFS(Pagamentos!$E:$E,Pagamentos!$F:$F,TRUE,Pagamentos!$C:$C,$C68,Pagamentos!$D:$D,G$2) -> 0 | H68: =SUMIFS(Pagamentos!$E:$E,Pagamentos!$F:$F,TRUE,Pagamentos!$C:$C,$C68,Pagamentos!$D:$D,H$2) -> 0 | I68: =SUMIFS(Pagamentos!$E:$E,Pagamentos!$F:$F,TRUE,Pagamentos!$C:$C,$C68,Pagamentos!$D:$D,I$2) -> 20 | J68: =SUMIFS(Pagamentos!$E:$E,Pagamentos!$F:$F,TRUE,Pagamentos!$C:$C,$C68,Pagamentos!$D:$D,J$2) -> 20 | K68: =SUMIFS(Pagamentos!$E:$E,Pagamentos!$F:$F,TRUE,Pagamentos!$C:$C,$C68,Pagamentos!$D:$D,K$2) -> 20 | L68: =SUMIFS(Pagamentos!$E:$E,Pagamentos!$F:$F,TRUE,Pagamentos!$C:$C,$C68,Pagamentos!$D:$D,L$2) -> 0 | ... P68: =SUMIFS(Pagamentos!$E:$E,Pagamentos!$F:$F,TRUE,Pagamentos!$C:$C,$C68,Pagamentos!$D:$D,P$2) -> 0 | Q68: 5 | R68: =IF(Q68="","",((SUM(E68:P68)-$S$2)/20)+Q68) -> 0 | S68: =IFERROR(__xludf.DUMMYFUNCTION("SPARKLINE(SUM(E68:P68),{""charttype"",""bar"";""max"",$S$2})"),"")
B69: {=IFERROR(INDEX(#REF!,MATCH(C69,#REF!,0)),"")} | C69: =IFERROR(__xludf.DUMMYFUNCTION("""COMPUTED_VALUE"""),"Steimbach ") -> Steimbach | D69: =IFERROR(__xludf.DUMMYFUNCTION("""COMPUTED_VALUE"""),"Graziela steimbach ") -> Graziela steimbach | E69: =SUMIFS(Pagamentos!$E:$E,Pagamentos!$F:$F,TRUE,Pagamentos!$C:$C,$C69,Pagamentos!$D:$D,E$2) -> 0 | F69: =SUMIFS(Pagamentos!$E:$E,Pagamentos!$F:$F,TRUE,Pagamentos!$C:$C,$C69,Pagamentos!$D:$D,F$2) -> 0 | G69: =SUMIFS(Pagamentos!$E:$E,Pagamentos!$F:$F,TRUE,Pagamentos!$C:$C,$C69,Pagamentos!$D:$D,G$2) -> 0 | H69: =SUMIFS(Pagamentos!$E:$E,Pagamentos!$F:$F,TRUE,Pagamentos!$C:$C,$C69,Pagamentos!$D:$D,H$2) -> 0 | I69: =SUMIFS(Pagamentos!$E:$E,Pagamentos!$F:$F,TRUE,Pagamentos!$C:$C,$C69,Pagamentos!$D:$D,I$2) -> 0 | J69: =SUMIFS(Pagamentos!$E:$E,Pagamentos!$F:$F,TRUE,Pagamentos!$C:$C,$C69,Pagamentos!$D:$D,J$2) -> 0 | K69: =SUMIFS(Pagamentos!$E:$E,Pagamentos!$F:$F,TRUE,Pagamentos!$C:$C,$C69,Pagamentos!$D:$D,K$2) -> 20 | L69: =SUMIFS(Pagamentos!$E:$E,Pagamentos!$F:$F,TRUE,Pagamentos!$C:$C,$C69,Pagamentos!$D:$D,L$2) -> 20 | ... P69: =SUMIFS(Pagamentos!$E:$E,Pagamentos!$F:$F,TRUE,Pagamentos!$C:$C,$C69,Pagamentos!$D:$D,P$2) -> 0 | Q69: 6 | R69: =IF(Q69="","",((SUM(E69:P69)-$S$2)/20)+Q69) -> 0 | S69: =IFERROR(__xludf.DUMMYFUNCTION("SPARKLINE(SUM(E69:P69),{""charttype"",""bar"";""max"",$S$2})"),"")
B70: {=IFERROR(INDEX(#REF!,MATCH(C70,#REF!,0)),"")} | E70: =SUMIFS(Pagamentos!$E:$E,Pagamentos!$F:$F,TRUE,Pagamentos!$C:$C,$C70,Pagamentos!$D:$D,E$2) -> 0 | F70: =SUMIFS(Pagamentos!$E:$E,Pagamentos!$F:$F,TRUE,Pagamentos!$C:$C,$C70,Pagamentos!$D:$D,F$2) -> 0 | G70: =SUMIFS(Pagamentos!$E:$E,Pagamentos!$F:$F,TRUE,Pagamentos!$C:$C,$C70,Pagamentos!$D:$D,G$2) -> 0 | H70: =SUMIFS(Pagamentos!$E:$E,Pagamentos!$F:$F,TRUE,Pagamentos!$C:$C,$C70,Pagamentos!$D:$D,H$2) -> 0 | I70: =SUMIFS(Pagamentos!$E:$E,Pagamentos!$F:$F,TRUE,Pagamentos!$C:$C,$C70,Pagamentos!$D:$D,I$2) -> 0 | J70: =SUMIFS(Pagamentos!$E:$E,Pagamentos!$F:$F,TRUE,Pagamentos!$C:$C,$C70,Pagamentos!$D:$D,J$2) -> 0 | K70: =SUMIFS(Pagamentos!$E:$E,Pagamentos!$F:$F,TRUE,Pagamentos!$C:$C,$C70,Pagamentos!$D:$D,K$2) -> 0 | L70: =SUMIFS(Pagamentos!$E:$E,Pagamentos!$F:$F,TRUE,Pagamentos!$C:$C,$C70,Pagamentos!$D:$D,L$2) -> 0 | ... P70: =SUMIFS(Pagamentos!$E:$E,Pagamentos!$F:$F,TRUE,Pagamentos!$C:$C,$C70,Pagamentos!$D:$D,P$2) -> 0 | R70: =IF(Q70="","",((SUM(E70:P70)-$S$2)/20)+Q70) | S70: =IFERROR(__xludf.DUMMYFUNCTION("SPARKLINE(SUM(E70:P70),{""charttype"",""bar"";""max"",$S$2})"),"")
B71: {=IFERROR(INDEX(#REF!,MATCH(C71,#REF!,0)),"")} | E71: =SUMIFS(Pagamentos!$E:$E,Pagamentos!$F:$F,TRUE,Pagamentos!$C:$C,$C71,Pagamentos!$D:$D,E$2) -> 0 | F71: =SUMIFS(Pagamentos!$E:$E,Pagamentos!$F:$F,TRUE,Pagamentos!$C:$C,$C71,Pagamentos!$D:$D,F$2) -> 0 | G71: =SUMIFS(Pagamentos!$E:$E,Pagamentos!$F:$F,TRUE,Pagamentos!$C:$C,$C71,Pagamentos!$D:$D,G$2) -> 0 | H71: =SUMIFS(Pagamentos!$E:$E,Pagamentos!$F:$F,TRUE,Pagamentos!$C:$C,$C71,Pagamentos!$D:$D,H$2) -> 0 | I71: =SUMIFS(Pagamentos!$E:$E,Pagamentos!$F:$F,TRUE,Pagamentos!$C:$C,$C71,Pagamentos!$D:$D,I$2) -> 0 | J71: =SUMIFS(Pagamentos!$E:$E,Pagamentos!$F:$F,TRUE,Pagamentos!$C:$C,$C71,Pagamentos!$D:$D,J$2) -> 0 | K71: =SUMIFS(Pagamentos!$E:$E,Pagamentos!$F:$F,TRUE,Pagamentos!$C:$C,$C71,Pagamentos!$D:$D,K$2) -> 0 | L71: =SUMIFS(Pagamentos!$E:$E,Pagamentos!$F:$F,TRUE,Pagamentos!$C:$C,$C71,Pagamentos!$D:$D,L$2) -> 0 | ... P71: =SUMIFS(Pagamentos!$E:$E,Pagamentos!$F:$F,TRUE,Pagamentos!$C:$C,$C71,Pagamentos!$D:$D,P$2) -> 0 | R71: =IF(Q71="","",((SUM(E71:P71)-$S$2)/20)+Q71) | S71: =IFERROR(__xludf.DUMMYFUNCTION("SPARKLINE(SUM(E71:P71),{""charttype"",""bar"";""max"",$S$2})"),"")
B72: {=IFERROR(INDEX(#REF!,MATCH(C72,#REF!,0)),"")} | E72: =SUMIFS(Pagamentos!$E:$E,Pagamentos!$F:$F,TRUE,Pagamentos!$C:$C,$C72,Pagamentos!$D:$D,E$2) -> 0 | F72: =SUMIFS(Pagamentos!$E:$E,Pagamentos!$F:$F,TRUE,Pagamentos!$C:$C,$C72,Pagamentos!$D:$D,F$2) -> 0 | G72: =SUMIFS(Pagamentos!$E:$E,Pagamentos!$F:$F,TRUE,Pagamentos!$C:$C,$C72,Pagamentos!$D:$D,G$2) -> 0 | H72: =SUMIFS(Pagamentos!$E:$E,Pagamentos!$F:$F,TRUE,Pagamentos!$C:$C,$C72,Pagamentos!$D:$D,H$2) -> 0 | I72: =SUMIFS(Pagamentos!$E:$E,Pagamentos!$F:$F,TRUE,Pagamentos!$C:$C,$C72,Pagamentos!$D:$D,I$2) -> 0 | J72: =SUMIFS(Pagamentos!$E:$E,Pagamentos!$F:$F,TRUE,Pagamentos!$C:$C,$C72,Pagamentos!$D:$D,J$2) -> 0 | K72: =SUMIFS(Pagamentos!$E:$E,Pagamentos!$F:$F,TRUE,Pagamentos!$C:$C,$C72,Pagamentos!$D:$D,K$2) -> 0 | L72: =SUMIFS(Pagamentos!$E:$E,Pagamentos!$F:$F,TRUE,Pagamentos!$C:$C,$C72,Pagamentos!$D:$D,L$2) -> 0 | ... P72: =SUMIFS(Pagamentos!$E:$E,Pagamentos!$F:$F,TRUE,Pagamentos!$C:$C,$C72,Pagamentos!$D:$D,P$2) -> 0 | R72: =IF(Q72="","",((SUM(E72:P72)-$S$2)/20)+Q72) | S72: =IFERROR(__xludf.DUMMYFUNCTION("SPARKLINE(SUM(E72:P72),{""charttype"",""bar"";""max"",$S$2})"),"")
B73: {=IFERROR(INDEX(#REF!,MATCH(C73,#REF!,0)),"")} | E73: =SUMIFS(Pagamentos!$E:$E,Pagamentos!$F:$F,TRUE,Pagamentos!$C:$C,$C73,Pagamentos!$D:$D,E$2) -> 0 | F73: =SUMIFS(Pagamentos!$E:$E,Pagamentos!$F:$F,TRUE,Pagamentos!$C:$C,$C73,Pagamentos!$D:$D,F$2) -> 0 | G73: =SUMIFS(Pagamentos!$E:$E,Pagamentos!$F:$F,TRUE,Pagamentos!$C:$C,$C73,Pagamentos!$D:$D,G$2) -> 0 | H73: =SUMIFS(Pagamentos!$E:$E,Pagamentos!$F:$F,TRUE,Pagamentos!$C:$C,$C73,Pagamentos!$D:$D,H$2) -> 0 | I73: =SUMIFS(Pagamentos!$E:$E,Pagamentos!$F:$F,TRUE,Pagamentos!$C:$C,$C73,Pagamentos!$D:$D,I$2) -> 0 | J73: =SUMIFS(Pagamentos!$E:$E,Pagamentos!$F:$F,TRUE,Pagamentos!$C:$C,$C73,Pagamentos!$D:$D,J$2) -> 0 | K73: =SUMIFS(Pagamentos!$E:$E,Pagamentos!$F:$F,TRUE,Pagamentos!$C:$C,$C73,Pagamentos!$D:$D,K$2) -> 0 | L73: =SUMIFS(Pagamentos!$E:$E,Pagamentos!$F:$F,TRUE,Pagamentos!$C:$C,$C73,Pagamentos!$D:$D,L$2) -> 0 | ... P73: =SUMIFS(Pagamentos!$E:$E,Pagamentos!$F:$F,TRUE,Pagamentos!$C:$C,$C73,Pagamentos!$D:$D,P$2) -> 0 | R73: =IF(Q73="","",((SUM(E73:P73)-$S$2)/20)+Q73) | S73: =IFERROR(__xludf.DUMMYFUNCTION("SPARKLINE(SUM(E73:P73),{""charttype"",""bar"";""max"",$S$2})"),"")
B74: {=IFERROR(INDEX(#REF!,MATCH(C74,#REF!,0)),"")} | E74: =SUMIFS(Pagamentos!$E:$E,Pagamentos!$F:$F,TRUE,Pagamentos!$C:$C,$C74,Pagamentos!$D:$D,E$2) -> 0 | F74: =SUMIFS(Pagamentos!$E:$E,Pagamentos!$F:$F,TRUE,Pagamentos!$C:$C,$C74,Pagamentos!$D:$D,F$2) -> 0 | G74: =SUMIFS(Pagamentos!$E:$E,Pagamentos!$F:$F,TRUE,Pagamentos!$C:$C,$C74,Pagamentos!$D:$D,G$2) -> 0 | H74: =SUMIFS(Pagamentos!$E:$E,Pagamentos!$F:$F,TRUE,Pagamentos!$C:$C,$C74,Pagamentos!$D:$D,H$2) -> 0 | I74: =SUMIFS(Pagamentos!$E:$E,Pagamentos!$F:$F,TRUE,Pagamentos!$C:$C,$C74,Pagamentos!$D:$D,I$2) -> 0 | J74: =SUMIFS(Pagamentos!$E:$E,Pagamentos!$F:$F,TRUE,Pagamentos!$C:$C,$C74,Pagamentos!$D:$D,J$2) -> 0 | K74: =SUMIFS(Pagamentos!$E:$E,Pagamentos!$F:$F,TRUE,Pagamentos!$C:$C,$C74,Pagamentos!$D:$D,K$2) -> 0 | L74: =SUMIFS(Pagamentos!$E:$E,Pagamentos!$F:$F,TRUE,Pagamentos!$C:$C,$C74,Pagamentos!$D:$D,L$2) -> 0 | ... P74: =SUMIFS(Pagamentos!$E:$E,Pagamentos!$F:$F,TRUE,Pagamentos!$C:$C,$C74,Pagamentos!$D:$D,P$2) -> 0 | R74: =IF(Q74="","",((SUM(E74:P74)-$S$2)/20)+Q74) | S74: =IFERROR(__xludf.DUMMYFUNCTION("SPARKLINE(SUM(E74:P74),{""charttype"",""bar"";""max"",$S$2})"),"")
B75: {=IFERROR(INDEX(#REF!,MATCH(C75,#REF!,0)),"")} | E75: =SUMIFS(Pagamentos!$E:$E,Pagamentos!$F:$F,TRUE,Pagamentos!$C:$C,$C75,Pagamentos!$D:$D,E$2) -> 0 | F75: =SUMIFS(Pagamentos!$E:$E,Pagamentos!$F:$F,TRUE,Pagamentos!$C:$C,$C75,Pagamentos!$D:$D,F$2) -> 0 | G75: =SUMIFS(Pagamentos!$E:$E,Pagamentos!$F:$F,TRUE,Pagamentos!$C:$C,$C75,Pagamentos!$D:$D,G$2) -> 0 | H75: =SUMIFS(Pagamentos!$E:$E,Pagamentos!$F:$F,TRUE,Pagamentos!$C:$C,$C75,Pagamentos!$D:$D,H$2) -> 0 | I75: =SUMIFS(Pagamentos!$E:$E,Pagamentos!$F:$F,TRUE,Pagamentos!$C:$C,$C75,Pagamentos!$D:$D,I$2) -> 0 | J75: =SUMIFS(Pagamentos!$E:$E,Pagamentos!$F:$F,TRUE,Pagamentos!$C:$C,$C75,Pagamentos!$D:$D,J$2) -> 0 | K75: =SUMIFS(Pagamentos!$E:$E,Pagamentos!$F:$F,TRUE,Pagamentos!$C:$C,$C75,Pagamentos!$D:$D,K$2) -> 0 | L75: =SUMIFS(Pagamentos!$E:$E,Pagamentos!$F:$F,TRUE,Pagamentos!$C:$C,$C75,Pagamentos!$D:$D,L$2) -> 0 | ... P75: =SUMIFS(Pagamentos!$E:$E,Pagamentos!$F:$F,TRUE,Pagamentos!$C:$C,$C75,Pagamentos!$D:$D,P$2) -> 0 | R75: =IF(Q75="","",((SUM(E75:P75)-$S$2)/20)+Q75) | S75: =IFERROR(__xludf.DUMMYFUNCTION("SPARKLINE(SUM(E75:P75),{""charttype"",""bar"";""max"",$S$2})"),"")
B76: {=IFERROR(INDEX(#REF!,MATCH(C76,#REF!,0)),"")} | E76: =SUMIFS(Pagamentos!$E:$E,Pagamentos!$F:$F,TRUE,Pagamentos!$C:$C,$C76,Pagamentos!$D:$D,E$2) -> 0 | F76: =SUMIFS(Pagamentos!$E:$E,Pagamentos!$F:$F,TRUE,Pagamentos!$C:$C,$C76,Pagamentos!$D:$D,F$2) -> 0 | G76: =SUMIFS(Pagamentos!$E:$E,Pagamentos!$F:$F,TRUE,Pagamentos!$C:$C,$C76,Pagamentos!$D:$D,G$2) -> 0 | H76: =SUMIFS(Pagamentos!$E:$E,Pagamentos!$F:$F,TRUE,Pagamentos!$C:$C,$C76,Pagamentos!$D:$D,H$2) -> 0 | I76: =SUMIFS(Pagamentos!$E:$E,Pagamentos!$F:$F,TRUE,Pagamentos!$C:$C,$C76,Pagamentos!$D:$D,I$2) -> 0 | J76: =SUMIFS(Pagamentos!$E:$E,Pagamentos!$F:$F,TRUE,Pagamentos!$C:$C,$C76,Pagamentos!$D:$D,J$2) -> 0 | K76: =SUMIFS(Pagamentos!$E:$E,Pagamentos!$F:$F,TRUE,Pagamentos!$C:$C,$C76,Pagamentos!$D:$D,K$2) -> 0 | L76: =SUMIFS(Pagamentos!$E:$E,Pagamentos!$F:$F,TRUE,Pagamentos!$C:$C,$C76,Pagamentos!$D:$D,L$2) -> 0 | ... P76: =SUMIFS(Pagamentos!$E:$E,Pagamentos!$F:$F,TRUE,Pagamentos!$C:$C,$C76,Pagamentos!$D:$D,P$2) -> 0 | R76: =IF(Q76="","",((SUM(E76:P76)-$S$2)/20)+Q76) | S76: =IFERROR(__xludf.DUMMYFUNCTION("SPARKLINE(SUM(E76:P76),{""charttype"",""bar"";""max"",$S$2})"),"")
B77: {=IFERROR(INDEX(#REF!,MATCH(C77,#REF!,0)),"")} | E77: =SUMIFS(Pagamentos!$E:$E,Pagamentos!$F:$F,TRUE,Pagamentos!$C:$C,$C77,Pagamentos!$D:$D,E$2) -> 0 | F77: =SUMIFS(Pagamentos!$E:$E,Pagamentos!$F:$F,TRUE,Pagamentos!$C:$C,$C77,Pagamentos!$D:$D,F$2) -> 0 | G77: =SUMIFS(Pagamentos!$E:$E,Pagamentos!$F:$F,TRUE,Pagamentos!$C:$C,$C77,Pagamentos!$D:$D,G$2) -> 0 | H77: =SUMIFS(Pagamentos!$E:$E,Pagamentos!$F:$F,TRUE,Pagamentos!$C:$C,$C77,Pagamentos!$D:$D,H$2) -> 0 | I77: =SUMIFS(Pagamentos!$E:$E,Pagamentos!$F:$F,TRUE,Pagamentos!$C:$C,$C77,Pagamentos!$D:$D,I$2) -> 0 | J77: =SUMIFS(Pagamentos!$E:$E,Pagamentos!$F:$F,TRUE,Pagamentos!$C:$C,$C77,Pagamentos!$D:$D,J$2) -> 0 | K77: =SUMIFS(Pagamentos!$E:$E,Pagamentos!$F:$F,TRUE,Pagamentos!$C:$C,$C77,Pagamentos!$D:$D,K$2) -> 0 | L77: =SUMIFS(Pagamentos!$E:$E,Pagamentos!$F:$F,TRUE,Pagamentos!$C:$C,$C77,Pagamentos!$D:$D,L$2) -> 0 | ... P77: =SUMIFS(Pagamentos!$E:$E,Pagamentos!$F:$F,TRUE,Pagamentos!$C:$C,$C77,Pagamentos!$D:$D,P$2) -> 0 | R77: =IF(Q77="","",((SUM(E77:P77)-$S$2)/20)+Q77) | S77: =IFERROR(__xludf.DUMMYFUNCTION("SPARKLINE(SUM(E77:P77),{""charttype"",""bar"";""max"",$S$2})"),"")
B78: {=IFERROR(INDEX(#REF!,MATCH(C78,#REF!,0)),"")} | E78: =SUMIFS(Pagamentos!$E:$E,Pagamentos!$F:$F,TRUE,Pagamentos!$C:$C,$C78,Pagamentos!$D:$D,E$2) -> 0 | F78: =SUMIFS(Pagamentos!$E:$E,Pagamentos!$F:$F,TRUE,Pagamentos!$C:$C,$C78,Pagamentos!$D:$D,F$2) -> 0 | G78: =SUMIFS(Pagamentos!$E:$E,Pagamentos!$F:$F,TRUE,Pagamentos!$C:$C,$C78,Pagamentos!$D:$D,G$2) -> 0 | H78: =SUMIFS(Pagamentos!$E:$E,Pagamentos!$F:$F,TRUE,Pagamentos!$C:$C,$C78,Pagamentos!$D:$D,H$2) -> 0 | I78: =SUMIFS(Pagamentos!$E:$E,Pagamentos!$F:$F,TRUE,Pagamentos!$C:$C,$C78,Pagamentos!$D:$D,I$2) -> 0 | J78: =SUMIFS(Pagamentos!$E:$E,Pagamentos!$F:$F,TRUE,Pagamentos!$C:$C,$C78,Pagamentos!$D:$D,J$2) -> 0 | K78: =SUMIFS(Pagamentos!$E:$E,Pagamentos!$F:$F,TRUE,Pagamentos!$C:$C,$C78,Pagamentos!$D:$D,K$2) -> 0 | L78: =SUMIFS(Pagamentos!$E:$E,Pagamentos!$F:$F,TRUE,Pagamentos!$C:$C,$C78,Pagamentos!$D:$D,L$2) -> 0 | ... P78: =SUMIFS(Pagamentos!$E:$E,Pagamentos!$F:$F,TRUE,Pagamentos!$C:$C,$C78,Pagamentos!$D:$D,P$2) -> 0 | R78: =IF(Q78="","",((SUM(E78:P78)-$S$2)/20)+Q78) | S78: =IFERROR(__xludf.DUMMYFUNCTION("SPARKLINE(SUM(E78:P78),{""charttype"",""bar"";""max"",$S$2})"),"")
B79: {=IFERROR(INDEX(#REF!,MATCH(C79,#REF!,0)),"")} | E79: =SUMIFS(Pagamentos!$E:$E,Pagamentos!$F:$F,TRUE,Pagamentos!$C:$C,$C79,Pagamentos!$D:$D,E$2) -> 0 | F79: =SUMIFS(Pagamentos!$E:$E,Pagamentos!$F:$F,TRUE,Pagamentos!$C:$C,$C79,Pagamentos!$D:$D,F$2) -> 0 | G79: =SUMIFS(Pagamentos!$E:$E,Pagamentos!$F:$F,TRUE,Pagamentos!$C:$C,$C79,Pagamentos!$D:$D,G$2) -> 0 | H79: =SUMIFS(Pagamentos!$E:$E,Pagamentos!$F:$F,TRUE,Pagamentos!$C:$C,$C79,Pagamentos!$D:$D,H$2) -> 0 | I79: =SUMIFS(Pagamentos!$E:$E,Pagamentos!$F:$F,TRUE,Pagamentos!$C:$C,$C79,Pagamentos!$D:$D,I$2) -> 0 | J79: =SUMIFS(Pagamentos!$E:$E,Pagamentos!$F:$F,TRUE,Pagamentos!$C:$C,$C79,Pagamentos!$D:$D,J$2) -> 0 | K79: =SUMIFS(Pagamentos!$E:$E,Pagamentos!$F:$F,TRUE,Pagamentos!$C:$C,$C79,Pagamentos!$D:$D,K$2) -> 0 | L79: =SUMIFS(Pagamentos!$E:$E,Pagamentos!$F:$F,TRUE,Pagamentos!$C:$C,$C79,Pagamentos!$D:$D,L$2) -> 0 | ... P79: =SUMIFS(Pagamentos!$E:$E,Pagamentos!$F:$F,TRUE,Pagamentos!$C:$C,$C79,Pagamentos!$D:$D,P$2) -> 0 | R79: =IF(Q79="","",((SUM(E79:P79)-$S$2)/20)+Q79) | S79: =IFERROR(__xludf.DUMMYFUNCTION("SPARKLINE(SUM(E79:P79),{""charttype"",""bar"";""max"",$S$2})"),"")
B80: {=IFERROR(INDEX(#REF!,MATCH(C80,#REF!,0)),"")} | E80: =SUMIFS(Pagamentos!$E:$E,Pagamentos!$F:$F,TRUE,Pagamentos!$C:$C,$C80,Pagamentos!$D:$D,E$2) -> 0 | F80: =SUMIFS(Pagamentos!$E:$E,Pagamentos!$F:$F,TRUE,Pagamentos!$C:$C,$C80,Pagamentos!$D:$D,F$2) -> 0 | G80: =SUMIFS(Pagamentos!$E:$E,Pagamentos!$F:$F,TRUE,Pagamentos!$C:$C,$C80,Pagamentos!$D:$D,G$2) -> 0 | H80: =SUMIFS(Pagamentos!$E:$E,Pagamentos!$F:$F,TRUE,Pagamentos!$C:$C,$C80,Pagamentos!$D:$D,H$2) -> 0 | I80: =SUMIFS(Pagamentos!$E:$E,Pagamentos!$F:$F,TRUE,Pagamentos!$C:$C,$C80,Pagamentos!$D:$D,I$2) -> 0 | J80: =SUMIFS(Pagamentos!$E:$E,Pagamentos!$F:$F,TRUE,Pagamentos!$C:$C,$C80,Pagamentos!$D:$D,J$2) -> 0 | K80: =SUMIFS(Pagamentos!$E:$E,Pagamentos!$F:$F,TRUE,Pagamentos!$C:$C,$C80,Pagamentos!$D:$D,K$2) -> 0 | L80: =SUMIFS(Pagamentos!$E:$E,Pagamentos!$F:$F,TRUE,Pagamentos!$C:$C,$C80,Pagamentos!$D:$D,L$2) -> 0 | ... P80: =SUMIFS(Pagamentos!$E:$E,Pagamentos!$F:$F,TRUE,Pagamentos!$C:$C,$C80,Pagamentos!$D:$D,P$2) -> 0 | R80: =IF(Q80="","",((SUM(E80:P80)-$S$2)/20)+Q80) | S80: =IFERROR(__xludf.DUMMYFUNCTION("SPARKLINE(SUM(E80:P80),{""charttype"",""bar"";""max"",$S$2})"),"")
B81: {=IFERROR(INDEX(#REF!,MATCH(C81,#REF!,0)),"")} | E81: =SUMIFS(Pagamentos!$E:$E,Pagamentos!$F:$F,TRUE,Pagamentos!$C:$C,$C81,Pagamentos!$D:$D,E$2) -> 0 | F81: =SUMIFS(Pagamentos!$E:$E,Pagamentos!$F:$F,TRUE,Pagamentos!$C:$C,$C81,Pagamentos!$D:$D,F$2) -> 0 | G81: =SUMIFS(Pagamentos!$E:$E,Pagamentos!$F:$F,TRUE,Pagamentos!$C:$C,$C81,Pagamentos!$D:$D,G$2) -> 0 | H81: =SUMIFS(Pagamentos!$E:$E,Pagamentos!$F:$F,TRUE,Pagamentos!$C:$C,$C81,Pagamentos!$D:$D,H$2) -> 0 | I81: =SUMIFS(Pagamentos!$E:$E,Pagamentos!$F:$F,TRUE,Pagamentos!$C:$C,$C81,Pagamentos!$D:$D,I$2) -> 0 | J81: =SUMIFS(Pagamentos!$E:$E,Pagamentos!$F:$F,TRUE,Pagamentos!$C:$C,$C81,Pagamentos!$D:$D,J$2) -> 0 | K81: =SUMIFS(Pagamentos!$E:$E,Pagamentos!$F:$F,TRUE,Pagamentos!$C:$C,$C81,Pagamentos!$D:$D,K$2) -> 0 | L81: =SUMIFS(Pagamentos!$E:$E,Pagamentos!$F:$F,TRUE,Pagamentos!$C:$C,$C81,Pagamentos!$D:$D,L$2) -> 0 | ... P81: =SUMIFS(Pagamentos!$E:$E,Pagamentos!$F:$F,TRUE,Pagamentos!$C:$C,$C81,Pagamentos!$D:$D,P$2) -> 0 | R81: =IF(Q81="","",((SUM(E81:P81)-$S$2)/20)+Q81) | S81: =IFERROR(__xludf.DUMMYFUNCTION("SPARKLINE(SUM(E81:P81),{""charttype"",""bar"";""max"",$S$2})"),"")
B82: {=IFERROR(INDEX(#REF!,MATCH(C82,#REF!,0)),"")} | E82: =SUMIFS(Pagamentos!$E:$E,Pagamentos!$F:$F,TRUE,Pagamentos!$C:$C,$C82,Pagamentos!$D:$D,E$2) -> 0 | F82: =SUMIFS(Pagamentos!$E:$E,Pagamentos!$F:$F,TRUE,Pagamentos!$C:$C,$C82,Pagamentos!$D:$D,F$2) -> 0 | G82: =SUMIFS(Pagamentos!$E:$E,Pagamentos!$F:$F,TRUE,Pagamentos!$C:$C,$C82,Pagamentos!$D:$D,G$2) -> 0 | H82: =SUMIFS(Pagamentos!$E:$E,Pagamentos!$F:$F,TRUE,Pagamentos!$C:$C,$C82,Pagamentos!$D:$D,H$2) -> 0 | I82: =SUMIFS(Pagamentos!$E:$E,Pagamentos!$F:$F,TRUE,Pagamentos!$C:$C,$C82,Pagamentos!$D:$D,I$2) -> 0 | J82: =SUMIFS(Pagamentos!$E:$E,Pagamentos!$F:$F,TRUE,Pagamentos!$C:$C,$C82,Pagamentos!$D:$D,J$2) -> 0 | K82: =SUMIFS(Pagamentos!$E:$E,Pagamentos!$F:$F,TRUE,Pagamentos!$C:$C,$C82,Pagamentos!$D:$D,K$2) -> 0 | L82: =SUMIFS(Pagamentos!$E:$E,Pagamentos!$F:$F,TRUE,Pagamentos!$C:$C,$C82,Pagamentos!$D:$D,L$2) -> 0 | ... P82: =SUMIFS(Pagamentos!$E:$E,Pagamentos!$F:$F,TRUE,Pagamentos!$C:$C,$C82,Pagamentos!$D:$D,P$2) -> 0 | R82: =IF(Q82="","",((SUM(E82:P82)-$S$2)/20)+Q82) | S82: =IFERROR(__xludf.DUMMYFUNCTION("SPARKLINE(SUM(E82:P82),{""charttype"",""bar"";""max"",$S$2})"),"")
B83: {=IFERROR(INDEX(#REF!,MATCH(C83,#REF!,0)),"")} | E83: =SUMIFS(Pagamentos!$E:$E,Pagamentos!$F:$F,TRUE,Pagamentos!$C:$C,$C83,Pagamentos!$D:$D,E$2) -> 0 | F83: =SUMIFS(Pagamentos!$E:$E,Pagamentos!$F:$F,TRUE,Pagamentos!$C:$C,$C83,Pagamentos!$D:$D,F$2) -> 0 | G83: =SUMIFS(Pagamentos!$E:$E,Pagamentos!$F:$F,TRUE,Pagamentos!$C:$C,$C83,Pagamentos!$D:$D,G$2) -> 0 | H83: =SUMIFS(Pagamentos!$E:$E,Pagamentos!$F:$F,TRUE,Pagamentos!$C:$C,$C83,Pagamentos!$D:$D,H$2) -> 0 | I83: =SUMIFS(Pagamentos!$E:$E,Pagamentos!$F:$F,TRUE,Pagamentos!$C:$C,$C83,Pagamentos!$D:$D,I$2) -> 0 | J83: =SUMIFS(Pagamentos!$E:$E,Pagamentos!$F:$F,TRUE,Pagamentos!$C:$C,$C83,Pagamentos!$D:$D,J$2) -> 0 | K83: =SUMIFS(Pagamentos!$E:$E,Pagamentos!$F:$F,TRUE,Pagamentos!$C:$C,$C83,Pagamentos!$D:$D,K$2) -> 0 | L83: =SUMIFS(Pagamentos!$E:$E,Pagamentos!$F:$F,TRUE,Pagamentos!$C:$C,$C83,Pagamentos!$D:$D,L$2) -> 0 | ... P83: =SUMIFS(Pagamentos!$E:$E,Pagamentos!$F:$F,TRUE,Pagamentos!$C:$C,$C83,Pagamentos!$D:$D,P$2) -> 0 | R83: =IF(Q83="","",((SUM(E83:P83)-$S$2)/20)+Q83) | S83: =IFERROR(__xludf.DUMMYFUNCTION("SPARKLINE(SUM(E83:P83),{""charttype"",""bar"";""max"",$S$2})"),"")
B84: {=IFERROR(INDEX(#REF!,MATCH(C84,#REF!,0)),"")} | E84: =SUMIFS(Pagamentos!$E:$E,Pagamentos!$F:$F,TRUE,Pagamentos!$C:$C,$C84,Pagamentos!$D:$D,E$2) -> 0 | F84: =SUMIFS(Pagamentos!$E:$E,Pagamentos!$F:$F,TRUE,Pagamentos!$C:$C,$C84,Pagamentos!$D:$D,F$2) -> 0 | G84: =SUMIFS(Pagamentos!$E:$E,Pagamentos!$F:$F,TRUE,Pagamentos!$C:$C,$C84,Pagamentos!$D:$D,G$2) -> 0 | H84: =SUMIFS(Pagamentos!$E:$E,Pagamentos!$F:$F,TRUE,Pagamentos!$C:$C,$C84,Pagamentos!$D:$D,H$2) -> 0 | I84: =SUMIFS(Pagamentos!$E:$E,Pagamentos!$F:$F,TRUE,Pagamentos!$C:$C,$C84,Pagamentos!$D:$D,I$2) -> 0 | J84: =SUMIFS(Pagamentos!$E:$E,Pagamentos!$F:$F,TRUE,Pagamentos!$C:$C,$C84,Pagamentos!$D:$D,J$2) -> 0 | K84: =SUMIFS(Pagamentos!$E:$E,Pagamentos!$F:$F,TRUE,Pagamentos!$C:$C,$C84,Pagamentos!$D:$D,K$2) -> 0 | L84: =SUMIFS(Pagamentos!$E:$E,Pagamentos!$F:$F,TRUE,Pagamentos!$C:$C,$C84,Pagamentos!$D:$D,L$2) -> 0 | ... P84: =SUMIFS(Pagamentos!$E:$E,Pagamentos!$F:$F,TRUE,Pagamentos!$C:$C,$C84,Pagamentos!$D:$D,P$2) -> 0 | R84: =IF(Q84="","",((SUM(E84:P84)-$S$2)/20)+Q84) | S84: =IFERROR(__xludf.DUMMYFUNCTION("SPARKLINE(SUM(E84:P84),{""charttype"",""bar"";""max"",$S$2})"),"")
B85: {=IFERROR(INDEX(#REF!,MATCH(C85,#REF!,0)),"")} | E85: =SUMIFS(Pagamentos!$E:$E,Pagamentos!$F:$F,TRUE,Pagamentos!$C:$C,$C85,Pagamentos!$D:$D,E$2) -> 0 | F85: =SUMIFS(Pagamentos!$E:$E,Pagamentos!$F:$F,TRUE,Pagamentos!$C:$C,$C85,Pagamentos!$D:$D,F$2) -> 0 | G85: =SUMIFS(Pagamentos!$E:$E,Pagamentos!$F:$F,TRUE,Pagamentos!$C:$C,$C85,Pagamentos!$D:$D,G$2) -> 0 | H85: =SUMIFS(Pagamentos!$E:$E,Pagamentos!$F:$F,TRUE,Pagamentos!$C:$C,$C85,Pagamentos!$D:$D,H$2) -> 0 | I85: =SUMIFS(Pagamentos!$E:$E,Pagamentos!$F:$F,TRUE,Pagamentos!$C:$C,$C85,Pagamentos!$D:$D,I$2) -> 0 | J85: =SUMIFS(Pagamentos!$E:$E,Pagamentos!$F:$F,TRUE,Pagamentos!$C:$C,$C85,Pagamentos!$D:$D,J$2) -> 0 | K85: =SUMIFS(Pagamentos!$E:$E,Pagamentos!$F:$F,TRUE,Pagamentos!$C:$C,$C85,Pagamentos!$D:$D,K$2) -> 0 | L85: =SUMIFS(Pagamentos!$E:$E,Pagamentos!$F:$F,TRUE,Pagamentos!$C:$C,$C85,Pagamentos!$D:$D,L$2) -> 0 | ... P85: =SUMIFS(Pagamentos!$E:$E,Pagamentos!$F:$F,TRUE,Pagamentos!$C:$C,$C85,Pagamentos!$D:$D,P$2) -> 0 | R85: =IF(Q85="","",((SUM(E85:P85)-$S$2)/20)+Q85) | S85: =IFERROR(__xludf.DUMMYFUNCTION("SPARKLINE(SUM(E85:P85),{""charttype"",""bar"";""max"",$S$2})"),"")
B86: {=IFERROR(INDEX(#REF!,MATCH(C86,#REF!,0)),"")} | E86: =SUMIFS(Pagamentos!$E:$E,Pagamentos!$F:$F,TRUE,Pagamentos!$C:$C,$C86,Pagamentos!$D:$D,E$2) -> 0 | F86: =SUMIFS(Pagamentos!$E:$E,Pagamentos!$F:$F,TRUE,Pagamentos!$C:$C,$C86,Pagamentos!$D:$D,F$2) -> 0 | G86: =SUMIFS(Pagamentos!$E:$E,Pagamentos!$F:$F,TRUE,Pagamentos!$C:$C,$C86,Pagamentos!$D:$D,G$2) -> 0 | H86: =SUMIFS(Pagamentos!$E:$E,Pagamentos!$F:$F,TRUE,Pagamentos!$C:$C,$C86,Pagamentos!$D:$D,H$2) -> 0 | I86: =SUMIFS(Pagamentos!$E:$E,Pagamentos!$F:$F,TRUE,Pagamentos!$C:$C,$C86,Pagamentos!$D:$D,I$2) -> 0 | J86: =SUMIFS(Pagamentos!$E:$E,Pagamentos!$F:$F,TRUE,Pagamentos!$C:$C,$C86,Pagamentos!$D:$D,J$2) -> 0 | K86: =SUMIFS(Pagamentos!$E:$E,Pagamentos!$F:$F,TRUE,Pagamentos!$C:$C,$C86,Pagamentos!$D:$D,K$2) -> 0 | L86: =SUMIFS(Pagamentos!$E:$E,Pagamentos!$F:$F,TRUE,Pagamentos!$C:$C,$C86,Pagamentos!$D:$D,L$2) -> 0 | ... P86: =SUMIFS(Pagamentos!$E:$E,Pagamentos!$F:$F,TRUE,Pagamentos!$C:$C,$C86,Pagamentos!$D:$D,P$2) -> 0 | R86: =IF(Q86="","",((SUM(E86:P86)-$S$2)/20)+Q86) | S86: =IFERROR(__xludf.DUMMYFUNCTION("SPARKLINE(SUM(E86:P86),{""charttype"",""bar"";""max"",$S$2})"),"")
B87: {=IFERROR(INDEX(#REF!,MATCH(C87,#REF!,0)),"")} | E87: =SUMIFS(Pagamentos!$E:$E,Pagamentos!$F:$F,TRUE,Pagamentos!$C:$C,$C87,Pagamentos!$D:$D,E$2) -> 0 | F87: =SUMIFS(Pagamentos!$E:$E,Pagamentos!$F:$F,TRUE,Pagamentos!$C:$C,$C87,Pagamentos!$D:$D,F$2) -> 0 | G87: =SUMIFS(Pagamentos!$E:$E,Pagamentos!$F:$F,TRUE,Pagamentos!$C:$C,$C87,Pagamentos!$D:$D,G$2) -> 0 | H87: =SUMIFS(Pagamentos!$E:$E,Pagamentos!$F:$F,TRUE,Pagamentos!$C:$C,$C87,Pagamentos!$D:$D,H$2) -> 0 | I87: =SUMIFS(Pagamentos!$E:$E,Pagamentos!$F:$F,TRUE,Pagamentos!$C:$C,$C87,Pagamentos!$D:$D,I$2) -> 0 | J87: =SUMIFS(Pagamentos!$E:$E,Pagamentos!$F:$F,TRUE,Pagamentos!$C:$C,$C87,Pagamentos!$D:$D,J$2) -> 0 | K87: =SUMIFS(Pagamentos!$E:$E,Pagamentos!$F:$F,TRUE,Pagamentos!$C:$C,$C87,Pagamentos!$D:$D,K$2) -> 0 | L87: =SUMIFS(Pagamentos!$E:$E,Pagamentos!$F:$F,TRUE,Pagamentos!$C:$C,$C87,Pagamentos!$D:$D,L$2) -> 0 | ... P87: =SUMIFS(Pagamentos!$E:$E,Pagamentos!$F:$F,TRUE,Pagamentos!$C:$C,$C87,Pagamentos!$D:$D,P$2) -> 0 | R87: =IF(Q87="","",((SUM(E87:P87)-$S$2)/20)+Q87) | S87: =IFERROR(__xludf.DUMMYFUNCTION("SPARKLINE(SUM(E87:P87),{""charttype"",""bar"";""max"",$S$2})"),"")
B88: {=IFERROR(INDEX(#REF!,MATCH(C88,#REF!,0)),"")} | E88: =SUMIFS(Pagamentos!$E:$E,Pagamentos!$F:$F,TRUE,Pagamentos!$C:$C,$C88,Pagamentos!$D:$D,E$2) -> 0 | F88: =SUMIFS(Pagamentos!$E:$E,Pagamentos!$F:$F,TRUE,Pagamentos!$C:$C,$C88,Pagamentos!$D:$D,F$2) -> 0 | G88: =SUMIFS(Pagamentos!$E:$E,Pagamentos!$F:$F,TRUE,Pagamentos!$C:$C,$C88,Pagamentos!$D:$D,G$2) -> 0 | H88: =SUMIFS(Pagamentos!$E:$E,Pagamentos!$F:$F,TRUE,Pagamentos!$C:$C,$C88,Pagamentos!$D:$D,H$2) -> 0 | I88: =SUMIFS(Pagamentos!$E:$E,Pagamentos!$F:$F,TRUE,Pagamentos!$C:$C,$C88,Pagamentos!$D:$D,I$2) -> 0 | J88: =SUMIFS(Pagamentos!$E:$E,Pagamentos!$F:$F,TRUE,Pagamentos!$C:$C,$C88,Pagamentos!$D:$D,J$2) -> 0 | K88: =SUMIFS(Pagamentos!$E:$E,Pagamentos!$F:$F,TRUE,Pagamentos!$C:$C,$C88,Pagamentos!$D:$D,K$2) -> 0 | L88: =SUMIFS(Pagamentos!$E:$E,Pagamentos!$F:$F,TRUE,Pagamentos!$C:$C,$C88,Pagamentos!$D:$D,L$2) -> 0 | ... P88: =SUMIFS(Pagamentos!$E:$E,Pagamentos!$F:$F,TRUE,Pagamentos!$C:$C,$C88,Pagamentos!$D:$D,P$2) -> 0 | R88: =IF(Q88="","",((SUM(E88:P88)-$S$2)/20)+Q88) | S88: =IFERROR(__xludf.DUMMYFUNCTION("SPARKLINE(SUM(E88:P88),{""charttype"",""bar"";""max"",$S$2})"),"")
B89: {=IFERROR(INDEX(#REF!,MATCH(C89,#REF!,0)),"")} | E89: =SUMIFS(Pagamentos!$E:$E,Pagamentos!$F:$F,TRUE,Pagamentos!$C:$C,$C89,Pagamentos!$D:$D,E$2) -> 0 | F89: =SUMIFS(Pagamentos!$E:$E,Pagamentos!$F:$F,TRUE,Pagamentos!$C:$C,$C89,Pagamentos!$D:$D,F$2) -> 0 | G89: =SUMIFS(Pagamentos!$E:$E,Pagamentos!$F:$F,TRUE,Pagamentos!$C:$C,$C89,Pagamentos!$D:$D,G$2) -> 0 | H89: =SUMIFS(Pagamentos!$E:$E,Pagamentos!$F:$F,TRUE,Pagamentos!$C:$C,$C89,Pagamentos!$D:$D,H$2) -> 0 | I89: =SUMIFS(Pagamentos!$E:$E,Pagamentos!$F:$F,TRUE,Pagamentos!$C:$C,$C89,Pagamentos!$D:$D,I$2) -> 0 | J89: =SUMIFS(Pagamentos!$E:$E,Pagamentos!$F:$F,TRUE,Pagamentos!$C:$C,$C89,Pagamentos!$D:$D,J$2) -> 0 | K89: =SUMIFS(Pagamentos!$E:$E,Pagamentos!$F:$F,TRUE,Pagamentos!$C:$C,$C89,Pagamentos!$D:$D,K$2) -> 0 | L89: =SUMIFS(Pagamentos!$E:$E,Pagamentos!$F:$F,TRUE,Pagamentos!$C:$C,$C89,Pagamentos!$D:$D,L$2) -> 0 | ... P89: =SUMIFS(Pagamentos!$E:$E,Pagamentos!$F:$F,TRUE,Pagamentos!$C:$C,$C89,Pagamentos!$D:$D,P$2) -> 0 | R89: =IF(Q89="","",((SUM(E89:P89)-$S$2)/20)+Q89) | S89: =IFERROR(__xludf.DUMMYFUNCTION("SPARKLINE(SUM(E89:P89),{""charttype"",""bar"";""max"",$S$2})"),"")
B90: {=IFERROR(INDEX(#REF!,MATCH(C90,#REF!,0)),"")} | E90: =SUMIFS(Pagamentos!$E:$E,Pagamentos!$F:$F,TRUE,Pagamentos!$C:$C,$C90,Pagamentos!$D:$D,E$2) -> 0 | F90: =SUMIFS(Pagamentos!$E:$E,Pagamentos!$F:$F,TRUE,Pagamentos!$C:$C,$C90,Pagamentos!$D:$D,F$2) -> 0 | G90: =SUMIFS(Pagamentos!$E:$E,Pagamentos!$F:$F,TRUE,Pagamentos!$C:$C,$C90,Pagamentos!$D:$D,G$2) -> 0 | H90: =SUMIFS(Pagamentos!$E:$E,Pagamentos!$F:$F,TRUE,Pagamentos!$C:$C,$C90,Pagamentos!$D:$D,H$2) -> 0 | I90: =SUMIFS(Pagamentos!$E:$E,Pagamentos!$F:$F,TRUE,Pagamentos!$C:$C,$C90,Pagamentos!$D:$D,I$2) -> 0 | J90: =SUMIFS(Pagamentos!$E:$E,Pagamentos!$F:$F,TRUE,Pagamentos!$C:$C,$C90,Pagamentos!$D:$D,J$2) -> 0 | K90: =SUMIFS(Pagamentos!$E:$E,Pagamentos!$F:$F,TRUE,Pagamentos!$C:$C,$C90,Pagamentos!$D:$D,K$2) -> 0 | L90: =SUMIFS(Pagamentos!$E:$E,Pagamentos!$F:$F,TRUE,Pagamentos!$C:$C,$C90,Pagamentos!$D:$D,L$2) -> 0 | ... P90: =SUMIFS(Pagamentos!$E:$E,Pagamentos!$F:$F,TRUE,Pagamentos!$C:$C,$C90,Pagamentos!$D:$D,P$2) -> 0 | R90: =IF(Q90="","",((SUM(E90:P90)-$S$2)/20)+Q90) | S90: =IFERROR(__xludf.DUMMYFUNCTION("SPARKLINE(SUM(E90:P90),{""charttype"",""bar"";""max"",$S$2})"),"")
B91: {=IFERROR(INDEX(#REF!,MATCH(C91,#REF!,0)),"")} | E91: =SUMIFS(Pagamentos!$E:$E,Pagamentos!$F:$F,TRUE,Pagamentos!$C:$C,$C91,Pagamentos!$D:$D,E$2) -> 0 | F91: =SUMIFS(Pagamentos!$E:$E,Pagamentos!$F:$F,TRUE,Pagamentos!$C:$C,$C91,Pagamentos!$D:$D,F$2) -> 0 | G91: =SUMIFS(Pagamentos!$E:$E,Pagamentos!$F:$F,TRUE,Pagamentos!$C:$C,$C91,Pagamentos!$D:$D,G$2) -> 0 | H91: =SUMIFS(Pagamentos!$E:$E,Pagamentos!$F:$F,TRUE,Pagamentos!$C:$C,$C91,Pagamentos!$D:$D,H$2) -> 0 | I91: =SUMIFS(Pagamentos!$E:$E,Pagamentos!$F:$F,TRUE,Pagamentos!$C:$C,$C91,Pagamentos!$D:$D,I$2) -> 0 | J91: =SUMIFS(Pagamentos!$E:$E,Pagamentos!$F:$F,TRUE,Pagamentos!$C:$C,$C91,Pagamentos!$D:$D,J$2) -> 0 | K91: =SUMIFS(Pagamentos!$E:$E,Pagamentos!$F:$F,TRUE,Pagamentos!$C:$C,$C91,Pagamentos!$D:$D,K$2) -> 0 | L91: =SUMIFS(Pagamentos!$E:$E,Pagamentos!$F:$F,TRUE,Pagamentos!$C:$C,$C91,Pagamentos!$D:$D,L$2) -> 0 | ... P91: =SUMIFS(Pagamentos!$E:$E,Pagamentos!$F:$F,TRUE,Pagamentos!$C:$C,$C91,Pagamentos!$D:$D,P$2) -> 0 | R91: =IF(Q91="","",((SUM(E91:P91)-$S$2)/20)+Q91) | S91: =IFERROR(__xludf.DUMMYFUNCTION("SPARKLINE(SUM(E91:P91),{""charttype"",""bar"";""max"",$S$2})"),"")
B92: {=IFERROR(INDEX(#REF!,MATCH(C92,#REF!,0)),"")} | E92: =SUMIFS(Pagamentos!$E:$E,Pagamentos!$F:$F,TRUE,Pagamentos!$C:$C,$C92,Pagamentos!$D:$D,E$2) -> 0 | F92: =SUMIFS(Pagamentos!$E:$E,Pagamentos!$F:$F,TRUE,Pagamentos!$C:$C,$C92,Pagamentos!$D:$D,F$2) -> 0 | G92: =SUMIFS(Pagamentos!$E:$E,Pagamentos!$F:$F,TRUE,Pagamentos!$C:$C,$C92,Pagamentos!$D:$D,G$2) -> 0 | H92: =SUMIFS(Pagamentos!$E:$E,Pagamentos!$F:$F,TRUE,Pagamentos!$C:$C,$C92,Pagamentos!$D:$D,H$2) -> 0 | I92: =SUMIFS(Pagamentos!$E:$E,Pagamentos!$F:$F,TRUE,Pagamentos!$C:$C,$C92,Pagamentos!$D:$D,I$2) -> 0 | J92: =SUMIFS(Pagamentos!$E:$E,Pagamentos!$F:$F,TRUE,Pagamentos!$C:$C,$C92,Pagamentos!$D:$D,J$2) -> 0 | K92: =SUMIFS(Pagamentos!$E:$E,Pagamentos!$F:$F,TRUE,Pagamentos!$C:$C,$C92,Pagamentos!$D:$D,K$2) -> 0 | L92: =SUMIFS(Pagamentos!$E:$E,Pagamentos!$F:$F,TRUE,Pagamentos!$C:$C,$C92,Pagamentos!$D:$D,L$2) -> 0 | ... P92: =SUMIFS(Pagamentos!$E:$E,Pagamentos!$F:$F,TRUE,Pagamentos!$C:$C,$C92,Pagamentos!$D:$D,P$2) -> 0 | R92: =IF(Q92="","",((SUM(E92:P92)-$S$2)/20)+Q92) | S92: =IFERROR(__xludf.DUMMYFUNCTION("SPARKLINE(SUM(E92:P92),{""charttype"",""bar"";""max"",$S$2})"),"")
B93: {=IFERROR(INDEX(#REF!,MATCH(C93,#REF!,0)),"")} | E93: =SUMIFS(Pagamentos!$E:$E,Pagamentos!$F:$F,TRUE,Pagamentos!$C:$C,$C93,Pagamentos!$D:$D,E$2) -> 0 | F93: =SUMIFS(Pagamentos!$E:$E,Pagamentos!$F:$F,TRUE,Pagamentos!$C:$C,$C93,Pagamentos!$D:$D,F$2) -> 0 | G93: =SUMIFS(Pagamentos!$E:$E,Pagamentos!$F:$F,TRUE,Pagamentos!$C:$C,$C93,Pagamentos!$D:$D,G$2) -> 0 | H93: =SUMIFS(Pagamentos!$E:$E,Pagamentos!$F:$F,TRUE,Pagamentos!$C:$C,$C93,Pagamentos!$D:$D,H$2) -> 0 | I93: =SUMIFS(Pagamentos!$E:$E,Pagamentos!$F:$F,TRUE,Pagamentos!$C:$C,$C93,Pagamentos!$D:$D,I$2) -> 0 | J93: =SUMIFS(Pagamentos!$E:$E,Pagamentos!$F:$F,TRUE,Pagamentos!$C:$C,$C93,Pagamentos!$D:$D,J$2) -> 0 | K93: =SUMIFS(Pagamentos!$E:$E,Pagamentos!$F:$F,TRUE,Pagamentos!$C:$C,$C93,Pagamentos!$D:$D,K$2) -> 0 | L93: =SUMIFS(Pagamentos!$E:$E,Pagamentos!$F:$F,TRUE,Pagamentos!$C:$C,$C93,Pagamentos!$D:$D,L$2) -> 0 | ... P93: =SUMIFS(Pagamentos!$E:$E,Pagamentos!$F:$F,TRUE,Pagamentos!$C:$C,$C93,Pagamentos!$D:$D,P$2) -> 0 | R93: =IF(Q93="","",((SUM(E93:P93)-$S$2)/20)+Q93) | S93: =IFERROR(__xludf.DUMMYFUNCTION("SPARKLINE(SUM(E93:P93),{""charttype"",""bar"";""max"",$S$2})"),"")
B94: {=IFERROR(INDEX(#REF!,MATCH(C94,#REF!,0)),"")} | E94: =SUMIFS(Pagamentos!$E:$E,Pagamentos!$F:$F,TRUE,Pagamentos!$C:$C,$C94,Pagamentos!$D:$D,E$2) -> 0 | F94: =SUMIFS(Pagamentos!$E:$E,Pagamentos!$F:$F,TRUE,Pagamentos!$C:$C,$C94,Pagamentos!$D:$D,F$2) -> 0 | G94: =SUMIFS(Pagamentos!$E:$E,Pagamentos!$F:$F,TRUE,Pagamentos!$C:$C,$C94,Pagamentos!$D:$D,G$2) -> 0 | H94: =SUMIFS(Pagamentos!$E:$E,Pagamentos!$F:$F,TRUE,Pagamentos!$C:$C,$C94,Pagamentos!$D:$D,H$2) -> 0 | I94: =SUMIFS(Pagamentos!$E:$E,Pagamentos!$F:$F,TRUE,Pagamentos!$C:$C,$C94,Pagamentos!$D:$D,I$2) -> 0 | J94: =SUMIFS(Pagamentos!$E:$E,Pagamentos!$F:$F,TRUE,Pagamentos!$C:$C,$C94,Pagamentos!$D:$D,J$2) -> 0 | K94: =SUMIFS(Pagamentos!$E:$E,Pagamentos!$F:$F,TRUE,Pagamentos!$C:$C,$C94,Pagamentos!$D:$D,K$2) -> 0 | L94: =SUMIFS(Pagamentos!$E:$E,Pagamentos!$F:$F,TRUE,Pagamentos!$C:$C,$C94,Pagamentos!$D:$D,L$2) -> 0 | ... P94: =SUMIFS(Pagamentos!$E:$E,Pagamentos!$F:$F,TRUE,Pagamentos!$C:$C,$C94,Pagamentos!$D:$D,P$2) -> 0 | R94: =IF(Q94="","",((SUM(E94:P94)-$S$2)/20)+Q94) | S94: =IFERROR(__xludf.DUMMYFUNCTION("SPARKLINE(SUM(E94:P94),{""charttype"",""bar"";""max"",$S$2})"),"")
B95: {=IFERROR(INDEX(#REF!,MATCH(C95,#REF!,0)),"")} | E95: =SUMIFS(Pagamentos!$E:$E,Pagamentos!$F:$F,TRUE,Pagamentos!$C:$C,$C95,Pagamentos!$D:$D,E$2) -> 0 | F95: =SUMIFS(Pagamentos!$E:$E,Pagamentos!$F:$F,TRUE,Pagamentos!$C:$C,$C95,Pagamentos!$D:$D,F$2) -> 0 | G95: =SUMIFS(Pagamentos!$E:$E,Pagamentos!$F:$F,TRUE,Pagamentos!$C:$C,$C95,Pagamentos!$D:$D,G$2) -> 0 | H95: =SUMIFS(Pagamentos!$E:$E,Pagamentos!$F:$F,TRUE,Pagamentos!$C:$C,$C95,Pagamentos!$D:$D,H$2) -> 0 | I95: =SUMIFS(Pagamentos!$E:$E,Pagamentos!$F:$F,TRUE,Pagamentos!$C:$C,$C95,Pagamentos!$D:$D,I$2) -> 0 | J95: =SUMIFS(Pagamentos!$E:$E,Pagamentos!$F:$F,TRUE,Pagamentos!$C:$C,$C95,Pagamentos!$D:$D,J$2) -> 0 | K95: =SUMIFS(Pagamentos!$E:$E,Pagamentos!$F:$F,TRUE,Pagamentos!$C:$C,$C95,Pagamentos!$D:$D,K$2) -> 0 | L95: =SUMIFS(Pagamentos!$E:$E,Pagamentos!$F:$F,TRUE,Pagamentos!$C:$C,$C95,Pagamentos!$D:$D,L$2) -> 0 | ... P95: =SUMIFS(Pagamentos!$E:$E,Pagamentos!$F:$F,TRUE,Pagamentos!$C:$C,$C95,Pagamentos!$D:$D,P$2) -> 0 | R95: =IF(Q95="","",((SUM(E95:P95)-$S$2)/20)+Q95) | S95: =IFERROR(__xludf.DUMMYFUNCTION("SPARKLINE(SUM(E95:P95),{""charttype"",""bar"";""max"",$S$2})"),"")
B96: {=IFERROR(INDEX(#REF!,MATCH(C96,#REF!,0)),"")} | E96: =SUMIFS(Pagamentos!$E:$E,Pagamentos!$F:$F,TRUE,Pagamentos!$C:$C,$C96,Pagamentos!$D:$D,E$2) -> 0 | F96: =SUMIFS(Pagamentos!$E:$E,Pagamentos!$F:$F,TRUE,Pagamentos!$C:$C,$C96,Pagamentos!$D:$D,F$2) -> 0 | G96: =SUMIFS(Pagamentos!$E:$E,Pagamentos!$F:$F,TRUE,Pagamentos!$C:$C,$C96,Pagamentos!$D:$D,G$2) -> 0 | H96: =SUMIFS(Pagamentos!$E:$E,Pagamentos!$F:$F,TRUE,Pagamentos!$C:$C,$C96,Pagamentos!$D:$D,H$2) -> 0 | I96: =SUMIFS(Pagamentos!$E:$E,Pagamentos!$F:$F,TRUE,Pagamentos!$C:$C,$C96,Pagamentos!$D:$D,I$2) -> 0 | J96: =SUMIFS(Pagamentos!$E:$E,Pagamentos!$F:$F,TRUE,Pagamentos!$C:$C,$C96,Pagamentos!$D:$D,J$2) -> 0 | K96: =SUMIFS(Pagamentos!$E:$E,Pagamentos!$F:$F,TRUE,Pagamentos!$C:$C,$C96,Pagamentos!$D:$D,K$2) -> 0 | L96: =SUMIFS(Pagamentos!$E:$E,Pagamentos!$F:$F,TRUE,Pagamentos!$C:$C,$C96,Pagamentos!$D:$D,L$2) -> 0 | ... P96: =SUMIFS(Pagamentos!$E:$E,Pagamentos!$F:$F,TRUE,Pagamentos!$C:$C,$C96,Pagamentos!$D:$D,P$2) -> 0 | R96: =IF(Q96="","",((SUM(E96:P96)-$S$2)/20)+Q96) | S96: =IFERROR(__xludf.DUMMYFUNCTION("SPARKLINE(SUM(E96:P96),{""charttype"",""bar"";""max"",$S$2})"),"")
B97: {=IFERROR(INDEX(#REF!,MATCH(C97,#REF!,0)),"")} | E97: =SUMIFS(Pagamentos!$E:$E,Pagamentos!$F:$F,TRUE,Pagamentos!$C:$C,$C97,Pagamentos!$D:$D,E$2) -> 0 | F97: =SUMIFS(Pagamentos!$E:$E,Pagamentos!$F:$F,TRUE,Pagamentos!$C:$C,$C97,Pagamentos!$D:$D,F$2) -> 0 | G97: =SUMIFS(Pagamentos!$E:$E,Pagamentos!$F:$F,TRUE,Pagamentos!$C:$C,$C97,Pagamentos!$D:$D,G$2) -> 0 | H97: =SUMIFS(Pagamentos!$E:$E,Pagamentos!$F:$F,TRUE,Pagamentos!$C:$C,$C97,Pagamentos!$D:$D,H$2) -> 0 | I97: =SUMIFS(Pagamentos!$E:$E,Pagamentos!$F:$F,TRUE,Pagamentos!$C:$C,$C97,Pagamentos!$D:$D,I$2) -> 0 | J97: =SUMIFS(Pagamentos!$E:$E,Pagamentos!$F:$F,TRUE,Pagamentos!$C:$C,$C97,Pagamentos!$D:$D,J$2) -> 0 | K97: =SUMIFS(Pagamentos!$E:$E,Pagamentos!$F:$F,TRUE,Pagamentos!$C:$C,$C97,Pagamentos!$D:$D,K$2) -> 0 | L97: =SUMIFS(Pagamentos!$E:$E,Pagamentos!$F:$F,TRUE,Pagamentos!$C:$C,$C97,Pagamentos!$D:$D,L$2) -> 0 | ... P97: =SUMIFS(Pagamentos!$E:$E,Pagamentos!$F:$F,TRUE,Pagamentos!$C:$C,$C97,Pagamentos!$D:$D,P$2) -> 0 | R97: =IF(Q97="","",((SUM(E97:P97)-$S$2)/20)+Q97) | S97: =IFERROR(__xludf.DUMMYFUNCTION("SPARKLINE(SUM(E97:P97),{""charttype"",""bar"";""max"",$S$2})"),"")
B98: {=IFERROR(INDEX(#REF!,MATCH(C98,#REF!,0)),"")} | E98: =SUMIFS(Pagamentos!$E:$E,Pagamentos!$F:$F,TRUE,Pagamentos!$C:$C,$C98,Pagamentos!$D:$D,E$2) -> 0 | F98: =SUMIFS(Pagamentos!$E:$E,Pagamentos!$F:$F,TRUE,Pagamentos!$C:$C,$C98,Pagamentos!$D:$D,F$2) -> 0 | G98: =SUMIFS(Pagamentos!$E:$E,Pagamentos!$F:$F,TRUE,Pagamentos!$C:$C,$C98,Pagamentos!$D:$D,G$2) -> 0 | H98: =SUMIFS(Pagamentos!$E:$E,Pagamentos!$F:$F,TRUE,Pagamentos!$C:$C,$C98,Pagamentos!$D:$D,H$2) -> 0 | I98: =SUMIFS(Pagamentos!$E:$E,Pagamentos!$F:$F,TRUE,Pagamentos!$C:$C,$C98,Pagamentos!$D:$D,I$2) -> 0 | J98: =SUMIFS(Pagamentos!$E:$E,Pagamentos!$F:$F,TRUE,Pagamentos!$C:$C,$C98,Pagamentos!$D:$D,J$2) -> 0 | K98: =SUMIFS(Pagamentos!$E:$E,Pagamentos!$F:$F,TRUE,Pagamentos!$C:$C,$C98,Pagamentos!$D:$D,K$2) -> 0 | L98: =SUMIFS(Pagamentos!$E:$E,Pagamentos!$F:$F,TRUE,Pagamentos!$C:$C,$C98,Pagamentos!$D:$D,L$2) -> 0 | ... P98: =SUMIFS(Pagamentos!$E:$E,Pagamentos!$F:$F,TRUE,Pagamentos!$C:$C,$C98,Pagamentos!$D:$D,P$2) -> 0 | R98: =IF(Q98="","",((SUM(E98:P98)-$S$2)/20)+Q98) | S98: =IFERROR(__xludf.DUMMYFUNCTION("SPARKLINE(SUM(E98:P98),{""charttype"",""bar"";""max"",$S$2})"),"")
B99: {=IFERROR(INDEX(#REF!,MATCH(C99,#REF!,0)),"")} | E99: =SUMIFS(Pagamentos!$E:$E,Pagamentos!$F:$F,TRUE,Pagamentos!$C:$C,$C99,Pagamentos!$D:$D,E$2) -> 0 | F99: =SUMIFS(Pagamentos!$E:$E,Pagamentos!$F:$F,TRUE,Pagamentos!$C:$C,$C99,Pagamentos!$D:$D,F$2) -> 0 | G99: =SUMIFS(Pagamentos!$E:$E,Pagamentos!$F:$F,TRUE,Pagamentos!$C:$C,$C99,Pagamentos!$D:$D,G$2) -> 0 | H99: =SUMIFS(Pagamentos!$E:$E,Pagamentos!$F:$F,TRUE,Pagamentos!$C:$C,$C99,Pagamentos!$D:$D,H$2) -> 0 | I99: =SUMIFS(Pagamentos!$E:$E,Pagamentos!$F:$F,TRUE,Pagamentos!$C:$C,$C99,Pagamentos!$D:$D,I$2) -> 0 | J99: =SUMIFS(Pagamentos!$E:$E,Pagamentos!$F:$F,TRUE,Pagamentos!$C:$C,$C99,Pagamentos!$D:$D,J$2) -> 0 | K99: =SUMIFS(Pagamentos!$E:$E,Pagamentos!$F:$F,TRUE,Pagamentos!$C:$C,$C99,Pagamentos!$D:$D,K$2) -> 0 | L99: =SUMIFS(Pagamentos!$E:$E,Pagamentos!$F:$F,TRUE,Pagamentos!$C:$C,$C99,Pagamentos!$D:$D,L$2) -> 0 | ... P99: =SUMIFS(Pagamentos!$E:$E,Pagamentos!$F:$F,TRUE,Pagamentos!$C:$C,$C99,Pagamentos!$D:$D,P$2) -> 0 | R99: =IF(Q99="","",((SUM(E99:P99)-$S$2)/20)+Q99) | S99: =IFERROR(__xludf.DUMMYFUNCTION("SPARKLINE(SUM(E99:P99),{""charttype"",""bar"";""max"",$S$2})"),"")
B100: {=IFERROR(INDEX(#REF!,MATCH(C100,#REF!,0)),"")} | E100: =SUMIFS(Pagamentos!$E:$E,Pagamentos!$F:$F,TRUE,Pagamentos!$C:$C,$C100,Pagamentos!$D:$D,E$2) -> 0 | F100: =SUMIFS(Pagamentos!$E:$E,Pagamentos!$F:$F,TRUE,Pagamentos!$C:$C,$C100,Pagamentos!$D:$D,F$2) -> 0 | G100: =SUMIFS(Pagamentos!$E:$E,Pagamentos!$F:$F,TRUE,Pagamentos!$C:$C,$C100,Pagamentos!$D:$D,G$2) -> 0 | H100: =SUMIFS(Pagamentos!$E:$E,Pagamentos!$F:$F,TRUE,Pagamentos!$C:$C,$C100,Pagamentos!$D:$D,H$2) -> 0 | I100: =SUMIFS(Pagamentos!$E:$E,Pagamentos!$F:$F,TRUE,Pagamentos!$C:$C,$C100,Pagamentos!$D:$D,I$2) -> 0 | J100: =SUMIFS(Pagamentos!$E:$E,Pagamentos!$F:$F,TRUE,Pagamentos!$C:$C,$C100,Pagamentos!$D:$D,J$2) -> 0 | K100: =SUMIFS(Pagamentos!$E:$E,Pagamentos!$F:$F,TRUE,Pagamentos!$C:$C,$C100,Pagamentos!$D:$D,K$2) -> 0 | L100: =SUMIFS(Pagamentos!$E:$E,Pagamentos!$F:$F,TRUE,Pagamentos!$C:$C,$C100,Pagamentos!$D:$D,L$2) -> 0 | ... P100: =SUMIFS(Pagamentos!$E:$E,Pagamentos!$F:$F,TRUE,Pagamentos!$C:$C,$C100,Pagamentos!$D:$D,P$2) -> 0 | R100: =IF(Q100="","",((SUM(E100:P100)-$S$2)/20)+Q100) | S100: =IFERROR(__xludf.DUMMYFUNCTION("SPARKLINE(SUM(E100:P100),{""charttype"",""bar"";""max"",$S$2})"),"")
...

Sheet Lançamentos
B1: Descritivo | C1: Despesa | D1: Receita | E1: Valor | F1: Data | G1: Mês | H1: Mês
B2: Taxa "Cesta de Relacionamento" Sicred | C2: Tarifas Banco | E2: 35 | F2: 46042 | G2: =IF(F2="","",MONTH(F2)) -> 1 | H2: {=IF(F2="","",INDEX(Cripto!$A$1:$A$12,G2))} -> Janeiro
B3: Sandro Martins (Copo B4 / FECABOM) | C3: Outros | E3: 50 | F3: 46048 | G3: =IF(F3="","",MONTH(F3)) -> 1 | H3: {=IF(F3="","",INDEX(Cripto!$A$1:$A$12,G3))} -> Janeiro
B4: Tarifas Caixa Economica Federal | C4: Tarifas Banco | E4: 0.17 | F4: 46053 | G4: =IF(F4="","",MONTH(F4)) -> 1 | H4: {=IF(F4="","",INDEX(Cripto!$A$1:$A$12,G4))} -> Janeiro
B5: Rendimentos Caixa Economica Federal | D5: Rendimentos | E5: =0.3+0.1 -> 0.4 | F5: 46053 | G5: =IF(F5="","",MONTH(F5)) -> 1 | H5: {=IF(F5="","",INDEX(Cripto!$A$1:$A$12,G5))} -> Janeiro
B6: Certificado Digital | C6: Outros | E6: 170 | F6: 46062 | G6: =IF(F6="","",MONTH(F6)) -> 2 | H6: {=IF(F6="","",INDEX(Cripto!$A$1:$A$12,G6))} -> Fevereiro
B7: Brinde Reunião Comando (Camila C Soares) | C7: Presentes | E7: 47.61 | F7: 46073 | G7: =IF(F7="","",MONTH(F7)) -> 2 | H7: {=IF(F7="","",INDEX(Cripto!$A$1:$A$12,G7))} -> Fevereiro
B8: Taxa "Cesta de Relacionamento" Sicred | C8: Tarifas Banco | E8: 35 | F8: 46073 | G8: =IF(F8="","",MONTH(F8)) -> 2 | H8: {=IF(F8="","",INDEX(Cripto!$A$1:$A$12,G8))} -> Fevereiro
B9: Lancheira aniversários Compra 1 | C9: Presentes | E9: 1945 | F9: 46076 | G9: =IF(F9="","",MONTH(F9)) -> 2 | H9: {=IF(F9="","",INDEX(Cripto!$A$1:$A$12,G9))} -> Fevereiro
B10: Lancheira aniversários Compra 2 | C10: Presentes | E10: 775.8 | F10: 46076 | G10: =IF(F10="","",MONTH(F10)) -> 2 | H10: {=IF(F10="","",INDEX(Cripto!$A$1:$A$12,G10))} -> Fevereiro
B11: Tarifas Caixa Economica Federal | C11: Tarifas Banco | E11: 0.17 | F11: 46081 | G11: =IF(F11="","",MONTH(F11)) -> 2 | H11: {=IF(F11="","",INDEX(Cripto!$A$1:$A$12,G11))} -> Fevereiro
B12: Rendimentos Caixa Economica Federal | D12: Rendimentos | E12: =SUM(0.14+0.4) -> 0.54 | F12: 46081 | G12: =IF(F12="","",MONTH(F12)) -> 2 | H12: {=IF(F12="","",INDEX(Cripto!$A$1:$A$12,G12))} -> Fevereiro
B13: Estampa das lancheiras (Adriano Lima) | C13: Presentes | E13: 800 | F13: 46093 | G13: =IF(F13="","",MONTH(F13)) -> 3 | H13: {=IF(F13="","",INDEX(Cripto!$A$1:$A$12,G13))} -> Março
B14: Taxa "Cesta de Relacionamento" Sicred | C14: Tarifas Banco | E14: 35 | F14: 46101 | G14: =IF(F14="","",MONTH(F14)) -> 3 | H14: {=IF(F14="","",INDEX(Cripto!$A$1:$A$12,G14))} -> Março
B15: Tarifas Caixa Economica Federal | C15: Tarifas Banco | E15: 0.88 | F15: 46111 | G15: =IF(F15="","",MONTH(F15)) -> 3 | H15: {=IF(F15="","",INDEX(Cripto!$A$1:$A$12,G15))} -> Março
B16: Rendimentos Caixa Economica Federal | D16: Rendimentos | E16: 0.62 | F16: 46111 | G16: =IF(F16="","",MONTH(F16)) -> 3 | H16: {=IF(F16="","",INDEX(Cripto!$A$1:$A$12,G16))} -> Março
B17: Coffee Break Treinamento APH (João Valdeci Moraes) | C17: Treinamentos | E17: 240 | F17: 46125 | G17: =IF(F17="","",MONTH(F17)) -> 4 | H17: {=IF(F17="","",INDEX(Cripto!$A$1:$A$12,G17))} -> Abril
B18: Coffee Break Treinamento APH (Camila Soares) | C18: Treinamentos | E18: 132.08 | F18: 46125 | G18: =IF(F18="","",MONTH(F18)) -> 4 | H18: {=IF(F18="","",INDEX(Cripto!$A$1:$A$12,G18))} -> Abril
B19: Taxa "Cesta de Relacionamento" Sicred | C19: Tarifas Banco | E19: 35 | F19: 46132 | G19: =IF(F19="","",MONTH(F19)) -> 4 | H19: {=IF(F19="","",INDEX(Cripto!$A$1:$A$12,G19))} -> Abril
B20: Cartório (Gabriel F.Farias) | C20: Cartório ou Documentação em geral | E20: 193.67 | F20: 46136 | G20: =IF(F20="","",MONTH(F20)) -> 4 | H20: {=IF(F20="","",INDEX(Cripto!$A$1:$A$12,G20))} -> Abril
B21: Rendimentos Caixa Economica Federal | D21: Rendimentos | E21: 1.34 | F21: 46142 | G21: =IF(F21="","",MONTH(F21)) -> 4 | H21: {=IF(F21="","",INDEX(Cripto!$A$1:$A$12,G21))} -> Abril
B22: Taxa "Cesta de Relacionamento" Sicred | C22: Tarifas Banco | E22: 35 | F22: 46162 | G22: =IF(F22="","",MONTH(F22)) -> 5 | H22: {=IF(F22="","",INDEX(Cripto!$A$1:$A$12,G22))} -> Maio
B23: Rendimentos SICREDI | D23: Rendimentos | E23: 11.31 | F23: 46146 | G23: =IF(F23="","",MONTH(F23)) -> 5 | H23: {=IF(F23="","",INDEX(Cripto!$A$1:$A$12,G23))} -> Maio
B24: Rendimentos Caixa Economica Federal | D24: Rendimentos | E24: =0.1+0.02+0.1+0.03+0.41+0.14+0.4+0.08 -> 1.28 | F24: 46173 | G24: =IF(F24="","",MONTH(F24)) -> 5 | H24: {=IF(F24="","",INDEX(Cripto!$A$1:$A$12,G24))} -> Maio
B25: Jogo Copa do Mundo - Acompanhante (Linder) | D25: Rendimentos | E25: 25 | F25: 46184 | G25: =IF(F25="","",MONTH(F25)) -> 6 | H25: {=IF(F25="","",INDEX(Cripto!$A$1:$A$12,G25))} -> Junho
B26: Taxa de funcionamento PMSJ | C26: Cartório ou Documentação em geral | E26: 440.66 | F26: 46184 | G26: =IF(F26="","",MONTH(F26)) -> 6 | H26: {=IF(F26="","",INDEX(Cripto!$A$1:$A$12,G26))} -> Junho
B27: Certificado Digital (Safe2pay) | C27: Cartório ou Documentação em geral | E27: 184 | F27: 46184 | G27: =IF(F27="","",MONTH(F27)) -> 6 | H27: {=IF(F27="","",INDEX(Cripto!$A$1:$A$12,G27))} -> Junho
B28: jogo Copa do Mundo - Acompanhante (Antunes) | D28: Rendimentos | E28: 25 | F28: 46188 | G28: =IF(F28="","",MONTH(F28)) -> 6 | H28: {=IF(F28="","",INDEX(Cripto!$A$1:$A$12,G28))} -> Junho
B29: Jogo Copa do Mundo - Acompanhante (Humberto) | D29: Rendimentos | E29: 25 | F29: 46190 | G29: =IF(F29="","",MONTH(F29)) -> 6 | H29: {=IF(F29="","",INDEX(Cripto!$A$1:$A$12,G29))} -> Junho
B30: Decoração e descartaveis - Jogo Copa do Mundo (Yanka) | C30: Mercado | E30: 80.85 | F30: 46191 | G30: =IF(F30="","",MONTH(F30)) -> 6 | H30: {=IF(F30="","",INDEX(Cripto!$A$1:$A$12,G30))} -> Junho
B31: Mercado - Jogo Copa do Mundo (MundialMIX) | C31: Mercado | E31: 248.35 | F31: 46195 | G31: =IF(F31="","",MONTH(F31)) -> 6 | H31: {=IF(F31="","",INDEX(Cripto!$A$1:$A$12,G31))} -> Junho
B32: Mercado - Jogo Copa do Mundo (Yanka) | C32: Mercado | E32: 35.66 | F32: 46195 | G32: =IF(F32="","",MONTH(F32)) -> 6 | H32: {=IF(F32="","",INDEX(Cripto!$A$1:$A$12,G32))} -> Junho
B33: Taxa "Cesta de Relacionamento" Sicred | C33: Tarifas Banco | E33: 35 | F33: 46195 | G33: =IF(F33="","",MONTH(F33)) -> 6 | H33: {=IF(F33="","",INDEX(Cripto!$A$1:$A$12,G33))} -> Junho
B34: Pães - Jogo Copa do Mundo (Industria de Paes) | C34: Mercado | E34: 36 | F34: 46196 | G34: =IF(F34="","",MONTH(F34)) -> 6 | H34: {=IF(F34="","",INDEX(Cripto!$A$1:$A$12,G34))} -> Junho
B35: Jogo Copa do Mundo - Acompanhante (Kassandra) | D35: Rendimentos | E35: 25 | F35: 46197 | G35: =IF(F35="","",MONTH(F35)) -> 6 | H35: {=IF(F35="","",INDEX(Cripto!$A$1:$A$12,G35))} -> Junho
B36: Tarifas Caixa Economica Federal | C36: Tarifas Banco | E36: 0.71 | F36: 46203 | G36: =IF(F36="","",MONTH(F36)) -> 6 | H36: {=IF(F36="","",INDEX(Cripto!$A$1:$A$12,G36))} -> Junho
B37: Rendimentos Caixa Economica Federal | D37: Rendimentos | E37: =(0.1+0.03+0.1+0.03+0.41+0.14+0.4+0.14) -> 1.35 | F37: 46203 | G37: =IF(F37="","",MONTH(F37)) -> 6 | H37: {=IF(F37="","",INDEX(Cripto!$A$1:$A$12,G37))} -> Junho
B38: Coffee Break - Palestra (Kiko) | C38: Treinamentos | E38: 384 | F38: 46220 | G38: =IF(F38="","",MONTH(F38)) -> 7 | H38: {=IF(F38="","",INDEX(Cripto!$A$1:$A$12,G38))} -> Julho
B39: Taxa "Cesta de Relacionamento" Sicredi | C39: Tarifas Banco | E39: 35 | F39: 46223 | G39: =IF(F39="","",MONTH(F39)) -> 7 | H39: {=IF(F39="","",INDEX(Cripto!$A$1:$A$12,G39))} -> Julho
B40: Refri - Palestra (Yanka) | C40: Treinamentos | E40: 38.88 | F40: 46225 | G40: =IF(F40="","",MONTH(F40)) -> 7 | H40: {=IF(F40="","",INDEX(Cripto!$A$1:$A$12,G40))} -> Julho
B41: Chocolate Palestrante Sgt Reinaldo - Palestra (Camila) | C41: Treinamentos | E41: 19.93 | F41: 46230 | G41: =IF(F41="","",MONTH(F41)) -> 7 | H41: {=IF(F41="","",INDEX(Cripto!$A$1:$A$12,G41))} -> Julho
B42: Rendimentos Caixa Economica Federal | D42: Rendimentos | E42: 1.35 | F42: 46234 | G42: =IF(F42="","",MONTH(F42)) -> 7 | H42: {=IF(F42="","",INDEX(Cripto!$A$1:$A$12,G42))} -> Julho
G43: =IF(F43="","",MONTH(F43)) | H43: {=IF(F43="","",INDEX(Cripto!$A$1:$A$12,G43))}
G44: =IF(F44="","",MONTH(F44)) | H44: {=IF(F44="","",INDEX(Cripto!$A$1:$A$12,G44))}
G45: =IF(F45="","",MONTH(F45)) | H45: {=IF(F45="","",INDEX(Cripto!$A$1:$A$12,G45))}
G46: =IF(F46="","",MONTH(F46)) | H46: {=IF(F46="","",INDEX(Cripto!$A$1:$A$12,G46))}
G47: =IF(F47="","",MONTH(F47)) | H47: {=IF(F47="","",INDEX(Cripto!$A$1:$A$12,G47))}
G48: =IF(F48="","",MONTH(F48)) | H48: {=IF(F48="","",INDEX(Cripto!$A$1:$A$12,G48))}
G49: =IF(F49="","",MONTH(F49)) | H49: {=IF(F49="","",INDEX(Cripto!$A$1:$A$12,G49))}
G50: =IF(F50="","",MONTH(F50)) | H50: {=IF(F50="","",INDEX(Cripto!$A$1:$A$12,G50))}
G51: =IF(F51="","",MONTH(F51)) | H51: {=IF(F51="","",INDEX(Cripto!$A$1:$A$12,G51))}
G52: =IF(F52="","",MONTH(F52)) | H52: {=IF(F52="","",INDEX(Cripto!$A$1:$A$12,G52))}
G53: =IF(F53="","",MONTH(F53)) | H53: {=IF(F53="","",INDEX(Cripto!$A$1:$A$12,G53))}
G54: =IF(F54="","",MONTH(F54)) | H54: {=IF(F54="","",INDEX(Cripto!$A$1:$A$12,G54))}
... G1096: =IF(F1096="","",MONTH(F1096)) | H1096: {=IF(F1096="","",INDEX(Cripto!$A$1:$A$12,G1096))}

Sheet Pagamentos
B1: Controle de Pagamento de Mensalidade
B2: Carimbo de data/hora | C2: Nome de Guerra | D2: Mês | E2: Valor | F2: Confirmo que todos os processos de conferência do pagamento foram efetuados
B3: 46061 | C3: Lourenço | D3: Janeiro | E3: 20 | F3: TRUE
B4: 46061 | C4: Luiz | D4: Janeiro | E4: 20 | F4: TRUE
B5: 46061 | C5: Yuri | D5: Janeiro | E5: 20 | F5: TRUE
B6: 46061 | C6: Antunes | D6: janeiro | E6: 20 | F6: TRUE
B7: 46061 | C7: Siqueira | D7: janeiro | E7: 20 | F7: TRUE
B8: 46061 | C8: Camila | D8: janeiro | E8: 20 | F8: TRUE
B9: 46061 | C9: Yanka | D9: janeiro | E9: 20 | F9: TRUE
B10: 46061 | C10: Martins | D10: janeiro | E10: 20 | F10: TRUE
B11: 46061 | C11: Natayan | D11: janeiro | E11: 40 | F11: TRUE
B12: 46061 | C12: Augusto | D12: janeiro | E12: 20 | F12: TRUE
B13: 46061 | C13: Nakata | D13: janeiro | E13: 40 | F13: TRUE
B14: 46061 | C14: Neumann | D14: janeiro | E14: 20 | F14: TRUE
... B227: 46240 | C227: Andréia M | D227: Agosto | E227: 20 | F227: TRUE
F228: FALSE
F229: FALSE
F230: FALSE
F231: FALSE
F232: FALSE
F233: FALSE
F234: FALSE
F235: FALSE
F236: FALSE
F237: FALSE
F238: FALSE
F239: FALSE
... F1279: FALSE
